{".class":"MypyFile","_fullname":"cvxpy.atoms.affine.cumsum","future_import_flags":[],"is_partial_stub_package":false,"is_stub":false,"names":{".class":"SymbolTable","AffAtom":{".class":"SymbolTableNode","cross_ref":"cvxpy.atoms.affine.affine_atom.AffAtom","kind":"Gdef"},"AxisAtom":{".class":"SymbolTableNode","cross_ref":"cvxpy.atoms.axis_atom.AxisAtom","kind":"Gdef"},"Constraint":{".class":"SymbolTableNode","cross_ref":"cvxpy.constraints.constraint.Constraint","kind":"Gdef"},"Expression":{".class":"SymbolTableNode","cross_ref":"cvxpy.expressions.expression.Expression","kind":"Gdef"},"List":{".class":"SymbolTableNode","cross_ref":"typing.List","kind":"Gdef"},"MulExpression":{".class":"SymbolTableNode","cross_ref":"cvxpy.atoms.affine.binary_operators.MulExpression","kind":"Gdef"},"Tuple":{".class":"SymbolTableNode","cross_ref":"typing.Tuple","kind":"Gdef"},"Variable":{".class":"SymbolTableNode","cross_ref":"cvxpy.expressions.variable.Variable","kind":"Gdef"},"__annotations__":{".class":"SymbolTableNode","kind":"Gdef","node":{".class":"Var","flags":["is_ready"],"fullname":"cvxpy.atoms.affine.cumsum.__annotations__","name":"__annotations__","type":{".class":"Instance","args":["builtins.str",{".class":"AnyType","missing_import_name":null,"source_any":null,"type_of_any":6}],"extra_attrs":null,"type_ref":"builtins.dict"}}},"__doc__":{".class":"SymbolTableNode","kind":"Gdef","node":{".class":"Var","flags":["is_ready"],"fullname":"cvxpy.atoms.affine.cumsum.__doc__","name":"__doc__","type":"builtins.str"}},"__file__":{".class":"SymbolTableNode","kind":"Gdef","node":{".class":"Var","flags":["is_ready"],"fullname":"cvxpy.atoms.affine.cumsum.__file__","name":"__file__","type":"builtins.str"}},"__name__":{".class":"SymbolTableNode","kind":"Gdef","node":{".class":"Var","flags":["is_ready"],"fullname":"cvxpy.atoms.affine.cumsum.__name__","name":"__name__","type":"builtins.str"}},"__package__":{".class":"SymbolTableNode","kind":"Gdef","node":{".class":"Var","flags":["is_ready"],"fullname":"cvxpy.atoms.affine.cumsum.__package__","name":"__package__","type":"builtins.str"}},"__spec__":{".class":"SymbolTableNode","kind":"Gdef","node":{".class":"Var","flags":["is_ready"],"fullname":"cvxpy.atoms.affine.cumsum.__spec__","name":"__spec__","type":"_frozen_importlib.ModuleSpec"}},"cumsum":{".class":"SymbolTableNode","kind":"Gdef","node":{".class":"TypeInfo","_promote":[],"abstract_attributes":[],"alt_promote":null,"bases":["cvxpy.atoms.affine.affine_atom.AffAtom","cvxpy.atoms.axis_atom.AxisAtom"],"dataclass_transform_spec":null,"declared_metaclass":null,"defn":{".class":"ClassDef","fullname":"cvxpy.atoms.affine.cumsum.cumsum","name":"cumsum","type_vars":[]},"deletable_attributes":[],"deprecated":null,"flags":[],"fullname":"cvxpy.atoms.affine.cumsum.cumsum","has_param_spec_type":false,"metaclass_type":"abc.ABCMeta","metadata":{},"module_name":"cvxpy.atoms.affine.cumsum","mro":["cvxpy.atoms.affine.cumsum.cumsum","cvxpy.atoms.affine.affine_atom.AffAtom","cvxpy.atoms.axis_atom.AxisAtom","cvxpy.atoms.atom.Atom","cvxpy.expressions.expression.Expression","cvxpy.utilities.canonical.Canonical","builtins.object"],"names":{".class":"SymbolTable","__init__":{".class":"SymbolTableNode","kind":"Mdef","node":{".class":"FuncDef","abstract_status":0,"arg_kinds":[0,0,1],"arg_names":["self","expr","axis"],"dataclass_transform_spec":null,"deprecated":null,"flags":[],"fullname":"cvxpy.atoms.affine.cumsum.cumsum.__init__","name":"__init__","type":{".class":"CallableType","arg_kinds":[0,0,1],"arg_names":["self","expr","axis"],"arg_types":["cvxpy.atoms.affine.cumsum.cumsum","cvxpy.expressions.expression.Expression","builtins.int"],"bound_args":[],"def_extras":{"first_arg":"self"},"fallback":"builtins.function","from_concatenate":false,"implicit":false,"imprecise_arg_kinds":false,"is_ellipsis_args":false,"name":"__init__ of cumsum","ret_type":{".class":"NoneType"},"type_guard":null,"type_is":null,"unpack_kwargs":false,"variables":[]}}},"_grad":{".class":"SymbolTableNode","kind":"Mdef","node":{".class":"FuncDef","abstract_status":0,"arg_kinds":[0,0],"arg_names":["self","values"],"dataclass_transform_spec":null,"deprecated":null,"flags":[],"fullname":"cvxpy.atoms.affine.cumsum.cumsum._grad","name":"_grad","type":null}},"get_data":{".class":"SymbolTableNode","kind":"Mdef","node":{".class":"FuncDef","abstract_status":0,"arg_kinds":[0],"arg_names":["self"],"dataclass_transform_spec":null,"deprecated":null,"flags":[],"fullname":"cvxpy.atoms.affine.cumsum.cumsum.get_data","name":"get_data","type":null}},"graph_implementation":{".class":"SymbolTableNode","kind":"Mdef","node":{".class":"FuncDef","abstract_status":0,"arg_kinds":[0,0,0,1],"arg_names":["self","arg_objs","shape","data"],"dataclass_transform_spec":null,"deprecated":null,"flags":[],"fullname":"cvxpy.atoms.affine.cumsum.cumsum.graph_implementation","name":"graph_implementation","type":{".class":"CallableType","arg_kinds":[0,0,0,1],"arg_names":["self","arg_objs","shape","data"],"arg_types":["cvxpy.atoms.affine.cumsum.cumsum",{".class":"AnyType","missing_import_name":null,"source_any":null,"type_of_any":1},{".class":"Instance","args":["builtins.int"],"extra_attrs":null,"type_ref":"builtins.tuple"},{".class":"AnyType","missing_import_name":null,"source_any":null,"type_of_any":1}],"bound_args":[],"def_extras":{"first_arg":"self"},"fallback":"builtins.function","from_concatenate":false,"implicit":false,"imprecise_arg_kinds":false,"is_ellipsis_args":false,"name":"graph_implementation of cumsum","ret_type":{".class":"TupleType","implicit":false,"items":["cvxpy.lin_ops.lin_op.LinOp",{".class":"Instance","args":["cvxpy.constraints.constraint.Constraint"],"extra_attrs":null,"type_ref":"builtins.list"}],"partial_fallback":{".class":"Instance","args":[{".class":"AnyType","missing_import_name":null,"source_any":null,"type_of_any":6}],"extra_attrs":null,"type_ref":"builtins.tuple"}},"type_guard":null,"type_is":null,"unpack_kwargs":false,"variables":[]}}},"numeric":{".class":"SymbolTableNode","kind":"Mdef","node":{".class":"Decorator","func":{".class":"FuncDef","abstract_status":0,"arg_kinds":[0,0],"arg_names":["self","values"],"dataclass_transform_spec":null,"deprecated":null,"flags":["is_decorated"],"fullname":"cvxpy.atoms.affine.cumsum.cumsum.numeric","name":"numeric","type":null},"is_overload":false,"var":{".class":"Var","flags":["is_initialized_in_class","is_ready","is_inferred"],"fullname":"cvxpy.atoms.affine.cumsum.cumsum.numeric","name":"numeric","type":{".class":"AnyType","missing_import_name":null,"source_any":null,"type_of_any":1}}}},"shape_from_args":{".class":"SymbolTableNode","kind":"Mdef","node":{".class":"FuncDef","abstract_status":0,"arg_kinds":[0],"arg_names":["self"],"dataclass_transform_spec":null,"deprecated":null,"flags":[],"fullname":"cvxpy.atoms.affine.cumsum.cumsum.shape_from_args","name":"shape_from_args","type":{".class":"CallableType","arg_kinds":[0],"arg_names":["self"],"arg_types":["cvxpy.atoms.affine.cumsum.cumsum"],"bound_args":[],"def_extras":{"first_arg":"self"},"fallback":"builtins.function","from_concatenate":false,"implicit":false,"imprecise_arg_kinds":false,"is_ellipsis_args":false,"name":"shape_from_args of cumsum","ret_type":{".class":"Instance","args":["builtins.int"],"extra_attrs":null,"type_ref":"builtins.tuple"},"type_guard":null,"type_is":null,"unpack_kwargs":false,"variables":[]}}},"validate_arguments":{".class":"SymbolTableNode","kind":"Mdef","node":{".class":"FuncDef","abstract_status":0,"arg_kinds":[0],"arg_names":["self"],"dataclass_transform_spec":null,"deprecated":null,"flags":[],"fullname":"cvxpy.atoms.affine.cumsum.cumsum.validate_arguments","name":"validate_arguments","type":null}}},"self_type":{".class":"TypeVarType","default":{".class":"AnyType","missing_import_name":null,"source_any":null,"type_of_any":4},"fullname":"cvxpy.atoms.affine.cumsum.cumsum.Self","id":0,"name":"Self","namespace":"","upper_bound":"cvxpy.atoms.affine.cumsum.cumsum","values":[],"variance":0},"slots":null,"tuple_type":null,"type_vars":[],"typeddict_type":null}},"get_diff_mat":{".class":"SymbolTableNode","kind":"Gdef","node":{".class":"FuncDef","abstract_status":0,"arg_kinds":[0,0],"arg_names":["dim","axis"],"dataclass_transform_spec":null,"deprecated":null,"flags":[],"fullname":"cvxpy.atoms.affine.cumsum.get_diff_mat","name":"get_diff_mat","type":{".class":"CallableType","arg_kinds":[0,0],"arg_names":["dim","axis"],"arg_types":["builtins.int","builtins.int"],"bound_args":[],"def_extras":{"first_arg":null},"fallback":"builtins.function","from_concatenate":false,"implicit":false,"imprecise_arg_kinds":false,"is_ellipsis_args":false,"name":"get_diff_mat","ret_type":{".class":"Instance","args":[{".class":"AnyType","missing_import_name":null,"source_any":null,"type_of_any":2}],"extra_attrs":null,"type_ref":"scipy.sparse._csc.csc_array"},"type_guard":null,"type_is":null,"unpack_kwargs":false,"variables":[]}}},"lo":{".class":"SymbolTableNode","cross_ref":"cvxpy.lin_ops.lin_op","kind":"Gdef"},"lu":{".class":"SymbolTableNode","cross_ref":"cvxpy.lin_ops.lin_utils","kind":"Gdef"},"np":{".class":"SymbolTableNode","cross_ref":"numpy","kind":"Gdef"},"sp":{".class":"SymbolTableNode","cross_ref":"scipy.sparse","kind":"Gdef"}},"path":"/home/gray/git/distopf_2/.venv/lib/python3.13/site-packages/cvxpy/atoms/affine/cumsum.py"}