{".class":"MypyFile","_fullname":"cvxpy.reductions.cone2cone.affine2direct","future_import_flags":[],"is_partial_stub_package":false,"is_stub":false,"names":{".class":"SymbolTable","DUAL_EXP":{".class":"SymbolTableNode","kind":"Gdef","node":{".class":"Var","flags":["is_ready","is_inferred","has_explicit_value"],"fullname":"cvxpy.reductions.cone2cone.affine2direct.DUAL_EXP","name":"DUAL_EXP","type":"builtins.str"}},"DUAL_POW3D":{".class":"SymbolTableNode","kind":"Gdef","node":{".class":"Var","flags":["is_ready","is_inferred","has_explicit_value"],"fullname":"cvxpy.reductions.cone2cone.affine2direct.DUAL_POW3D","name":"DUAL_POW3D","type":"builtins.str"}},"Dualize":{".class":"SymbolTableNode","kind":"Gdef","node":{".class":"TypeInfo","_promote":[],"abstract_attributes":[],"alt_promote":null,"bases":["builtins.object"],"dataclass_transform_spec":null,"declared_metaclass":null,"defn":{".class":"ClassDef","fullname":"cvxpy.reductions.cone2cone.affine2direct.Dualize","name":"Dualize","type_vars":[]},"deletable_attributes":[],"deprecated":null,"flags":[],"fullname":"cvxpy.reductions.cone2cone.affine2direct.Dualize","has_param_spec_type":false,"metaclass_type":null,"metadata":{},"module_name":"cvxpy.reductions.cone2cone.affine2direct","mro":["cvxpy.reductions.cone2cone.affine2direct.Dualize","builtins.object"],"names":{".class":"SymbolTable","apply":{".class":"SymbolTableNode","kind":"Mdef","node":{".class":"Decorator","func":{".class":"FuncDef","abstract_status":0,"arg_kinds":[0],"arg_names":["problem"],"dataclass_transform_spec":null,"deprecated":null,"flags":["is_static","is_decorated"],"fullname":"cvxpy.reductions.cone2cone.affine2direct.Dualize.apply","name":"apply","type":null},"is_overload":false,"var":{".class":"Var","flags":["is_initialized_in_class","is_staticmethod","is_ready","is_inferred"],"fullname":"cvxpy.reductions.cone2cone.affine2direct.Dualize.apply","name":"apply","type":{".class":"CallableType","arg_kinds":[0],"arg_names":["problem"],"arg_types":[{".class":"AnyType","missing_import_name":null,"source_any":null,"type_of_any":1}],"bound_args":[],"def_extras":{"first_arg":null},"fallback":"builtins.function","from_concatenate":false,"implicit":true,"imprecise_arg_kinds":false,"is_ellipsis_args":false,"name":"apply of Dualize","ret_type":{".class":"AnyType","missing_import_name":null,"source_any":null,"type_of_any":1},"type_guard":null,"type_is":null,"unpack_kwargs":false,"variables":[]}}}},"invert":{".class":"SymbolTableNode","kind":"Mdef","node":{".class":"Decorator","func":{".class":"FuncDef","abstract_status":0,"arg_kinds":[0,0],"arg_names":["solution","inv_data"],"dataclass_transform_spec":null,"deprecated":null,"flags":["is_static","is_decorated"],"fullname":"cvxpy.reductions.cone2cone.affine2direct.Dualize.invert","name":"invert","type":null},"is_overload":false,"var":{".class":"Var","flags":["is_initialized_in_class","is_staticmethod","is_ready","is_inferred"],"fullname":"cvxpy.reductions.cone2cone.affine2direct.Dualize.invert","name":"invert","type":{".class":"CallableType","arg_kinds":[0,0],"arg_names":["solution","inv_data"],"arg_types":[{".class":"AnyType","missing_import_name":null,"source_any":null,"type_of_any":1},{".class":"AnyType","missing_import_name":null,"source_any":null,"type_of_any":1}],"bound_args":[],"def_extras":{"first_arg":null},"fallback":"builtins.function","from_concatenate":false,"implicit":true,"imprecise_arg_kinds":false,"is_ellipsis_args":false,"name":"invert of Dualize","ret_type":{".class":"AnyType","missing_import_name":null,"source_any":null,"type_of_any":1},"type_guard":null,"type_is":null,"unpack_kwargs":false,"variables":[]}}}}},"self_type":{".class":"TypeVarType","default":{".class":"AnyType","missing_import_name":null,"source_any":null,"type_of_any":4},"fullname":"cvxpy.reductions.cone2cone.affine2direct.Dualize.Self","id":0,"name":"Self","namespace":"","upper_bound":"cvxpy.reductions.cone2cone.affine2direct.Dualize","values":[],"variance":0},"slots":null,"tuple_type":null,"type_vars":[],"typeddict_type":null}},"EXP":{".class":"SymbolTableNode","kind":"Gdef","node":{".class":"Var","flags":["is_ready","is_inferred","has_explicit_value"],"fullname":"cvxpy.reductions.cone2cone.affine2direct.EXP","name":"EXP","type":"builtins.str"}},"ExpCone_obj":{".class":"SymbolTableNode","cross_ref":"cvxpy.constraints.exponential.ExpCone","kind":"Gdef"},"FREE":{".class":"SymbolTableNode","kind":"Gdef","node":{".class":"Var","flags":["is_ready","is_inferred","has_explicit_value"],"fullname":"cvxpy.reductions.cone2cone.affine2direct.FREE","name":"FREE","type":"builtins.str"}},"NONNEG":{".class":"SymbolTableNode","kind":"Gdef","node":{".class":"Var","flags":["is_ready","is_inferred","has_explicit_value"],"fullname":"cvxpy.reductions.cone2cone.affine2direct.NONNEG","name":"NONNEG","type":"builtins.str"}},"NonNeg_obj":{".class":"SymbolTableNode","cross_ref":"cvxpy.constraints.nonpos.NonNeg","kind":"Gdef"},"Optional":{".class":"SymbolTableNode","cross_ref":"typing.Optional","kind":"Gdef"},"POW3D":{".class":"SymbolTableNode","kind":"Gdef","node":{".class":"Var","flags":["is_ready","is_inferred","has_explicit_value"],"fullname":"cvxpy.reductions.cone2cone.affine2direct.POW3D","name":"POW3D","type":"builtins.str"}},"PSD":{".class":"SymbolTableNode","kind":"Gdef","node":{".class":"Var","flags":["is_ready","is_inferred","has_explicit_value"],"fullname":"cvxpy.reductions.cone2cone.affine2direct.PSD","name":"PSD","type":"builtins.str"}},"PSD_obj":{".class":"SymbolTableNode","cross_ref":"cvxpy.constraints.psd.PSD","kind":"Gdef"},"PowCone_obj":{".class":"SymbolTableNode","cross_ref":"cvxpy.constraints.power.PowCone3D","kind":"Gdef"},"SOC":{".class":"SymbolTableNode","kind":"Gdef","node":{".class":"Var","flags":["is_ready","is_inferred","has_explicit_value"],"fullname":"cvxpy.reductions.cone2cone.affine2direct.SOC","name":"SOC","type":"builtins.str"}},"SOC_obj":{".class":"SymbolTableNode","cross_ref":"cvxpy.constraints.second_order.SOC","kind":"Gdef"},"Slacks":{".class":"SymbolTableNode","kind":"Gdef","node":{".class":"TypeInfo","_promote":[],"abstract_attributes":[],"alt_promote":null,"bases":["builtins.object"],"dataclass_transform_spec":null,"declared_metaclass":null,"defn":{".class":"ClassDef","fullname":"cvxpy.reductions.cone2cone.affine2direct.Slacks","name":"Slacks","type_vars":[]},"deletable_attributes":[],"deprecated":null,"flags":[],"fullname":"cvxpy.reductions.cone2cone.affine2direct.Slacks","has_param_spec_type":false,"metaclass_type":null,"metadata":{},"module_name":"cvxpy.reductions.cone2cone.affine2direct","mro":["cvxpy.reductions.cone2cone.affine2direct.Slacks","builtins.object"],"names":{".class":"SymbolTable","apply":{".class":"SymbolTableNode","kind":"Mdef","node":{".class":"Decorator","func":{".class":"FuncDef","abstract_status":0,"arg_kinds":[0,0],"arg_names":["prob","affine"],"dataclass_transform_spec":null,"deprecated":null,"flags":["is_static","is_decorated"],"fullname":"cvxpy.reductions.cone2cone.affine2direct.Slacks.apply","name":"apply","type":null},"is_overload":false,"var":{".class":"Var","flags":["is_initialized_in_class","is_staticmethod","is_ready","is_inferred"],"fullname":"cvxpy.reductions.cone2cone.affine2direct.Slacks.apply","name":"apply","type":{".class":"CallableType","arg_kinds":[0,0],"arg_names":["prob","affine"],"arg_types":[{".class":"AnyType","missing_import_name":null,"source_any":null,"type_of_any":1},{".class":"AnyType","missing_import_name":null,"source_any":null,"type_of_any":1}],"bound_args":[],"def_extras":{"first_arg":null},"fallback":"builtins.function","from_concatenate":false,"implicit":true,"imprecise_arg_kinds":false,"is_ellipsis_args":false,"name":"apply of Slacks","ret_type":{".class":"AnyType","missing_import_name":null,"source_any":null,"type_of_any":1},"type_guard":null,"type_is":null,"unpack_kwargs":false,"variables":[]}}}},"extend_bounds":{".class":"SymbolTableNode","kind":"Mdef","node":{".class":"Decorator","func":{".class":"FuncDef","abstract_status":0,"arg_kinds":[0,0,0],"arg_names":["num_vars","bounds_vector","fill_value"],"dataclass_transform_spec":null,"deprecated":null,"flags":["is_static","is_decorated"],"fullname":"cvxpy.reductions.cone2cone.affine2direct.Slacks.extend_bounds","name":"extend_bounds","type":{".class":"CallableType","arg_kinds":[0,0,0],"arg_names":["num_vars","bounds_vector","fill_value"],"arg_types":["builtins.int",{".class":"UnionType","items":[{".class":"Instance","args":[{".class":"Instance","args":[{".class":"AnyType","missing_import_name":null,"source_any":null,"type_of_any":6}],"extra_attrs":null,"type_ref":"builtins.tuple"},{".class":"Instance","args":[{".class":"AnyType","missing_import_name":null,"source_any":null,"type_of_any":2}],"extra_attrs":null,"type_ref":"numpy.dtype"}],"extra_attrs":null,"type_ref":"numpy.ndarray"},{".class":"NoneType"}],"uses_pep604_syntax":false},"builtins.float"],"bound_args":[],"def_extras":{"first_arg":null},"fallback":"builtins.function","from_concatenate":false,"implicit":false,"imprecise_arg_kinds":false,"is_ellipsis_args":false,"name":"extend_bounds of Slacks","ret_type":{".class":"Instance","args":[{".class":"Instance","args":[{".class":"AnyType","missing_import_name":null,"source_any":null,"type_of_any":6}],"extra_attrs":null,"type_ref":"builtins.tuple"},{".class":"Instance","args":[{".class":"AnyType","missing_import_name":null,"source_any":null,"type_of_any":2}],"extra_attrs":null,"type_ref":"numpy.dtype"}],"extra_attrs":null,"type_ref":"numpy.ndarray"},"type_guard":null,"type_is":null,"unpack_kwargs":false,"variables":[]}},"is_overload":false,"var":{".class":"Var","flags":["is_initialized_in_class","is_staticmethod","is_ready","is_inferred"],"fullname":"cvxpy.reductions.cone2cone.affine2direct.Slacks.extend_bounds","name":"extend_bounds","type":{".class":"CallableType","arg_kinds":[0,0,0],"arg_names":["num_vars","bounds_vector","fill_value"],"arg_types":["builtins.int",{".class":"UnionType","items":[{".class":"Instance","args":[{".class":"Instance","args":[{".class":"AnyType","missing_import_name":null,"source_any":null,"type_of_any":6}],"extra_attrs":null,"type_ref":"builtins.tuple"},{".class":"Instance","args":[{".class":"AnyType","missing_import_name":null,"source_any":null,"type_of_any":2}],"extra_attrs":null,"type_ref":"numpy.dtype"}],"extra_attrs":null,"type_ref":"numpy.ndarray"},{".class":"NoneType"}],"uses_pep604_syntax":false},"builtins.float"],"bound_args":[],"def_extras":{"first_arg":null},"fallback":"builtins.function","from_concatenate":false,"implicit":false,"imprecise_arg_kinds":false,"is_ellipsis_args":false,"name":"extend_bounds of Slacks","ret_type":{".class":"Instance","args":[{".class":"Instance","args":[{".class":"AnyType","missing_import_name":null,"source_any":null,"type_of_any":6}],"extra_attrs":null,"type_ref":"builtins.tuple"},{".class":"Instance","args":[{".class":"AnyType","missing_import_name":null,"source_any":null,"type_of_any":2}],"extra_attrs":null,"type_ref":"numpy.dtype"}],"extra_attrs":null,"type_ref":"numpy.ndarray"},"type_guard":null,"type_is":null,"unpack_kwargs":false,"variables":[]}}}},"invert":{".class":"SymbolTableNode","kind":"Mdef","node":{".class":"Decorator","func":{".class":"FuncDef","abstract_status":0,"arg_kinds":[0,0],"arg_names":["solution","inv_data"],"dataclass_transform_spec":null,"deprecated":null,"flags":["is_static","is_decorated"],"fullname":"cvxpy.reductions.cone2cone.affine2direct.Slacks.invert","name":"invert","type":null},"is_overload":false,"var":{".class":"Var","flags":["is_initialized_in_class","is_staticmethod","is_ready","is_inferred"],"fullname":"cvxpy.reductions.cone2cone.affine2direct.Slacks.invert","name":"invert","type":{".class":"CallableType","arg_kinds":[0,0],"arg_names":["solution","inv_data"],"arg_types":[{".class":"AnyType","missing_import_name":null,"source_any":null,"type_of_any":1},{".class":"AnyType","missing_import_name":null,"source_any":null,"type_of_any":1}],"bound_args":[],"def_extras":{"first_arg":null},"fallback":"builtins.function","from_concatenate":false,"implicit":true,"imprecise_arg_kinds":false,"is_ellipsis_args":false,"name":"invert of Slacks","ret_type":{".class":"AnyType","missing_import_name":null,"source_any":null,"type_of_any":1},"type_guard":null,"type_is":null,"unpack_kwargs":false,"variables":[]}}}}},"self_type":{".class":"TypeVarType","default":{".class":"AnyType","missing_import_name":null,"source_any":null,"type_of_any":4},"fullname":"cvxpy.reductions.cone2cone.affine2direct.Slacks.Self","id":0,"name":"Self","namespace":"","upper_bound":"cvxpy.reductions.cone2cone.affine2direct.Slacks","values":[],"variance":0},"slots":null,"tuple_type":null,"type_vars":[],"typeddict_type":null}},"Solution":{".class":"SymbolTableNode","cross_ref":"cvxpy.reductions.solution.Solution","kind":"Gdef"},"ZERO":{".class":"SymbolTableNode","kind":"Gdef","node":{".class":"Var","flags":["is_ready","is_inferred","has_explicit_value"],"fullname":"cvxpy.reductions.cone2cone.affine2direct.ZERO","name":"ZERO","type":"builtins.str"}},"Zero_obj":{".class":"SymbolTableNode","cross_ref":"cvxpy.constraints.zero.Zero","kind":"Gdef"},"__annotations__":{".class":"SymbolTableNode","kind":"Gdef","node":{".class":"Var","flags":["is_ready"],"fullname":"cvxpy.reductions.cone2cone.affine2direct.__annotations__","name":"__annotations__","type":{".class":"Instance","args":["builtins.str",{".class":"AnyType","missing_import_name":null,"source_any":null,"type_of_any":6}],"extra_attrs":null,"type_ref":"builtins.dict"}}},"__doc__":{".class":"SymbolTableNode","kind":"Gdef","node":{".class":"Var","flags":["is_ready"],"fullname":"cvxpy.reductions.cone2cone.affine2direct.__doc__","name":"__doc__","type":"builtins.str"}},"__file__":{".class":"SymbolTableNode","kind":"Gdef","node":{".class":"Var","flags":["is_ready"],"fullname":"cvxpy.reductions.cone2cone.affine2direct.__file__","name":"__file__","type":"builtins.str"}},"__name__":{".class":"SymbolTableNode","kind":"Gdef","node":{".class":"Var","flags":["is_ready"],"fullname":"cvxpy.reductions.cone2cone.affine2direct.__name__","name":"__name__","type":"builtins.str"}},"__package__":{".class":"SymbolTableNode","kind":"Gdef","node":{".class":"Var","flags":["is_ready"],"fullname":"cvxpy.reductions.cone2cone.affine2direct.__package__","name":"__package__","type":"builtins.str"}},"__spec__":{".class":"SymbolTableNode","kind":"Gdef","node":{".class":"Var","flags":["is_ready"],"fullname":"cvxpy.reductions.cone2cone.affine2direct.__spec__","name":"__spec__","type":"_frozen_importlib.ModuleSpec"}},"np":{".class":"SymbolTableNode","cross_ref":"numpy","kind":"Gdef"},"s":{".class":"SymbolTableNode","cross_ref":"cvxpy.settings","kind":"Gdef"},"sp":{".class":"SymbolTableNode","cross_ref":"scipy","kind":"Gdef"}},"path":"/home/gray/git/distopf_2/.venv/lib/python3.13/site-packages/cvxpy/reductions/cone2cone/affine2direct.py"}