{".class":"MypyFile","_fullname":"cimgraph.databases.neo4j.neo4j","future_import_flags":["annotations"],"is_partial_stub_package":false,"is_stub":false,"names":{".class":"SymbolTable","AsyncGraphDatabase":{".class":"SymbolTableNode","cross_ref":"neo4j._async.driver.AsyncGraphDatabase","kind":"Gdef"},"ConnectionInterface":{".class":"SymbolTableNode","cross_ref":"cimgraph.databases.ConnectionInterface","kind":"Gdef"},"DriverError":{".class":"SymbolTableNode","cross_ref":"neo4j.exceptions.DriverError","kind":"Gdef"},"Graph":{".class":"SymbolTableNode","cross_ref":"cimgraph.databases.Graph","kind":"Gdef"},"GraphDatabase":{".class":"SymbolTableNode","cross_ref":"neo4j._sync.driver.GraphDatabase","kind":"Gdef"},"Neo4jConnection":{".class":"SymbolTableNode","kind":"Gdef","node":{".class":"TypeInfo","_promote":[],"abstract_attributes":[],"alt_promote":null,"bases":["cimgraph.databases.ConnectionInterface"],"dataclass_transform_spec":null,"declared_metaclass":null,"defn":{".class":"ClassDef","fullname":"cimgraph.databases.neo4j.neo4j.Neo4jConnection","name":"Neo4jConnection","type_vars":[]},"deletable_attributes":[],"deprecated":null,"flags":[],"fullname":"cimgraph.databases.neo4j.neo4j.Neo4jConnection","has_param_spec_type":false,"metaclass_type":"abc.ABCMeta","metadata":{},"module_name":"cimgraph.databases.neo4j.neo4j","mro":["cimgraph.databases.neo4j.neo4j.Neo4jConnection","cimgraph.databases.ConnectionInterface","abc.ABC","builtins.object"],"names":{".class":"SymbolTable","__init__":{".class":"SymbolTableNode","kind":"Mdef","node":{".class":"FuncDef","abstract_status":0,"arg_kinds":[0],"arg_names":["self"],"dataclass_transform_spec":null,"deprecated":null,"flags":[],"fullname":"cimgraph.databases.neo4j.neo4j.Neo4jConnection.__init__","name":"__init__","type":null}},"async_execute":{".class":"SymbolTableNode","kind":"Mdef","node":{".class":"FuncDef","abstract_status":0,"arg_kinds":[0,0],"arg_names":["self","query_message"],"dataclass_transform_spec":null,"deprecated":null,"flags":["is_coroutine"],"fullname":"cimgraph.databases.neo4j.neo4j.Neo4jConnection.async_execute","name":"async_execute","type":{".class":"CallableType","arg_kinds":[0,0],"arg_names":["self","query_message"],"arg_types":["cimgraph.databases.neo4j.neo4j.Neo4jConnection","builtins.str"],"bound_args":[],"def_extras":{"first_arg":"self"},"fallback":"builtins.function","from_concatenate":false,"implicit":false,"imprecise_arg_kinds":false,"is_ellipsis_args":false,"name":"async_execute of Neo4jConnection","ret_type":{".class":"Instance","args":[{".class":"AnyType","missing_import_name":null,"source_any":null,"type_of_any":6},{".class":"AnyType","missing_import_name":null,"source_any":null,"type_of_any":6},"cimgraph.databases.QueryResponse"],"extra_attrs":null,"type_ref":"typing.Coroutine"},"type_guard":null,"type_is":null,"unpack_kwargs":false,"variables":[]}}},"cim":{".class":"SymbolTableNode","implicit":true,"kind":"Mdef","node":{".class":"Var","flags":["explicit_self_type","is_ready","is_inferred"],"fullname":"cimgraph.databases.neo4j.neo4j.Neo4jConnection.cim","name":"cim","type":{".class":"UnboundType","args":[],"expr":null,"expr_fallback":null,"name":"cim"}}},"cim_profile":{".class":"SymbolTableNode","implicit":true,"kind":"Mdef","node":{".class":"Var","flags":["is_inferred"],"fullname":"cimgraph.databases.neo4j.neo4j.Neo4jConnection.cim_profile","name":"cim_profile","type":{".class":"AnyType","missing_import_name":null,"source_any":null,"type_of_any":1}}},"connect":{".class":"SymbolTableNode","kind":"Mdef","node":{".class":"FuncDef","abstract_status":0,"arg_kinds":[0],"arg_names":["self"],"dataclass_transform_spec":null,"deprecated":null,"flags":[],"fullname":"cimgraph.databases.neo4j.neo4j.Neo4jConnection.connect","name":"connect","type":null}},"create_distributed_graph":{".class":"SymbolTableNode","kind":"Mdef","node":{".class":"FuncDef","abstract_status":0,"arg_kinds":[0,0,1],"arg_names":["self","area","graph"],"dataclass_transform_spec":null,"deprecated":null,"flags":[],"fullname":"cimgraph.databases.neo4j.neo4j.Neo4jConnection.create_distributed_graph","name":"create_distributed_graph","type":{".class":"CallableType","arg_kinds":[0,0,1],"arg_names":["self","area","graph"],"arg_types":["cimgraph.databases.neo4j.neo4j.Neo4jConnection","builtins.object",{".class":"Instance","args":[{".class":"AnyType","missing_import_name":null,"source_any":null,"type_of_any":4},{".class":"AnyType","missing_import_name":null,"source_any":null,"type_of_any":4}],"extra_attrs":null,"type_ref":"builtins.dict"}],"bound_args":[],"def_extras":{"first_arg":"self"},"fallback":"builtins.function","from_concatenate":false,"implicit":false,"imprecise_arg_kinds":false,"is_ellipsis_args":false,"name":"create_distributed_graph of Neo4jConnection","ret_type":{".class":"TypeAliasType","args":[],"type_ref":"cimgraph.databases.Graph"},"type_guard":null,"type_is":null,"unpack_kwargs":false,"variables":[]}}},"create_new_graph":{".class":"SymbolTableNode","kind":"Mdef","node":{".class":"FuncDef","abstract_status":0,"arg_kinds":[0,0,1],"arg_names":["self","container","graph"],"dataclass_transform_spec":null,"deprecated":null,"flags":[],"fullname":"cimgraph.databases.neo4j.neo4j.Neo4jConnection.create_new_graph","name":"create_new_graph","type":{".class":"CallableType","arg_kinds":[0,0,1],"arg_names":["self","container","graph"],"arg_types":["cimgraph.databases.neo4j.neo4j.Neo4jConnection","builtins.object",{".class":"TypeAliasType","args":[],"type_ref":"cimgraph.databases.Graph"}],"bound_args":[],"def_extras":{"first_arg":"self"},"fallback":"builtins.function","from_concatenate":false,"implicit":false,"imprecise_arg_kinds":false,"is_ellipsis_args":false,"name":"create_new_graph of Neo4jConnection","ret_type":{".class":"TypeAliasType","args":[],"type_ref":"cimgraph.databases.Graph"},"type_guard":null,"type_is":null,"unpack_kwargs":false,"variables":[]}}},"database":{".class":"SymbolTableNode","implicit":true,"kind":"Mdef","node":{".class":"Var","flags":["is_inferred"],"fullname":"cimgraph.databases.neo4j.neo4j.Neo4jConnection.database","name":"database","type":{".class":"AnyType","missing_import_name":null,"source_any":null,"type_of_any":1}}},"disconnect":{".class":"SymbolTableNode","kind":"Mdef","node":{".class":"FuncDef","abstract_status":0,"arg_kinds":[0],"arg_names":["self"],"dataclass_transform_spec":null,"deprecated":null,"flags":[],"fullname":"cimgraph.databases.neo4j.neo4j.Neo4jConnection.disconnect","name":"disconnect","type":null}},"driver":{".class":"SymbolTableNode","implicit":true,"kind":"Mdef","node":{".class":"Var","flags":["is_inferred"],"fullname":"cimgraph.databases.neo4j.neo4j.Neo4jConnection.driver","name":"driver","type":{".class":"AnyType","missing_import_name":null,"source_any":null,"type_of_any":1}}},"edge_query_parser":{".class":"SymbolTableNode","kind":"Mdef","node":{".class":"FuncDef","abstract_status":0,"arg_kinds":[0,0,0,0,1],"arg_names":["self","query_output","graph","cim_class","expand_graph"],"dataclass_transform_spec":null,"deprecated":null,"flags":[],"fullname":"cimgraph.databases.neo4j.neo4j.Neo4jConnection.edge_query_parser","name":"edge_query_parser","type":{".class":"CallableType","arg_kinds":[0,0,0,0,1],"arg_names":["self","query_output","graph","cim_class","expand_graph"],"arg_types":["cimgraph.databases.neo4j.neo4j.Neo4jConnection","cimgraph.databases.QueryResponse",{".class":"TypeAliasType","args":[],"type_ref":"cimgraph.databases.Graph"},"builtins.type",{".class":"AnyType","missing_import_name":null,"source_any":null,"type_of_any":1}],"bound_args":[],"def_extras":{"first_arg":"self"},"fallback":"builtins.function","from_concatenate":false,"implicit":false,"imprecise_arg_kinds":false,"is_ellipsis_args":false,"name":"edge_query_parser of Neo4jConnection","ret_type":{".class":"AnyType","missing_import_name":null,"source_any":null,"type_of_any":1},"type_guard":null,"type_is":null,"unpack_kwargs":false,"variables":[]}}},"edge_query_runner":{".class":"SymbolTableNode","kind":"Mdef","node":{".class":"FuncDef","abstract_status":0,"arg_kinds":[0,0,0,0,0],"arg_names":["self","mrid_list","index","graph","cim_class"],"dataclass_transform_spec":null,"deprecated":null,"flags":["is_coroutine"],"fullname":"cimgraph.databases.neo4j.neo4j.Neo4jConnection.edge_query_runner","name":"edge_query_runner","type":{".class":"CallableType","arg_kinds":[0,0,0,0,0],"arg_names":["self","mrid_list","index","graph","cim_class"],"arg_types":["cimgraph.databases.neo4j.neo4j.Neo4jConnection",{".class":"Instance","args":["builtins.str"],"extra_attrs":null,"type_ref":"builtins.list"},"builtins.int",{".class":"Instance","args":["builtins.type",{".class":"Instance","args":["builtins.str","builtins.object"],"extra_attrs":null,"type_ref":"builtins.dict"}],"extra_attrs":null,"type_ref":"builtins.dict"},"builtins.type"],"bound_args":[],"def_extras":{"first_arg":"self"},"fallback":"builtins.function","from_concatenate":false,"implicit":false,"imprecise_arg_kinds":false,"is_ellipsis_args":false,"name":"edge_query_runner of Neo4jConnection","ret_type":{".class":"Instance","args":[{".class":"AnyType","missing_import_name":null,"source_any":null,"type_of_any":6},{".class":"AnyType","missing_import_name":null,"source_any":null,"type_of_any":6},{".class":"AnyType","missing_import_name":null,"source_any":null,"type_of_any":1}],"extra_attrs":null,"type_ref":"typing.Coroutine"},"type_guard":null,"type_is":null,"unpack_kwargs":false,"variables":[]}}},"execute":{".class":"SymbolTableNode","kind":"Mdef","node":{".class":"FuncDef","abstract_status":0,"arg_kinds":[0,0],"arg_names":["self","query_message"],"dataclass_transform_spec":null,"deprecated":null,"flags":[],"fullname":"cimgraph.databases.neo4j.neo4j.Neo4jConnection.execute","name":"execute","type":{".class":"CallableType","arg_kinds":[0,0],"arg_names":["self","query_message"],"arg_types":["cimgraph.databases.neo4j.neo4j.Neo4jConnection","builtins.str"],"bound_args":[],"def_extras":{"first_arg":"self"},"fallback":"builtins.function","from_concatenate":false,"implicit":false,"imprecise_arg_kinds":false,"is_ellipsis_args":false,"name":"execute of Neo4jConnection","ret_type":"cimgraph.databases.QueryResponse","type_guard":null,"type_is":null,"unpack_kwargs":false,"variables":[]}}},"get_all_attributes":{".class":"SymbolTableNode","kind":"Mdef","node":{".class":"FuncDef","abstract_status":0,"arg_kinds":[0,0,0],"arg_names":["self","graph","cim_class"],"dataclass_transform_spec":null,"deprecated":null,"flags":[],"fullname":"cimgraph.databases.neo4j.neo4j.Neo4jConnection.get_all_attributes","name":"get_all_attributes","type":null}},"get_all_edges":{".class":"SymbolTableNode","kind":"Mdef","node":{".class":"FuncDef","abstract_status":0,"arg_kinds":[0,0,0],"arg_names":["self","graph","cim_class"],"dataclass_transform_spec":null,"deprecated":null,"flags":[],"fullname":"cimgraph.databases.neo4j.neo4j.Neo4jConnection.get_all_edges","name":"get_all_edges","type":{".class":"CallableType","arg_kinds":[0,0,0],"arg_names":["self","graph","cim_class"],"arg_types":["cimgraph.databases.neo4j.neo4j.Neo4jConnection",{".class":"Instance","args":["builtins.type",{".class":"Instance","args":["builtins.str","builtins.object"],"extra_attrs":null,"type_ref":"builtins.dict"}],"extra_attrs":null,"type_ref":"builtins.dict"},"builtins.type"],"bound_args":[],"def_extras":{"first_arg":"self"},"fallback":"builtins.function","from_concatenate":false,"implicit":false,"imprecise_arg_kinds":false,"is_ellipsis_args":false,"name":"get_all_edges of Neo4jConnection","ret_type":{".class":"NoneType"},"type_guard":null,"type_is":null,"unpack_kwargs":false,"variables":[]}}},"get_all_edges_async":{".class":"SymbolTableNode","kind":"Mdef","node":{".class":"FuncDef","abstract_status":0,"arg_kinds":[0,0,0,0],"arg_names":["self","mrid_list","graph","cim_class"],"dataclass_transform_spec":null,"deprecated":null,"flags":["is_coroutine"],"fullname":"cimgraph.databases.neo4j.neo4j.Neo4jConnection.get_all_edges_async","name":"get_all_edges_async","type":{".class":"CallableType","arg_kinds":[0,0,0,0],"arg_names":["self","mrid_list","graph","cim_class"],"arg_types":["cimgraph.databases.neo4j.neo4j.Neo4jConnection",{".class":"AnyType","missing_import_name":null,"source_any":null,"type_of_any":1},{".class":"Instance","args":["builtins.type",{".class":"Instance","args":["builtins.str","builtins.object"],"extra_attrs":null,"type_ref":"builtins.dict"}],"extra_attrs":null,"type_ref":"builtins.dict"},"builtins.type"],"bound_args":[],"def_extras":{"first_arg":"self"},"fallback":"builtins.function","from_concatenate":false,"implicit":false,"imprecise_arg_kinds":false,"is_ellipsis_args":false,"name":"get_all_edges_async of Neo4jConnection","ret_type":{".class":"Instance","args":[{".class":"AnyType","missing_import_name":null,"source_any":null,"type_of_any":6},{".class":"AnyType","missing_import_name":null,"source_any":null,"type_of_any":6},{".class":"AnyType","missing_import_name":null,"source_any":null,"type_of_any":1}],"extra_attrs":null,"type_ref":"typing.Coroutine"},"type_guard":null,"type_is":null,"unpack_kwargs":false,"variables":[]}}},"get_edges_query":{".class":"SymbolTableNode","kind":"Mdef","node":{".class":"FuncDef","abstract_status":0,"arg_kinds":[0,0,0],"arg_names":["self","graph","cim_class"],"dataclass_transform_spec":null,"deprecated":null,"flags":[],"fullname":"cimgraph.databases.neo4j.neo4j.Neo4jConnection.get_edges_query","name":"get_edges_query","type":{".class":"CallableType","arg_kinds":[0,0,0],"arg_names":["self","graph","cim_class"],"arg_types":["cimgraph.databases.neo4j.neo4j.Neo4jConnection",{".class":"Instance","args":["builtins.type",{".class":"Instance","args":["builtins.str","builtins.object"],"extra_attrs":null,"type_ref":"builtins.dict"}],"extra_attrs":null,"type_ref":"builtins.dict"},"builtins.type"],"bound_args":[],"def_extras":{"first_arg":"self"},"fallback":"builtins.function","from_concatenate":false,"implicit":false,"imprecise_arg_kinds":false,"is_ellipsis_args":false,"name":"get_edges_query of Neo4jConnection","ret_type":"builtins.str","type_guard":null,"type_is":null,"unpack_kwargs":false,"variables":[]}}},"get_from_triple":{".class":"SymbolTableNode","kind":"Mdef","node":{".class":"FuncDef","abstract_status":0,"arg_kinds":[0,0,0,1],"arg_names":["self","subject","predicate","graph"],"dataclass_transform_spec":null,"deprecated":null,"flags":[],"fullname":"cimgraph.databases.neo4j.neo4j.Neo4jConnection.get_from_triple","name":"get_from_triple","type":{".class":"CallableType","arg_kinds":[0,0,0,1],"arg_names":["self","subject","predicate","graph"],"arg_types":["cimgraph.databases.neo4j.neo4j.Neo4jConnection","builtins.object","builtins.str",{".class":"TypeAliasType","args":[],"type_ref":"cimgraph.databases.Graph"}],"bound_args":[],"def_extras":{"first_arg":"self"},"fallback":"builtins.function","from_concatenate":false,"implicit":false,"imprecise_arg_kinds":false,"is_ellipsis_args":false,"name":"get_from_triple of Neo4jConnection","ret_type":{".class":"Instance","args":["builtins.object"],"extra_attrs":null,"type_ref":"builtins.list"},"type_guard":null,"type_is":null,"unpack_kwargs":false,"variables":[]}}},"get_object":{".class":"SymbolTableNode","kind":"Mdef","node":{".class":"FuncDef","abstract_status":0,"arg_kinds":[0,0,1],"arg_names":["self","mRID","graph"],"dataclass_transform_spec":null,"deprecated":null,"flags":[],"fullname":"cimgraph.databases.neo4j.neo4j.Neo4jConnection.get_object","name":"get_object","type":{".class":"CallableType","arg_kinds":[0,0,1],"arg_names":["self","mRID","graph"],"arg_types":["cimgraph.databases.neo4j.neo4j.Neo4jConnection","builtins.str",{".class":"Instance","args":[{".class":"AnyType","missing_import_name":null,"source_any":null,"type_of_any":4},{".class":"AnyType","missing_import_name":null,"source_any":null,"type_of_any":4}],"extra_attrs":null,"type_ref":"builtins.dict"}],"bound_args":[],"def_extras":{"first_arg":"self"},"fallback":"builtins.function","from_concatenate":false,"implicit":false,"imprecise_arg_kinds":false,"is_ellipsis_args":false,"name":"get_object of Neo4jConnection","ret_type":"builtins.object","type_guard":null,"type_is":null,"unpack_kwargs":false,"variables":[]}}},"iec61970_301":{".class":"SymbolTableNode","implicit":true,"kind":"Mdef","node":{".class":"Var","flags":["is_inferred"],"fullname":"cimgraph.databases.neo4j.neo4j.Neo4jConnection.iec61970_301","name":"iec61970_301","type":{".class":"AnyType","missing_import_name":null,"source_any":null,"type_of_any":1}}},"namespace":{".class":"SymbolTableNode","implicit":true,"kind":"Mdef","node":{".class":"Var","flags":["is_inferred"],"fullname":"cimgraph.databases.neo4j.neo4j.Neo4jConnection.namespace","name":"namespace","type":{".class":"AnyType","missing_import_name":null,"source_any":null,"type_of_any":1}}},"parse_node_query":{".class":"SymbolTableNode","kind":"Mdef","node":{".class":"FuncDef","abstract_status":0,"arg_kinds":[0,0,0],"arg_names":["self","graph","query_output"],"dataclass_transform_spec":null,"deprecated":null,"flags":[],"fullname":"cimgraph.databases.neo4j.neo4j.Neo4jConnection.parse_node_query","name":"parse_node_query","type":{".class":"CallableType","arg_kinds":[0,0,0],"arg_names":["self","graph","query_output"],"arg_types":["cimgraph.databases.neo4j.neo4j.Neo4jConnection",{".class":"Instance","args":[{".class":"AnyType","missing_import_name":null,"source_any":null,"type_of_any":4},{".class":"AnyType","missing_import_name":null,"source_any":null,"type_of_any":4}],"extra_attrs":null,"type_ref":"builtins.dict"},{".class":"Instance","args":[{".class":"AnyType","missing_import_name":null,"source_any":null,"type_of_any":4},{".class":"AnyType","missing_import_name":null,"source_any":null,"type_of_any":4}],"extra_attrs":null,"type_ref":"builtins.dict"}],"bound_args":[],"def_extras":{"first_arg":"self"},"fallback":"builtins.function","from_concatenate":false,"implicit":false,"imprecise_arg_kinds":false,"is_ellipsis_args":false,"name":"parse_node_query of Neo4jConnection","ret_type":{".class":"TypeAliasType","args":[],"type_ref":"cimgraph.databases.Graph"},"type_guard":null,"type_is":null,"unpack_kwargs":false,"variables":[]}}},"password":{".class":"SymbolTableNode","implicit":true,"kind":"Mdef","node":{".class":"Var","flags":["is_inferred"],"fullname":"cimgraph.databases.neo4j.neo4j.Neo4jConnection.password","name":"password","type":{".class":"AnyType","missing_import_name":null,"source_any":null,"type_of_any":1}}},"property_query_parser":{".class":"SymbolTableNode","kind":"Mdef","node":{".class":"FuncDef","abstract_status":0,"arg_kinds":[0,0,0,0,1],"arg_names":["self","query_output","graph","cim_class","expand_graph"],"dataclass_transform_spec":null,"deprecated":null,"flags":[],"fullname":"cimgraph.databases.neo4j.neo4j.Neo4jConnection.property_query_parser","name":"property_query_parser","type":{".class":"CallableType","arg_kinds":[0,0,0,0,1],"arg_names":["self","query_output","graph","cim_class","expand_graph"],"arg_types":["cimgraph.databases.neo4j.neo4j.Neo4jConnection","cimgraph.databases.QueryResponse",{".class":"TypeAliasType","args":[],"type_ref":"cimgraph.databases.Graph"},"builtins.type",{".class":"AnyType","missing_import_name":null,"source_any":null,"type_of_any":1}],"bound_args":[],"def_extras":{"first_arg":"self"},"fallback":"builtins.function","from_concatenate":false,"implicit":false,"imprecise_arg_kinds":false,"is_ellipsis_args":false,"name":"property_query_parser of Neo4jConnection","ret_type":{".class":"AnyType","missing_import_name":null,"source_any":null,"type_of_any":1},"type_guard":null,"type_is":null,"unpack_kwargs":false,"variables":[]}}},"query_tx":{".class":"SymbolTableNode","kind":"Mdef","node":{".class":"FuncDef","abstract_status":0,"arg_kinds":[0,0,0],"arg_names":["self","tx","query_message"],"dataclass_transform_spec":null,"deprecated":null,"flags":["is_coroutine"],"fullname":"cimgraph.databases.neo4j.neo4j.Neo4jConnection.query_tx","name":"query_tx","type":null}},"upload":{".class":"SymbolTableNode","kind":"Mdef","node":{".class":"FuncDef","abstract_status":0,"arg_kinds":[0,0],"arg_names":["self","graph"],"dataclass_transform_spec":null,"deprecated":null,"flags":[],"fullname":"cimgraph.databases.neo4j.neo4j.Neo4jConnection.upload","name":"upload","type":null}},"url":{".class":"SymbolTableNode","implicit":true,"kind":"Mdef","node":{".class":"Var","flags":["is_inferred"],"fullname":"cimgraph.databases.neo4j.neo4j.Neo4jConnection.url","name":"url","type":{".class":"AnyType","missing_import_name":null,"source_any":null,"type_of_any":1}}},"username":{".class":"SymbolTableNode","implicit":true,"kind":"Mdef","node":{".class":"Var","flags":["is_inferred"],"fullname":"cimgraph.databases.neo4j.neo4j.Neo4jConnection.username","name":"username","type":{".class":"AnyType","missing_import_name":null,"source_any":null,"type_of_any":1}}}},"self_type":{".class":"TypeVarType","default":{".class":"AnyType","missing_import_name":null,"source_any":null,"type_of_any":4},"fullname":"cimgraph.databases.neo4j.neo4j.Neo4jConnection.Self","id":0,"name":"Self","namespace":"","upper_bound":"cimgraph.databases.neo4j.neo4j.Neo4jConnection","values":[],"variance":0},"slots":null,"tuple_type":null,"type_vars":[],"typeddict_type":null}},"Neo4jError":{".class":"SymbolTableNode","cross_ref":"neo4j.exceptions.Neo4jError","kind":"Gdef"},"QueryResponse":{".class":"SymbolTableNode","cross_ref":"cimgraph.databases.QueryResponse","kind":"Gdef"},"UUID":{".class":"SymbolTableNode","cross_ref":"uuid.UUID","kind":"Gdef"},"__annotations__":{".class":"SymbolTableNode","kind":"Gdef","node":{".class":"Var","flags":["is_ready"],"fullname":"cimgraph.databases.neo4j.neo4j.__annotations__","name":"__annotations__","type":{".class":"Instance","args":["builtins.str",{".class":"AnyType","missing_import_name":null,"source_any":null,"type_of_any":6}],"extra_attrs":null,"type_ref":"builtins.dict"}}},"__doc__":{".class":"SymbolTableNode","kind":"Gdef","node":{".class":"Var","flags":["is_ready"],"fullname":"cimgraph.databases.neo4j.neo4j.__doc__","name":"__doc__","type":"builtins.str"}},"__file__":{".class":"SymbolTableNode","kind":"Gdef","node":{".class":"Var","flags":["is_ready"],"fullname":"cimgraph.databases.neo4j.neo4j.__file__","name":"__file__","type":"builtins.str"}},"__name__":{".class":"SymbolTableNode","kind":"Gdef","node":{".class":"Var","flags":["is_ready"],"fullname":"cimgraph.databases.neo4j.neo4j.__name__","name":"__name__","type":"builtins.str"}},"__package__":{".class":"SymbolTableNode","kind":"Gdef","node":{".class":"Var","flags":["is_ready"],"fullname":"cimgraph.databases.neo4j.neo4j.__package__","name":"__package__","type":"builtins.str"}},"__spec__":{".class":"SymbolTableNode","kind":"Gdef","node":{".class":"Var","flags":["is_ready"],"fullname":"cimgraph.databases.neo4j.neo4j.__spec__","name":"__spec__","type":"_frozen_importlib.ModuleSpec"}},"_log":{".class":"SymbolTableNode","kind":"Gdef","node":{".class":"Var","flags":["is_inferred","has_explicit_value"],"fullname":"cimgraph.databases.neo4j.neo4j._log","name":"_log","type":"logging.Logger"}},"annotations":{".class":"SymbolTableNode","cross_ref":"__future__.annotations","kind":"Gdef"},"asyncio":{".class":"SymbolTableNode","cross_ref":"asyncio","kind":"Gdef"},"cim":{".class":"SymbolTableNode","cross_ref":"cimgraph.data_profile.cimhub_2023","kind":"Gdef"},"cypher":{".class":"SymbolTableNode","cross_ref":"cimgraph.queries.cypher","kind":"Gdef"},"defaultdict":{".class":"SymbolTableNode","cross_ref":"collections.defaultdict","kind":"Gdef"},"get_cim_profile":{".class":"SymbolTableNode","cross_ref":"cimgraph.databases.get_cim_profile","kind":"Gdef"},"get_database":{".class":"SymbolTableNode","cross_ref":"cimgraph.databases.get_database","kind":"Gdef"},"get_iec61970_301":{".class":"SymbolTableNode","cross_ref":"cimgraph.databases.get_iec61970_301","kind":"Gdef"},"get_namespace":{".class":"SymbolTableNode","cross_ref":"cimgraph.databases.get_namespace","kind":"Gdef"},"get_password":{".class":"SymbolTableNode","cross_ref":"cimgraph.databases.get_password","kind":"Gdef"},"get_url":{".class":"SymbolTableNode","cross_ref":"cimgraph.databases.get_url","kind":"Gdef"},"get_username":{".class":"SymbolTableNode","cross_ref":"cimgraph.databases.get_username","kind":"Gdef"},"logging":{".class":"SymbolTableNode","cross_ref":"logging","kind":"Gdef"},"math":{".class":"SymbolTableNode","cross_ref":"math","kind":"Gdef"},"nest_asyncio":{".class":"SymbolTableNode","kind":"Gdef","node":{".class":"Var","flags":["is_suppressed_import","is_ready","is_inferred"],"fullname":"cimgraph.databases.neo4j.neo4j.nest_asyncio","name":"nest_asyncio","type":{".class":"AnyType","missing_import_name":"cimgraph.databases.neo4j.neo4j.nest_asyncio","source_any":null,"type_of_any":3}}}},"path":"/home/gray/git/distopf_2/.venv/lib/python3.13/site-packages/cimgraph/databases/neo4j/neo4j.py"}