{".class":"MypyFile","_fullname":"pint.delegates.txt_defparser.plain","future_import_flags":["annotations"],"is_partial_stub_package":false,"is_stub":false,"names":{".class":"SymbolTable","AliasDefinition":{".class":"SymbolTableNode","kind":"Gdef","node":{".class":"TypeInfo","_promote":[],"abstract_attributes":[],"alt_promote":null,"bases":["pint.delegates.base_defparser.PintParsedStatement","pint.facets.plain.definitions.AliasDefinition"],"dataclass_transform_spec":null,"declared_metaclass":null,"defn":{".class":"ClassDef","fullname":"pint.delegates.txt_defparser.plain.AliasDefinition","name":"AliasDefinition","type_vars":[]},"deletable_attributes":[],"deprecated":null,"flags":[],"fullname":"pint.delegates.txt_defparser.plain.AliasDefinition","has_param_spec_type":false,"metaclass_type":null,"metadata":{"dataclass":{"attributes":[{"alias":null,"column":4,"has_default":false,"is_in_init":true,"is_init_var":false,"is_neither_frozen_nor_nonfrozen":false,"kw_only":false,"line":267,"name":"name","type":"builtins.str"},{"alias":null,"column":4,"has_default":false,"is_in_init":true,"is_init_var":false,"is_neither_frozen_nor_nonfrozen":false,"kw_only":false,"line":269,"name":"aliases","type":{".class":"Instance","args":["builtins.str"],"extra_attrs":null,"type_ref":"builtins.tuple"}},{"alias":null,"column":4,"has_default":true,"is_in_init":false,"is_init_var":false,"is_neither_frozen_nor_nonfrozen":false,"kw_only":false,"line":162,"name":"is_position_set","type":"builtins.bool"},{"alias":null,"column":4,"has_default":true,"is_in_init":false,"is_init_var":false,"is_neither_frozen_nor_nonfrozen":false,"kw_only":false,"line":164,"name":"start_line","type":"builtins.int"},{"alias":null,"column":4,"has_default":true,"is_in_init":false,"is_init_var":false,"is_neither_frozen_nor_nonfrozen":false,"kw_only":false,"line":165,"name":"start_col","type":"builtins.int"},{"alias":null,"column":4,"has_default":true,"is_in_init":false,"is_init_var":false,"is_neither_frozen_nor_nonfrozen":false,"kw_only":false,"line":167,"name":"end_line","type":"builtins.int"},{"alias":null,"column":4,"has_default":true,"is_in_init":false,"is_init_var":false,"is_neither_frozen_nor_nonfrozen":false,"kw_only":false,"line":168,"name":"end_col","type":"builtins.int"},{"alias":null,"column":4,"has_default":true,"is_in_init":false,"is_init_var":false,"is_neither_frozen_nor_nonfrozen":false,"kw_only":false,"line":170,"name":"raw","type":{".class":"UnionType","items":["builtins.str",{".class":"NoneType"}],"uses_pep604_syntax":false}}],"frozen":true},"dataclass_tag":{}},"module_name":"pint.delegates.txt_defparser.plain","mro":["pint.delegates.txt_defparser.plain.AliasDefinition","pint.delegates.base_defparser.PintParsedStatement","flexparser.flexparser.ParsedStatement","flexparser.flexparser.Statement","pint.facets.plain.definitions.AliasDefinition","pint.errors.WithDefErr","builtins.object"],"names":{".class":"SymbolTable","__dataclass_fields__":{".class":"SymbolTableNode","kind":"Mdef","node":{".class":"Var","flags":["is_classvar","is_ready"],"fullname":"pint.delegates.txt_defparser.plain.AliasDefinition.__dataclass_fields__","name":"__dataclass_fields__","type":{".class":"Instance","args":["builtins.str",{".class":"Instance","args":[{".class":"AnyType","missing_import_name":null,"source_any":null,"type_of_any":2}],"extra_attrs":null,"type_ref":"dataclasses.Field"}],"extra_attrs":null,"type_ref":"builtins.dict"}},"plugin_generated":true},"__init__":{".class":"SymbolTableNode","kind":"Mdef","node":{".class":"FuncDef","abstract_status":0,"arg_kinds":[0,0,0],"arg_names":["self","name","aliases"],"dataclass_transform_spec":null,"deprecated":null,"flags":[],"fullname":"pint.delegates.txt_defparser.plain.AliasDefinition.__init__","name":"__init__","type":{".class":"CallableType","arg_kinds":[0,0,0],"arg_names":["self","name","aliases"],"arg_types":["pint.delegates.txt_defparser.plain.AliasDefinition","builtins.str",{".class":"Instance","args":["builtins.str"],"extra_attrs":null,"type_ref":"builtins.tuple"}],"bound_args":[],"def_extras":{},"fallback":"builtins.function","from_concatenate":false,"implicit":false,"imprecise_arg_kinds":false,"is_ellipsis_args":false,"name":"__init__ of AliasDefinition","ret_type":{".class":"NoneType"},"type_guard":null,"type_is":null,"unpack_kwargs":false,"variables":[]}},"plugin_generated":true},"__match_args__":{".class":"SymbolTableNode","kind":"Mdef","node":{".class":"Var","flags":["is_ready","allow_incompatible_override"],"fullname":"pint.delegates.txt_defparser.plain.AliasDefinition.__match_args__","name":"__match_args__","type":{".class":"TupleType","implicit":false,"items":[{".class":"LiteralType","fallback":"builtins.str","value":"name"},{".class":"LiteralType","fallback":"builtins.str","value":"aliases"}],"partial_fallback":{".class":"Instance","args":[{".class":"AnyType","missing_import_name":null,"source_any":null,"type_of_any":6}],"extra_attrs":null,"type_ref":"builtins.tuple"}}},"plugin_generated":true},"__mypy-replace":{".class":"SymbolTableNode","kind":"Mdef","node":{".class":"Decorator","func":{".class":"FuncDef","abstract_status":0,"arg_kinds":[5,5,5,5,5,5,5,5],"arg_names":["name","aliases","is_position_set","start_line","start_col","end_line","end_col","raw"],"dataclass_transform_spec":null,"deprecated":null,"flags":["is_static","is_decorated"],"fullname":"pint.delegates.txt_defparser.plain.AliasDefinition.__mypy-replace","name":"__mypy-replace","type":{".class":"CallableType","arg_kinds":[5,5,5,5,5,5,5,5],"arg_names":["name","aliases","is_position_set","start_line","start_col","end_line","end_col","raw"],"arg_types":["builtins.str",{".class":"Instance","args":["builtins.str"],"extra_attrs":null,"type_ref":"builtins.tuple"},"builtins.bool","builtins.int","builtins.int","builtins.int","builtins.int",{".class":"UnionType","items":["builtins.str",{".class":"NoneType"}],"uses_pep604_syntax":false}],"bound_args":[],"def_extras":{},"fallback":"builtins.function","from_concatenate":false,"implicit":false,"imprecise_arg_kinds":false,"is_ellipsis_args":false,"name":"__mypy-replace of AliasDefinition","ret_type":{".class":"NoneType"},"type_guard":null,"type_is":null,"unpack_kwargs":false,"variables":[]}},"is_overload":false,"var":{".class":"Var","flags":["is_staticmethod","is_ready"],"fullname":"pint.delegates.txt_defparser.plain.AliasDefinition.__mypy-replace","name":"__mypy-replace","type":{".class":"CallableType","arg_kinds":[5,5,5,5,5,5,5,5],"arg_names":["name","aliases","is_position_set","start_line","start_col","end_line","end_col","raw"],"arg_types":["builtins.str",{".class":"Instance","args":["builtins.str"],"extra_attrs":null,"type_ref":"builtins.tuple"},"builtins.bool","builtins.int","builtins.int","builtins.int","builtins.int",{".class":"UnionType","items":["builtins.str",{".class":"NoneType"}],"uses_pep604_syntax":false}],"bound_args":[],"def_extras":{},"fallback":"builtins.function","from_concatenate":false,"implicit":false,"imprecise_arg_kinds":false,"is_ellipsis_args":false,"name":"__mypy-replace of AliasDefinition","ret_type":{".class":"NoneType"},"type_guard":null,"type_is":null,"unpack_kwargs":false,"variables":[]}}},"plugin_generated":true},"__replace__":{".class":"SymbolTableNode","kind":"Mdef","node":{".class":"FuncDef","abstract_status":0,"arg_kinds":[0,5,5],"arg_names":["self","name","aliases"],"dataclass_transform_spec":null,"deprecated":null,"flags":[],"fullname":"pint.delegates.txt_defparser.plain.AliasDefinition.__replace__","name":"__replace__","type":{".class":"CallableType","arg_kinds":[0,5,5],"arg_names":["self","name","aliases"],"arg_types":["pint.delegates.txt_defparser.plain.AliasDefinition","builtins.str",{".class":"Instance","args":["builtins.str"],"extra_attrs":null,"type_ref":"builtins.tuple"}],"bound_args":[],"def_extras":{},"fallback":"builtins.function","from_concatenate":false,"implicit":false,"imprecise_arg_kinds":false,"is_ellipsis_args":false,"name":"__replace__ of AliasDefinition","ret_type":"pint.delegates.txt_defparser.plain.AliasDefinition","type_guard":null,"type_is":null,"unpack_kwargs":false,"variables":[]}},"plugin_generated":true},"aliases":{".class":"SymbolTableNode","kind":"Mdef","node":{".class":"Var","flags":["is_property","is_ready"],"fullname":"pint.delegates.txt_defparser.plain.AliasDefinition.aliases","name":"aliases","type":{".class":"Instance","args":["builtins.str"],"extra_attrs":null,"type_ref":"builtins.tuple"}}},"end_col":{".class":"SymbolTableNode","kind":"Mdef","node":{".class":"Var","flags":["is_property","is_ready"],"fullname":"pint.delegates.txt_defparser.plain.AliasDefinition.end_col","name":"end_col","type":"builtins.int"}},"end_line":{".class":"SymbolTableNode","kind":"Mdef","node":{".class":"Var","flags":["is_property","is_ready"],"fullname":"pint.delegates.txt_defparser.plain.AliasDefinition.end_line","name":"end_line","type":"builtins.int"}},"from_string":{".class":"SymbolTableNode","kind":"Mdef","node":{".class":"Decorator","func":{".class":"FuncDef","abstract_status":0,"arg_kinds":[0,0],"arg_names":["cls","s"],"dataclass_transform_spec":null,"deprecated":null,"flags":["is_class","is_decorated"],"fullname":"pint.delegates.txt_defparser.plain.AliasDefinition.from_string","name":"from_string","type":{".class":"CallableType","arg_kinds":[0,0],"arg_names":["cls","s"],"arg_types":[{".class":"TypeType","item":"pint.delegates.txt_defparser.plain.AliasDefinition"},"builtins.str"],"bound_args":[],"def_extras":{"first_arg":"cls"},"fallback":"builtins.function","from_concatenate":false,"implicit":false,"imprecise_arg_kinds":false,"is_ellipsis_args":false,"name":"from_string of AliasDefinition","ret_type":{".class":"TypeAliasType","args":["pint.delegates.txt_defparser.plain.AliasDefinition"],"type_ref":"flexparser.flexparser.NullableParsedResult"},"type_guard":null,"type_is":null,"unpack_kwargs":false,"variables":[]}},"is_overload":false,"var":{".class":"Var","flags":["is_initialized_in_class","is_classmethod","is_ready","is_inferred"],"fullname":"pint.delegates.txt_defparser.plain.AliasDefinition.from_string","name":"from_string","type":{".class":"CallableType","arg_kinds":[0,0],"arg_names":["cls","s"],"arg_types":[{".class":"TypeType","item":"pint.delegates.txt_defparser.plain.AliasDefinition"},"builtins.str"],"bound_args":[],"def_extras":{"first_arg":"cls"},"fallback":"builtins.function","from_concatenate":false,"implicit":false,"imprecise_arg_kinds":false,"is_ellipsis_args":false,"name":"from_string of AliasDefinition","ret_type":{".class":"TypeAliasType","args":["pint.delegates.txt_defparser.plain.AliasDefinition"],"type_ref":"flexparser.flexparser.NullableParsedResult"},"type_guard":null,"type_is":null,"unpack_kwargs":false,"variables":[]}}}},"is_position_set":{".class":"SymbolTableNode","kind":"Mdef","node":{".class":"Var","flags":["is_property","is_ready"],"fullname":"pint.delegates.txt_defparser.plain.AliasDefinition.is_position_set","name":"is_position_set","type":"builtins.bool"}},"name":{".class":"SymbolTableNode","kind":"Mdef","node":{".class":"Var","flags":["is_property","is_ready"],"fullname":"pint.delegates.txt_defparser.plain.AliasDefinition.name","name":"name","type":"builtins.str"}},"raw":{".class":"SymbolTableNode","kind":"Mdef","node":{".class":"Var","flags":["is_property","is_ready"],"fullname":"pint.delegates.txt_defparser.plain.AliasDefinition.raw","name":"raw","type":{".class":"UnionType","items":["builtins.str",{".class":"NoneType"}],"uses_pep604_syntax":false}}},"start_col":{".class":"SymbolTableNode","kind":"Mdef","node":{".class":"Var","flags":["is_property","is_ready"],"fullname":"pint.delegates.txt_defparser.plain.AliasDefinition.start_col","name":"start_col","type":"builtins.int"}},"start_line":{".class":"SymbolTableNode","kind":"Mdef","node":{".class":"Var","flags":["is_property","is_ready"],"fullname":"pint.delegates.txt_defparser.plain.AliasDefinition.start_line","name":"start_line","type":"builtins.int"}}},"self_type":{".class":"TypeVarType","default":{".class":"AnyType","missing_import_name":null,"source_any":null,"type_of_any":4},"fullname":"pint.delegates.txt_defparser.plain.AliasDefinition.Self","id":0,"name":"Self","namespace":"","upper_bound":"pint.delegates.txt_defparser.plain.AliasDefinition","values":[],"variance":0},"slots":null,"tuple_type":null,"type_vars":[],"typeddict_type":null}},"CommentDefinition":{".class":"SymbolTableNode","kind":"Gdef","node":{".class":"TypeInfo","_promote":[],"abstract_attributes":[],"alt_promote":null,"bases":["pint.delegates.base_defparser.PintParsedStatement","pint.facets.plain.definitions.CommentDefinition"],"dataclass_transform_spec":null,"declared_metaclass":null,"defn":{".class":"ClassDef","fullname":"pint.delegates.txt_defparser.plain.CommentDefinition","name":"CommentDefinition","type_vars":[]},"deletable_attributes":[],"deprecated":null,"flags":[],"fullname":"pint.delegates.txt_defparser.plain.CommentDefinition","has_param_spec_type":false,"metaclass_type":null,"metadata":{"dataclass":{"attributes":[{"alias":null,"column":4,"has_default":false,"is_in_init":true,"is_init_var":false,"is_neither_frozen_nor_nonfrozen":false,"kw_only":false,"line":54,"name":"comment","type":"builtins.str"},{"alias":null,"column":4,"has_default":true,"is_in_init":false,"is_init_var":false,"is_neither_frozen_nor_nonfrozen":false,"kw_only":false,"line":162,"name":"is_position_set","type":"builtins.bool"},{"alias":null,"column":4,"has_default":true,"is_in_init":false,"is_init_var":false,"is_neither_frozen_nor_nonfrozen":false,"kw_only":false,"line":164,"name":"start_line","type":"builtins.int"},{"alias":null,"column":4,"has_default":true,"is_in_init":false,"is_init_var":false,"is_neither_frozen_nor_nonfrozen":false,"kw_only":false,"line":165,"name":"start_col","type":"builtins.int"},{"alias":null,"column":4,"has_default":true,"is_in_init":false,"is_init_var":false,"is_neither_frozen_nor_nonfrozen":false,"kw_only":false,"line":167,"name":"end_line","type":"builtins.int"},{"alias":null,"column":4,"has_default":true,"is_in_init":false,"is_init_var":false,"is_neither_frozen_nor_nonfrozen":false,"kw_only":false,"line":168,"name":"end_col","type":"builtins.int"},{"alias":null,"column":4,"has_default":true,"is_in_init":false,"is_init_var":false,"is_neither_frozen_nor_nonfrozen":false,"kw_only":false,"line":170,"name":"raw","type":{".class":"UnionType","items":["builtins.str",{".class":"NoneType"}],"uses_pep604_syntax":false}}],"frozen":true},"dataclass_tag":{}},"module_name":"pint.delegates.txt_defparser.plain","mro":["pint.delegates.txt_defparser.plain.CommentDefinition","pint.delegates.base_defparser.PintParsedStatement","flexparser.flexparser.ParsedStatement","flexparser.flexparser.Statement","pint.facets.plain.definitions.CommentDefinition","builtins.object"],"names":{".class":"SymbolTable","__dataclass_fields__":{".class":"SymbolTableNode","kind":"Mdef","node":{".class":"Var","flags":["is_classvar","is_ready"],"fullname":"pint.delegates.txt_defparser.plain.CommentDefinition.__dataclass_fields__","name":"__dataclass_fields__","type":{".class":"Instance","args":["builtins.str",{".class":"Instance","args":[{".class":"AnyType","missing_import_name":null,"source_any":null,"type_of_any":2}],"extra_attrs":null,"type_ref":"dataclasses.Field"}],"extra_attrs":null,"type_ref":"builtins.dict"}},"plugin_generated":true},"__init__":{".class":"SymbolTableNode","kind":"Mdef","node":{".class":"FuncDef","abstract_status":0,"arg_kinds":[0,0],"arg_names":["self","comment"],"dataclass_transform_spec":null,"deprecated":null,"flags":[],"fullname":"pint.delegates.txt_defparser.plain.CommentDefinition.__init__","name":"__init__","type":{".class":"CallableType","arg_kinds":[0,0],"arg_names":["self","comment"],"arg_types":["pint.delegates.txt_defparser.plain.CommentDefinition","builtins.str"],"bound_args":[],"def_extras":{},"fallback":"builtins.function","from_concatenate":false,"implicit":false,"imprecise_arg_kinds":false,"is_ellipsis_args":false,"name":"__init__ of CommentDefinition","ret_type":{".class":"NoneType"},"type_guard":null,"type_is":null,"unpack_kwargs":false,"variables":[]}},"plugin_generated":true},"__match_args__":{".class":"SymbolTableNode","kind":"Mdef","node":{".class":"Var","flags":["is_ready","allow_incompatible_override"],"fullname":"pint.delegates.txt_defparser.plain.CommentDefinition.__match_args__","name":"__match_args__","type":{".class":"TupleType","implicit":false,"items":[{".class":"LiteralType","fallback":"builtins.str","value":"comment"}],"partial_fallback":{".class":"Instance","args":[{".class":"AnyType","missing_import_name":null,"source_any":null,"type_of_any":6}],"extra_attrs":null,"type_ref":"builtins.tuple"}}},"plugin_generated":true},"__mypy-replace":{".class":"SymbolTableNode","kind":"Mdef","node":{".class":"Decorator","func":{".class":"FuncDef","abstract_status":0,"arg_kinds":[5,5,5,5,5,5,5],"arg_names":["comment","is_position_set","start_line","start_col","end_line","end_col","raw"],"dataclass_transform_spec":null,"deprecated":null,"flags":["is_static","is_decorated"],"fullname":"pint.delegates.txt_defparser.plain.CommentDefinition.__mypy-replace","name":"__mypy-replace","type":{".class":"CallableType","arg_kinds":[5,5,5,5,5,5,5],"arg_names":["comment","is_position_set","start_line","start_col","end_line","end_col","raw"],"arg_types":["builtins.str","builtins.bool","builtins.int","builtins.int","builtins.int","builtins.int",{".class":"UnionType","items":["builtins.str",{".class":"NoneType"}],"uses_pep604_syntax":false}],"bound_args":[],"def_extras":{},"fallback":"builtins.function","from_concatenate":false,"implicit":false,"imprecise_arg_kinds":false,"is_ellipsis_args":false,"name":"__mypy-replace of CommentDefinition","ret_type":{".class":"NoneType"},"type_guard":null,"type_is":null,"unpack_kwargs":false,"variables":[]}},"is_overload":false,"var":{".class":"Var","flags":["is_staticmethod","is_ready"],"fullname":"pint.delegates.txt_defparser.plain.CommentDefinition.__mypy-replace","name":"__mypy-replace","type":{".class":"CallableType","arg_kinds":[5,5,5,5,5,5,5],"arg_names":["comment","is_position_set","start_line","start_col","end_line","end_col","raw"],"arg_types":["builtins.str","builtins.bool","builtins.int","builtins.int","builtins.int","builtins.int",{".class":"UnionType","items":["builtins.str",{".class":"NoneType"}],"uses_pep604_syntax":false}],"bound_args":[],"def_extras":{},"fallback":"builtins.function","from_concatenate":false,"implicit":false,"imprecise_arg_kinds":false,"is_ellipsis_args":false,"name":"__mypy-replace of CommentDefinition","ret_type":{".class":"NoneType"},"type_guard":null,"type_is":null,"unpack_kwargs":false,"variables":[]}}},"plugin_generated":true},"__replace__":{".class":"SymbolTableNode","kind":"Mdef","node":{".class":"FuncDef","abstract_status":0,"arg_kinds":[0,5],"arg_names":["self","comment"],"dataclass_transform_spec":null,"deprecated":null,"flags":[],"fullname":"pint.delegates.txt_defparser.plain.CommentDefinition.__replace__","name":"__replace__","type":{".class":"CallableType","arg_kinds":[0,5],"arg_names":["self","comment"],"arg_types":["pint.delegates.txt_defparser.plain.CommentDefinition","builtins.str"],"bound_args":[],"def_extras":{},"fallback":"builtins.function","from_concatenate":false,"implicit":false,"imprecise_arg_kinds":false,"is_ellipsis_args":false,"name":"__replace__ of CommentDefinition","ret_type":"pint.delegates.txt_defparser.plain.CommentDefinition","type_guard":null,"type_is":null,"unpack_kwargs":false,"variables":[]}},"plugin_generated":true},"comment":{".class":"SymbolTableNode","kind":"Mdef","node":{".class":"Var","flags":["is_property","is_ready"],"fullname":"pint.delegates.txt_defparser.plain.CommentDefinition.comment","name":"comment","type":"builtins.str"}},"end_col":{".class":"SymbolTableNode","kind":"Mdef","node":{".class":"Var","flags":["is_property","is_ready"],"fullname":"pint.delegates.txt_defparser.plain.CommentDefinition.end_col","name":"end_col","type":"builtins.int"}},"end_line":{".class":"SymbolTableNode","kind":"Mdef","node":{".class":"Var","flags":["is_property","is_ready"],"fullname":"pint.delegates.txt_defparser.plain.CommentDefinition.end_line","name":"end_line","type":"builtins.int"}},"from_string":{".class":"SymbolTableNode","kind":"Mdef","node":{".class":"Decorator","func":{".class":"FuncDef","abstract_status":0,"arg_kinds":[0,0],"arg_names":["cls","s"],"dataclass_transform_spec":null,"deprecated":null,"flags":["is_class","is_decorated"],"fullname":"pint.delegates.txt_defparser.plain.CommentDefinition.from_string","name":"from_string","type":{".class":"CallableType","arg_kinds":[0,0],"arg_names":["cls","s"],"arg_types":[{".class":"TypeType","item":"pint.delegates.txt_defparser.plain.CommentDefinition"},"builtins.str"],"bound_args":[],"def_extras":{"first_arg":"cls"},"fallback":"builtins.function","from_concatenate":false,"implicit":false,"imprecise_arg_kinds":false,"is_ellipsis_args":false,"name":"from_string of CommentDefinition","ret_type":{".class":"TypeAliasType","args":["pint.delegates.txt_defparser.plain.CommentDefinition"],"type_ref":"flexparser.flexparser.NullableParsedResult"},"type_guard":null,"type_is":null,"unpack_kwargs":false,"variables":[]}},"is_overload":false,"var":{".class":"Var","flags":["is_initialized_in_class","is_classmethod","is_ready","is_inferred"],"fullname":"pint.delegates.txt_defparser.plain.CommentDefinition.from_string","name":"from_string","type":{".class":"CallableType","arg_kinds":[0,0],"arg_names":["cls","s"],"arg_types":[{".class":"TypeType","item":"pint.delegates.txt_defparser.plain.CommentDefinition"},"builtins.str"],"bound_args":[],"def_extras":{"first_arg":"cls"},"fallback":"builtins.function","from_concatenate":false,"implicit":false,"imprecise_arg_kinds":false,"is_ellipsis_args":false,"name":"from_string of CommentDefinition","ret_type":{".class":"TypeAliasType","args":["pint.delegates.txt_defparser.plain.CommentDefinition"],"type_ref":"flexparser.flexparser.NullableParsedResult"},"type_guard":null,"type_is":null,"unpack_kwargs":false,"variables":[]}}}},"is_position_set":{".class":"SymbolTableNode","kind":"Mdef","node":{".class":"Var","flags":["is_property","is_ready"],"fullname":"pint.delegates.txt_defparser.plain.CommentDefinition.is_position_set","name":"is_position_set","type":"builtins.bool"}},"raw":{".class":"SymbolTableNode","kind":"Mdef","node":{".class":"Var","flags":["is_property","is_ready"],"fullname":"pint.delegates.txt_defparser.plain.CommentDefinition.raw","name":"raw","type":{".class":"UnionType","items":["builtins.str",{".class":"NoneType"}],"uses_pep604_syntax":false}}},"start_col":{".class":"SymbolTableNode","kind":"Mdef","node":{".class":"Var","flags":["is_property","is_ready"],"fullname":"pint.delegates.txt_defparser.plain.CommentDefinition.start_col","name":"start_col","type":"builtins.int"}},"start_line":{".class":"SymbolTableNode","kind":"Mdef","node":{".class":"Var","flags":["is_property","is_ready"],"fullname":"pint.delegates.txt_defparser.plain.CommentDefinition.start_line","name":"start_line","type":"builtins.int"}}},"self_type":{".class":"TypeVarType","default":{".class":"AnyType","missing_import_name":null,"source_any":null,"type_of_any":4},"fullname":"pint.delegates.txt_defparser.plain.CommentDefinition.Self","id":0,"name":"Self","namespace":"","upper_bound":"pint.delegates.txt_defparser.plain.CommentDefinition","values":[],"variance":0},"slots":null,"tuple_type":null,"type_vars":[],"typeddict_type":null}},"Converter":{".class":"SymbolTableNode","cross_ref":"pint.converters.Converter","kind":"Gdef"},"DerivedDimensionDefinition":{".class":"SymbolTableNode","kind":"Gdef","node":{".class":"TypeInfo","_promote":[],"abstract_attributes":[],"alt_promote":null,"bases":["pint.delegates.base_defparser.PintParsedStatement","pint.facets.plain.definitions.DerivedDimensionDefinition"],"dataclass_transform_spec":null,"declared_metaclass":null,"defn":{".class":"ClassDef","fullname":"pint.delegates.txt_defparser.plain.DerivedDimensionDefinition","name":"DerivedDimensionDefinition","type_vars":[]},"deletable_attributes":[],"deprecated":null,"flags":[],"fullname":"pint.delegates.txt_defparser.plain.DerivedDimensionDefinition","has_param_spec_type":false,"metaclass_type":null,"metadata":{"dataclass":{"attributes":[{"alias":null,"column":4,"has_default":false,"is_in_init":true,"is_init_var":false,"is_neither_frozen_nor_nonfrozen":false,"kw_only":false,"line":74,"name":"name","type":"builtins.str"},{"alias":null,"column":4,"has_default":false,"is_in_init":true,"is_init_var":false,"is_neither_frozen_nor_nonfrozen":false,"kw_only":false,"line":236,"name":"reference","type":"pint.util.UnitsContainer"},{"alias":null,"column":4,"has_default":true,"is_in_init":false,"is_init_var":false,"is_neither_frozen_nor_nonfrozen":false,"kw_only":false,"line":162,"name":"is_position_set","type":"builtins.bool"},{"alias":null,"column":4,"has_default":true,"is_in_init":false,"is_init_var":false,"is_neither_frozen_nor_nonfrozen":false,"kw_only":false,"line":164,"name":"start_line","type":"builtins.int"},{"alias":null,"column":4,"has_default":true,"is_in_init":false,"is_init_var":false,"is_neither_frozen_nor_nonfrozen":false,"kw_only":false,"line":165,"name":"start_col","type":"builtins.int"},{"alias":null,"column":4,"has_default":true,"is_in_init":false,"is_init_var":false,"is_neither_frozen_nor_nonfrozen":false,"kw_only":false,"line":167,"name":"end_line","type":"builtins.int"},{"alias":null,"column":4,"has_default":true,"is_in_init":false,"is_init_var":false,"is_neither_frozen_nor_nonfrozen":false,"kw_only":false,"line":168,"name":"end_col","type":"builtins.int"},{"alias":null,"column":4,"has_default":true,"is_in_init":false,"is_init_var":false,"is_neither_frozen_nor_nonfrozen":false,"kw_only":false,"line":170,"name":"raw","type":{".class":"UnionType","items":["builtins.str",{".class":"NoneType"}],"uses_pep604_syntax":false}}],"frozen":true},"dataclass_tag":{}},"module_name":"pint.delegates.txt_defparser.plain","mro":["pint.delegates.txt_defparser.plain.DerivedDimensionDefinition","pint.delegates.base_defparser.PintParsedStatement","flexparser.flexparser.ParsedStatement","flexparser.flexparser.Statement","pint.facets.plain.definitions.DerivedDimensionDefinition","pint.facets.plain.definitions.DimensionDefinition","pint.facets.plain.definitions.NamedDefinition","pint.errors.WithDefErr","builtins.object"],"names":{".class":"SymbolTable","__dataclass_fields__":{".class":"SymbolTableNode","kind":"Mdef","node":{".class":"Var","flags":["is_classvar","is_ready"],"fullname":"pint.delegates.txt_defparser.plain.DerivedDimensionDefinition.__dataclass_fields__","name":"__dataclass_fields__","type":{".class":"Instance","args":["builtins.str",{".class":"Instance","args":[{".class":"AnyType","missing_import_name":null,"source_any":null,"type_of_any":2}],"extra_attrs":null,"type_ref":"dataclasses.Field"}],"extra_attrs":null,"type_ref":"builtins.dict"}},"plugin_generated":true},"__init__":{".class":"SymbolTableNode","kind":"Mdef","node":{".class":"FuncDef","abstract_status":0,"arg_kinds":[0,0,0],"arg_names":["self","name","reference"],"dataclass_transform_spec":null,"deprecated":null,"flags":[],"fullname":"pint.delegates.txt_defparser.plain.DerivedDimensionDefinition.__init__","name":"__init__","type":{".class":"CallableType","arg_kinds":[0,0,0],"arg_names":["self","name","reference"],"arg_types":["pint.delegates.txt_defparser.plain.DerivedDimensionDefinition","builtins.str","pint.util.UnitsContainer"],"bound_args":[],"def_extras":{},"fallback":"builtins.function","from_concatenate":false,"implicit":false,"imprecise_arg_kinds":false,"is_ellipsis_args":false,"name":"__init__ of DerivedDimensionDefinition","ret_type":{".class":"NoneType"},"type_guard":null,"type_is":null,"unpack_kwargs":false,"variables":[]}},"plugin_generated":true},"__match_args__":{".class":"SymbolTableNode","kind":"Mdef","node":{".class":"Var","flags":["is_ready","allow_incompatible_override"],"fullname":"pint.delegates.txt_defparser.plain.DerivedDimensionDefinition.__match_args__","name":"__match_args__","type":{".class":"TupleType","implicit":false,"items":[{".class":"LiteralType","fallback":"builtins.str","value":"name"},{".class":"LiteralType","fallback":"builtins.str","value":"reference"}],"partial_fallback":{".class":"Instance","args":[{".class":"AnyType","missing_import_name":null,"source_any":null,"type_of_any":6}],"extra_attrs":null,"type_ref":"builtins.tuple"}}},"plugin_generated":true},"__mypy-replace":{".class":"SymbolTableNode","kind":"Mdef","node":{".class":"Decorator","func":{".class":"FuncDef","abstract_status":0,"arg_kinds":[5,5,5,5,5,5,5,5],"arg_names":["name","reference","is_position_set","start_line","start_col","end_line","end_col","raw"],"dataclass_transform_spec":null,"deprecated":null,"flags":["is_static","is_decorated"],"fullname":"pint.delegates.txt_defparser.plain.DerivedDimensionDefinition.__mypy-replace","name":"__mypy-replace","type":{".class":"CallableType","arg_kinds":[5,5,5,5,5,5,5,5],"arg_names":["name","reference","is_position_set","start_line","start_col","end_line","end_col","raw"],"arg_types":["builtins.str","pint.util.UnitsContainer","builtins.bool","builtins.int","builtins.int","builtins.int","builtins.int",{".class":"UnionType","items":["builtins.str",{".class":"NoneType"}],"uses_pep604_syntax":false}],"bound_args":[],"def_extras":{},"fallback":"builtins.function","from_concatenate":false,"implicit":false,"imprecise_arg_kinds":false,"is_ellipsis_args":false,"name":"__mypy-replace of DerivedDimensionDefinition","ret_type":{".class":"NoneType"},"type_guard":null,"type_is":null,"unpack_kwargs":false,"variables":[]}},"is_overload":false,"var":{".class":"Var","flags":["is_staticmethod","is_ready"],"fullname":"pint.delegates.txt_defparser.plain.DerivedDimensionDefinition.__mypy-replace","name":"__mypy-replace","type":{".class":"CallableType","arg_kinds":[5,5,5,5,5,5,5,5],"arg_names":["name","reference","is_position_set","start_line","start_col","end_line","end_col","raw"],"arg_types":["builtins.str","pint.util.UnitsContainer","builtins.bool","builtins.int","builtins.int","builtins.int","builtins.int",{".class":"UnionType","items":["builtins.str",{".class":"NoneType"}],"uses_pep604_syntax":false}],"bound_args":[],"def_extras":{},"fallback":"builtins.function","from_concatenate":false,"implicit":false,"imprecise_arg_kinds":false,"is_ellipsis_args":false,"name":"__mypy-replace of DerivedDimensionDefinition","ret_type":{".class":"NoneType"},"type_guard":null,"type_is":null,"unpack_kwargs":false,"variables":[]}}},"plugin_generated":true},"__replace__":{".class":"SymbolTableNode","kind":"Mdef","node":{".class":"FuncDef","abstract_status":0,"arg_kinds":[0,5,5],"arg_names":["self","name","reference"],"dataclass_transform_spec":null,"deprecated":null,"flags":[],"fullname":"pint.delegates.txt_defparser.plain.DerivedDimensionDefinition.__replace__","name":"__replace__","type":{".class":"CallableType","arg_kinds":[0,5,5],"arg_names":["self","name","reference"],"arg_types":["pint.delegates.txt_defparser.plain.DerivedDimensionDefinition","builtins.str","pint.util.UnitsContainer"],"bound_args":[],"def_extras":{},"fallback":"builtins.function","from_concatenate":false,"implicit":false,"imprecise_arg_kinds":false,"is_ellipsis_args":false,"name":"__replace__ of DerivedDimensionDefinition","ret_type":"pint.delegates.txt_defparser.plain.DerivedDimensionDefinition","type_guard":null,"type_is":null,"unpack_kwargs":false,"variables":[]}},"plugin_generated":true},"end_col":{".class":"SymbolTableNode","kind":"Mdef","node":{".class":"Var","flags":["is_property","is_ready"],"fullname":"pint.delegates.txt_defparser.plain.DerivedDimensionDefinition.end_col","name":"end_col","type":"builtins.int"}},"end_line":{".class":"SymbolTableNode","kind":"Mdef","node":{".class":"Var","flags":["is_property","is_ready"],"fullname":"pint.delegates.txt_defparser.plain.DerivedDimensionDefinition.end_line","name":"end_line","type":"builtins.int"}},"from_string_and_config":{".class":"SymbolTableNode","kind":"Mdef","node":{".class":"Decorator","func":{".class":"FuncDef","abstract_status":0,"arg_kinds":[0,0,0],"arg_names":["cls","s","config"],"dataclass_transform_spec":null,"deprecated":null,"flags":["is_class","is_decorated"],"fullname":"pint.delegates.txt_defparser.plain.DerivedDimensionDefinition.from_string_and_config","name":"from_string_and_config","type":{".class":"CallableType","arg_kinds":[0,0,0],"arg_names":["cls","s","config"],"arg_types":[{".class":"TypeType","item":"pint.delegates.txt_defparser.plain.DerivedDimensionDefinition"},"builtins.str","pint.delegates.base_defparser.ParserConfig"],"bound_args":[],"def_extras":{"first_arg":"cls"},"fallback":"builtins.function","from_concatenate":false,"implicit":false,"imprecise_arg_kinds":false,"is_ellipsis_args":false,"name":"from_string_and_config of DerivedDimensionDefinition","ret_type":{".class":"TypeAliasType","args":["pint.delegates.txt_defparser.plain.DerivedDimensionDefinition"],"type_ref":"flexparser.flexparser.NullableParsedResult"},"type_guard":null,"type_is":null,"unpack_kwargs":false,"variables":[]}},"is_overload":false,"var":{".class":"Var","flags":["is_initialized_in_class","is_classmethod","is_ready","is_inferred"],"fullname":"pint.delegates.txt_defparser.plain.DerivedDimensionDefinition.from_string_and_config","name":"from_string_and_config","type":{".class":"CallableType","arg_kinds":[0,0,0],"arg_names":["cls","s","config"],"arg_types":[{".class":"TypeType","item":"pint.delegates.txt_defparser.plain.DerivedDimensionDefinition"},"builtins.str","pint.delegates.base_defparser.ParserConfig"],"bound_args":[],"def_extras":{"first_arg":"cls"},"fallback":"builtins.function","from_concatenate":false,"implicit":false,"imprecise_arg_kinds":false,"is_ellipsis_args":false,"name":"from_string_and_config of DerivedDimensionDefinition","ret_type":{".class":"TypeAliasType","args":["pint.delegates.txt_defparser.plain.DerivedDimensionDefinition"],"type_ref":"flexparser.flexparser.NullableParsedResult"},"type_guard":null,"type_is":null,"unpack_kwargs":false,"variables":[]}}}},"is_position_set":{".class":"SymbolTableNode","kind":"Mdef","node":{".class":"Var","flags":["is_property","is_ready"],"fullname":"pint.delegates.txt_defparser.plain.DerivedDimensionDefinition.is_position_set","name":"is_position_set","type":"builtins.bool"}},"name":{".class":"SymbolTableNode","kind":"Mdef","node":{".class":"Var","flags":["is_property","is_ready"],"fullname":"pint.delegates.txt_defparser.plain.DerivedDimensionDefinition.name","name":"name","type":"builtins.str"}},"raw":{".class":"SymbolTableNode","kind":"Mdef","node":{".class":"Var","flags":["is_property","is_ready"],"fullname":"pint.delegates.txt_defparser.plain.DerivedDimensionDefinition.raw","name":"raw","type":{".class":"UnionType","items":["builtins.str",{".class":"NoneType"}],"uses_pep604_syntax":false}}},"reference":{".class":"SymbolTableNode","kind":"Mdef","node":{".class":"Var","flags":["is_property","is_ready"],"fullname":"pint.delegates.txt_defparser.plain.DerivedDimensionDefinition.reference","name":"reference","type":"pint.util.UnitsContainer"}},"start_col":{".class":"SymbolTableNode","kind":"Mdef","node":{".class":"Var","flags":["is_property","is_ready"],"fullname":"pint.delegates.txt_defparser.plain.DerivedDimensionDefinition.start_col","name":"start_col","type":"builtins.int"}},"start_line":{".class":"SymbolTableNode","kind":"Mdef","node":{".class":"Var","flags":["is_property","is_ready"],"fullname":"pint.delegates.txt_defparser.plain.DerivedDimensionDefinition.start_line","name":"start_line","type":"builtins.int"}}},"self_type":{".class":"TypeVarType","default":{".class":"AnyType","missing_import_name":null,"source_any":null,"type_of_any":4},"fullname":"pint.delegates.txt_defparser.plain.DerivedDimensionDefinition.Self","id":0,"name":"Self","namespace":"","upper_bound":"pint.delegates.txt_defparser.plain.DerivedDimensionDefinition","values":[],"variance":0},"slots":null,"tuple_type":null,"type_vars":[],"typeddict_type":null}},"DimensionDefinition":{".class":"SymbolTableNode","kind":"Gdef","node":{".class":"TypeInfo","_promote":[],"abstract_attributes":[],"alt_promote":null,"bases":["pint.delegates.base_defparser.PintParsedStatement","pint.facets.plain.definitions.DimensionDefinition"],"dataclass_transform_spec":null,"declared_metaclass":null,"defn":{".class":"ClassDef","fullname":"pint.delegates.txt_defparser.plain.DimensionDefinition","name":"DimensionDefinition","type_vars":[]},"deletable_attributes":[],"deprecated":null,"flags":[],"fullname":"pint.delegates.txt_defparser.plain.DimensionDefinition","has_param_spec_type":false,"metaclass_type":null,"metadata":{"dataclass":{"attributes":[{"alias":null,"column":4,"has_default":false,"is_in_init":true,"is_init_var":false,"is_neither_frozen_nor_nonfrozen":false,"kw_only":false,"line":74,"name":"name","type":"builtins.str"},{"alias":null,"column":4,"has_default":true,"is_in_init":false,"is_init_var":false,"is_neither_frozen_nor_nonfrozen":false,"kw_only":false,"line":162,"name":"is_position_set","type":"builtins.bool"},{"alias":null,"column":4,"has_default":true,"is_in_init":false,"is_init_var":false,"is_neither_frozen_nor_nonfrozen":false,"kw_only":false,"line":164,"name":"start_line","type":"builtins.int"},{"alias":null,"column":4,"has_default":true,"is_in_init":false,"is_init_var":false,"is_neither_frozen_nor_nonfrozen":false,"kw_only":false,"line":165,"name":"start_col","type":"builtins.int"},{"alias":null,"column":4,"has_default":true,"is_in_init":false,"is_init_var":false,"is_neither_frozen_nor_nonfrozen":false,"kw_only":false,"line":167,"name":"end_line","type":"builtins.int"},{"alias":null,"column":4,"has_default":true,"is_in_init":false,"is_init_var":false,"is_neither_frozen_nor_nonfrozen":false,"kw_only":false,"line":168,"name":"end_col","type":"builtins.int"},{"alias":null,"column":4,"has_default":true,"is_in_init":false,"is_init_var":false,"is_neither_frozen_nor_nonfrozen":false,"kw_only":false,"line":170,"name":"raw","type":{".class":"UnionType","items":["builtins.str",{".class":"NoneType"}],"uses_pep604_syntax":false}}],"frozen":true},"dataclass_tag":{}},"module_name":"pint.delegates.txt_defparser.plain","mro":["pint.delegates.txt_defparser.plain.DimensionDefinition","pint.delegates.base_defparser.PintParsedStatement","flexparser.flexparser.ParsedStatement","flexparser.flexparser.Statement","pint.facets.plain.definitions.DimensionDefinition","pint.facets.plain.definitions.NamedDefinition","pint.errors.WithDefErr","builtins.object"],"names":{".class":"SymbolTable","__dataclass_fields__":{".class":"SymbolTableNode","kind":"Mdef","node":{".class":"Var","flags":["is_classvar","is_ready"],"fullname":"pint.delegates.txt_defparser.plain.DimensionDefinition.__dataclass_fields__","name":"__dataclass_fields__","type":{".class":"Instance","args":["builtins.str",{".class":"Instance","args":[{".class":"AnyType","missing_import_name":null,"source_any":null,"type_of_any":2}],"extra_attrs":null,"type_ref":"dataclasses.Field"}],"extra_attrs":null,"type_ref":"builtins.dict"}},"plugin_generated":true},"__init__":{".class":"SymbolTableNode","kind":"Mdef","node":{".class":"FuncDef","abstract_status":0,"arg_kinds":[0,0],"arg_names":["self","name"],"dataclass_transform_spec":null,"deprecated":null,"flags":[],"fullname":"pint.delegates.txt_defparser.plain.DimensionDefinition.__init__","name":"__init__","type":{".class":"CallableType","arg_kinds":[0,0],"arg_names":["self","name"],"arg_types":["pint.delegates.txt_defparser.plain.DimensionDefinition","builtins.str"],"bound_args":[],"def_extras":{},"fallback":"builtins.function","from_concatenate":false,"implicit":false,"imprecise_arg_kinds":false,"is_ellipsis_args":false,"name":"__init__ of DimensionDefinition","ret_type":{".class":"NoneType"},"type_guard":null,"type_is":null,"unpack_kwargs":false,"variables":[]}},"plugin_generated":true},"__match_args__":{".class":"SymbolTableNode","kind":"Mdef","node":{".class":"Var","flags":["is_ready","allow_incompatible_override"],"fullname":"pint.delegates.txt_defparser.plain.DimensionDefinition.__match_args__","name":"__match_args__","type":{".class":"TupleType","implicit":false,"items":[{".class":"LiteralType","fallback":"builtins.str","value":"name"}],"partial_fallback":{".class":"Instance","args":[{".class":"AnyType","missing_import_name":null,"source_any":null,"type_of_any":6}],"extra_attrs":null,"type_ref":"builtins.tuple"}}},"plugin_generated":true},"__mypy-replace":{".class":"SymbolTableNode","kind":"Mdef","node":{".class":"Decorator","func":{".class":"FuncDef","abstract_status":0,"arg_kinds":[5,5,5,5,5,5,5],"arg_names":["name","is_position_set","start_line","start_col","end_line","end_col","raw"],"dataclass_transform_spec":null,"deprecated":null,"flags":["is_static","is_decorated"],"fullname":"pint.delegates.txt_defparser.plain.DimensionDefinition.__mypy-replace","name":"__mypy-replace","type":{".class":"CallableType","arg_kinds":[5,5,5,5,5,5,5],"arg_names":["name","is_position_set","start_line","start_col","end_line","end_col","raw"],"arg_types":["builtins.str","builtins.bool","builtins.int","builtins.int","builtins.int","builtins.int",{".class":"UnionType","items":["builtins.str",{".class":"NoneType"}],"uses_pep604_syntax":false}],"bound_args":[],"def_extras":{},"fallback":"builtins.function","from_concatenate":false,"implicit":false,"imprecise_arg_kinds":false,"is_ellipsis_args":false,"name":"__mypy-replace of DimensionDefinition","ret_type":{".class":"NoneType"},"type_guard":null,"type_is":null,"unpack_kwargs":false,"variables":[]}},"is_overload":false,"var":{".class":"Var","flags":["is_staticmethod","is_ready"],"fullname":"pint.delegates.txt_defparser.plain.DimensionDefinition.__mypy-replace","name":"__mypy-replace","type":{".class":"CallableType","arg_kinds":[5,5,5,5,5,5,5],"arg_names":["name","is_position_set","start_line","start_col","end_line","end_col","raw"],"arg_types":["builtins.str","builtins.bool","builtins.int","builtins.int","builtins.int","builtins.int",{".class":"UnionType","items":["builtins.str",{".class":"NoneType"}],"uses_pep604_syntax":false}],"bound_args":[],"def_extras":{},"fallback":"builtins.function","from_concatenate":false,"implicit":false,"imprecise_arg_kinds":false,"is_ellipsis_args":false,"name":"__mypy-replace of DimensionDefinition","ret_type":{".class":"NoneType"},"type_guard":null,"type_is":null,"unpack_kwargs":false,"variables":[]}}},"plugin_generated":true},"__replace__":{".class":"SymbolTableNode","kind":"Mdef","node":{".class":"FuncDef","abstract_status":0,"arg_kinds":[0,5],"arg_names":["self","name"],"dataclass_transform_spec":null,"deprecated":null,"flags":[],"fullname":"pint.delegates.txt_defparser.plain.DimensionDefinition.__replace__","name":"__replace__","type":{".class":"CallableType","arg_kinds":[0,5],"arg_names":["self","name"],"arg_types":["pint.delegates.txt_defparser.plain.DimensionDefinition","builtins.str"],"bound_args":[],"def_extras":{},"fallback":"builtins.function","from_concatenate":false,"implicit":false,"imprecise_arg_kinds":false,"is_ellipsis_args":false,"name":"__replace__ of DimensionDefinition","ret_type":"pint.delegates.txt_defparser.plain.DimensionDefinition","type_guard":null,"type_is":null,"unpack_kwargs":false,"variables":[]}},"plugin_generated":true},"end_col":{".class":"SymbolTableNode","kind":"Mdef","node":{".class":"Var","flags":["is_property","is_ready"],"fullname":"pint.delegates.txt_defparser.plain.DimensionDefinition.end_col","name":"end_col","type":"builtins.int"}},"end_line":{".class":"SymbolTableNode","kind":"Mdef","node":{".class":"Var","flags":["is_property","is_ready"],"fullname":"pint.delegates.txt_defparser.plain.DimensionDefinition.end_line","name":"end_line","type":"builtins.int"}},"from_string":{".class":"SymbolTableNode","kind":"Mdef","node":{".class":"Decorator","func":{".class":"FuncDef","abstract_status":0,"arg_kinds":[0,0],"arg_names":["cls","s"],"dataclass_transform_spec":null,"deprecated":null,"flags":["is_class","is_decorated"],"fullname":"pint.delegates.txt_defparser.plain.DimensionDefinition.from_string","name":"from_string","type":{".class":"CallableType","arg_kinds":[0,0],"arg_names":["cls","s"],"arg_types":[{".class":"TypeType","item":"pint.delegates.txt_defparser.plain.DimensionDefinition"},"builtins.str"],"bound_args":[],"def_extras":{"first_arg":"cls"},"fallback":"builtins.function","from_concatenate":false,"implicit":false,"imprecise_arg_kinds":false,"is_ellipsis_args":false,"name":"from_string of DimensionDefinition","ret_type":{".class":"TypeAliasType","args":["pint.delegates.txt_defparser.plain.DimensionDefinition"],"type_ref":"flexparser.flexparser.NullableParsedResult"},"type_guard":null,"type_is":null,"unpack_kwargs":false,"variables":[]}},"is_overload":false,"var":{".class":"Var","flags":["is_initialized_in_class","is_classmethod","is_ready","is_inferred"],"fullname":"pint.delegates.txt_defparser.plain.DimensionDefinition.from_string","name":"from_string","type":{".class":"CallableType","arg_kinds":[0,0],"arg_names":["cls","s"],"arg_types":[{".class":"TypeType","item":"pint.delegates.txt_defparser.plain.DimensionDefinition"},"builtins.str"],"bound_args":[],"def_extras":{"first_arg":"cls"},"fallback":"builtins.function","from_concatenate":false,"implicit":false,"imprecise_arg_kinds":false,"is_ellipsis_args":false,"name":"from_string of DimensionDefinition","ret_type":{".class":"TypeAliasType","args":["pint.delegates.txt_defparser.plain.DimensionDefinition"],"type_ref":"flexparser.flexparser.NullableParsedResult"},"type_guard":null,"type_is":null,"unpack_kwargs":false,"variables":[]}}}},"is_position_set":{".class":"SymbolTableNode","kind":"Mdef","node":{".class":"Var","flags":["is_property","is_ready"],"fullname":"pint.delegates.txt_defparser.plain.DimensionDefinition.is_position_set","name":"is_position_set","type":"builtins.bool"}},"name":{".class":"SymbolTableNode","kind":"Mdef","node":{".class":"Var","flags":["is_property","is_ready"],"fullname":"pint.delegates.txt_defparser.plain.DimensionDefinition.name","name":"name","type":"builtins.str"}},"raw":{".class":"SymbolTableNode","kind":"Mdef","node":{".class":"Var","flags":["is_property","is_ready"],"fullname":"pint.delegates.txt_defparser.plain.DimensionDefinition.raw","name":"raw","type":{".class":"UnionType","items":["builtins.str",{".class":"NoneType"}],"uses_pep604_syntax":false}}},"start_col":{".class":"SymbolTableNode","kind":"Mdef","node":{".class":"Var","flags":["is_property","is_ready"],"fullname":"pint.delegates.txt_defparser.plain.DimensionDefinition.start_col","name":"start_col","type":"builtins.int"}},"start_line":{".class":"SymbolTableNode","kind":"Mdef","node":{".class":"Var","flags":["is_property","is_ready"],"fullname":"pint.delegates.txt_defparser.plain.DimensionDefinition.start_line","name":"start_line","type":"builtins.int"}}},"self_type":{".class":"TypeVarType","default":{".class":"AnyType","missing_import_name":null,"source_any":null,"type_of_any":4},"fullname":"pint.delegates.txt_defparser.plain.DimensionDefinition.Self","id":0,"name":"Self","namespace":"","upper_bound":"pint.delegates.txt_defparser.plain.DimensionDefinition","values":[],"variance":0},"slots":null,"tuple_type":null,"type_vars":[],"typeddict_type":null}},"Equality":{".class":"SymbolTableNode","kind":"Gdef","node":{".class":"TypeInfo","_promote":[],"abstract_attributes":[],"alt_promote":null,"bases":["pint.delegates.base_defparser.PintParsedStatement","pint.facets.plain.definitions.Equality"],"dataclass_transform_spec":null,"declared_metaclass":null,"defn":{".class":"ClassDef","fullname":"pint.delegates.txt_defparser.plain.Equality","name":"Equality","type_vars":[]},"deletable_attributes":[],"deprecated":null,"flags":[],"fullname":"pint.delegates.txt_defparser.plain.Equality","has_param_spec_type":false,"metaclass_type":null,"metadata":{"dataclass":{"attributes":[{"alias":null,"column":4,"has_default":false,"is_in_init":true,"is_init_var":false,"is_neither_frozen_nor_nonfrozen":false,"kw_only":false,"line":46,"name":"lhs","type":"builtins.str"},{"alias":null,"column":4,"has_default":false,"is_in_init":true,"is_init_var":false,"is_neither_frozen_nor_nonfrozen":false,"kw_only":false,"line":47,"name":"rhs","type":"builtins.str"},{"alias":null,"column":4,"has_default":true,"is_in_init":false,"is_init_var":false,"is_neither_frozen_nor_nonfrozen":false,"kw_only":false,"line":162,"name":"is_position_set","type":"builtins.bool"},{"alias":null,"column":4,"has_default":true,"is_in_init":false,"is_init_var":false,"is_neither_frozen_nor_nonfrozen":false,"kw_only":false,"line":164,"name":"start_line","type":"builtins.int"},{"alias":null,"column":4,"has_default":true,"is_in_init":false,"is_init_var":false,"is_neither_frozen_nor_nonfrozen":false,"kw_only":false,"line":165,"name":"start_col","type":"builtins.int"},{"alias":null,"column":4,"has_default":true,"is_in_init":false,"is_init_var":false,"is_neither_frozen_nor_nonfrozen":false,"kw_only":false,"line":167,"name":"end_line","type":"builtins.int"},{"alias":null,"column":4,"has_default":true,"is_in_init":false,"is_init_var":false,"is_neither_frozen_nor_nonfrozen":false,"kw_only":false,"line":168,"name":"end_col","type":"builtins.int"},{"alias":null,"column":4,"has_default":true,"is_in_init":false,"is_init_var":false,"is_neither_frozen_nor_nonfrozen":false,"kw_only":false,"line":170,"name":"raw","type":{".class":"UnionType","items":["builtins.str",{".class":"NoneType"}],"uses_pep604_syntax":false}}],"frozen":true},"dataclass_tag":{}},"module_name":"pint.delegates.txt_defparser.plain","mro":["pint.delegates.txt_defparser.plain.Equality","pint.delegates.base_defparser.PintParsedStatement","flexparser.flexparser.ParsedStatement","flexparser.flexparser.Statement","pint.facets.plain.definitions.Equality","builtins.object"],"names":{".class":"SymbolTable","__dataclass_fields__":{".class":"SymbolTableNode","kind":"Mdef","node":{".class":"Var","flags":["is_classvar","is_ready"],"fullname":"pint.delegates.txt_defparser.plain.Equality.__dataclass_fields__","name":"__dataclass_fields__","type":{".class":"Instance","args":["builtins.str",{".class":"Instance","args":[{".class":"AnyType","missing_import_name":null,"source_any":null,"type_of_any":2}],"extra_attrs":null,"type_ref":"dataclasses.Field"}],"extra_attrs":null,"type_ref":"builtins.dict"}},"plugin_generated":true},"__init__":{".class":"SymbolTableNode","kind":"Mdef","node":{".class":"FuncDef","abstract_status":0,"arg_kinds":[0,0,0],"arg_names":["self","lhs","rhs"],"dataclass_transform_spec":null,"deprecated":null,"flags":[],"fullname":"pint.delegates.txt_defparser.plain.Equality.__init__","name":"__init__","type":{".class":"CallableType","arg_kinds":[0,0,0],"arg_names":["self","lhs","rhs"],"arg_types":["pint.delegates.txt_defparser.plain.Equality","builtins.str","builtins.str"],"bound_args":[],"def_extras":{},"fallback":"builtins.function","from_concatenate":false,"implicit":false,"imprecise_arg_kinds":false,"is_ellipsis_args":false,"name":"__init__ of Equality","ret_type":{".class":"NoneType"},"type_guard":null,"type_is":null,"unpack_kwargs":false,"variables":[]}},"plugin_generated":true},"__match_args__":{".class":"SymbolTableNode","kind":"Mdef","node":{".class":"Var","flags":["is_ready","allow_incompatible_override"],"fullname":"pint.delegates.txt_defparser.plain.Equality.__match_args__","name":"__match_args__","type":{".class":"TupleType","implicit":false,"items":[{".class":"LiteralType","fallback":"builtins.str","value":"lhs"},{".class":"LiteralType","fallback":"builtins.str","value":"rhs"}],"partial_fallback":{".class":"Instance","args":[{".class":"AnyType","missing_import_name":null,"source_any":null,"type_of_any":6}],"extra_attrs":null,"type_ref":"builtins.tuple"}}},"plugin_generated":true},"__mypy-replace":{".class":"SymbolTableNode","kind":"Mdef","node":{".class":"Decorator","func":{".class":"FuncDef","abstract_status":0,"arg_kinds":[5,5,5,5,5,5,5,5],"arg_names":["lhs","rhs","is_position_set","start_line","start_col","end_line","end_col","raw"],"dataclass_transform_spec":null,"deprecated":null,"flags":["is_static","is_decorated"],"fullname":"pint.delegates.txt_defparser.plain.Equality.__mypy-replace","name":"__mypy-replace","type":{".class":"CallableType","arg_kinds":[5,5,5,5,5,5,5,5],"arg_names":["lhs","rhs","is_position_set","start_line","start_col","end_line","end_col","raw"],"arg_types":["builtins.str","builtins.str","builtins.bool","builtins.int","builtins.int","builtins.int","builtins.int",{".class":"UnionType","items":["builtins.str",{".class":"NoneType"}],"uses_pep604_syntax":false}],"bound_args":[],"def_extras":{},"fallback":"builtins.function","from_concatenate":false,"implicit":false,"imprecise_arg_kinds":false,"is_ellipsis_args":false,"name":"__mypy-replace of Equality","ret_type":{".class":"NoneType"},"type_guard":null,"type_is":null,"unpack_kwargs":false,"variables":[]}},"is_overload":false,"var":{".class":"Var","flags":["is_staticmethod","is_ready"],"fullname":"pint.delegates.txt_defparser.plain.Equality.__mypy-replace","name":"__mypy-replace","type":{".class":"CallableType","arg_kinds":[5,5,5,5,5,5,5,5],"arg_names":["lhs","rhs","is_position_set","start_line","start_col","end_line","end_col","raw"],"arg_types":["builtins.str","builtins.str","builtins.bool","builtins.int","builtins.int","builtins.int","builtins.int",{".class":"UnionType","items":["builtins.str",{".class":"NoneType"}],"uses_pep604_syntax":false}],"bound_args":[],"def_extras":{},"fallback":"builtins.function","from_concatenate":false,"implicit":false,"imprecise_arg_kinds":false,"is_ellipsis_args":false,"name":"__mypy-replace of Equality","ret_type":{".class":"NoneType"},"type_guard":null,"type_is":null,"unpack_kwargs":false,"variables":[]}}},"plugin_generated":true},"__replace__":{".class":"SymbolTableNode","kind":"Mdef","node":{".class":"FuncDef","abstract_status":0,"arg_kinds":[0,5,5],"arg_names":["self","lhs","rhs"],"dataclass_transform_spec":null,"deprecated":null,"flags":[],"fullname":"pint.delegates.txt_defparser.plain.Equality.__replace__","name":"__replace__","type":{".class":"CallableType","arg_kinds":[0,5,5],"arg_names":["self","lhs","rhs"],"arg_types":["pint.delegates.txt_defparser.plain.Equality","builtins.str","builtins.str"],"bound_args":[],"def_extras":{},"fallback":"builtins.function","from_concatenate":false,"implicit":false,"imprecise_arg_kinds":false,"is_ellipsis_args":false,"name":"__replace__ of Equality","ret_type":"pint.delegates.txt_defparser.plain.Equality","type_guard":null,"type_is":null,"unpack_kwargs":false,"variables":[]}},"plugin_generated":true},"end_col":{".class":"SymbolTableNode","kind":"Mdef","node":{".class":"Var","flags":["is_property","is_ready"],"fullname":"pint.delegates.txt_defparser.plain.Equality.end_col","name":"end_col","type":"builtins.int"}},"end_line":{".class":"SymbolTableNode","kind":"Mdef","node":{".class":"Var","flags":["is_property","is_ready"],"fullname":"pint.delegates.txt_defparser.plain.Equality.end_line","name":"end_line","type":"builtins.int"}},"from_string":{".class":"SymbolTableNode","kind":"Mdef","node":{".class":"Decorator","func":{".class":"FuncDef","abstract_status":0,"arg_kinds":[0,0],"arg_names":["cls","s"],"dataclass_transform_spec":null,"deprecated":null,"flags":["is_class","is_decorated"],"fullname":"pint.delegates.txt_defparser.plain.Equality.from_string","name":"from_string","type":{".class":"CallableType","arg_kinds":[0,0],"arg_names":["cls","s"],"arg_types":[{".class":"TypeType","item":"pint.delegates.txt_defparser.plain.Equality"},"builtins.str"],"bound_args":[],"def_extras":{"first_arg":"cls"},"fallback":"builtins.function","from_concatenate":false,"implicit":false,"imprecise_arg_kinds":false,"is_ellipsis_args":false,"name":"from_string of Equality","ret_type":{".class":"TypeAliasType","args":["pint.delegates.txt_defparser.plain.Equality"],"type_ref":"flexparser.flexparser.NullableParsedResult"},"type_guard":null,"type_is":null,"unpack_kwargs":false,"variables":[]}},"is_overload":false,"var":{".class":"Var","flags":["is_initialized_in_class","is_classmethod","is_ready","is_inferred"],"fullname":"pint.delegates.txt_defparser.plain.Equality.from_string","name":"from_string","type":{".class":"CallableType","arg_kinds":[0,0],"arg_names":["cls","s"],"arg_types":[{".class":"TypeType","item":"pint.delegates.txt_defparser.plain.Equality"},"builtins.str"],"bound_args":[],"def_extras":{"first_arg":"cls"},"fallback":"builtins.function","from_concatenate":false,"implicit":false,"imprecise_arg_kinds":false,"is_ellipsis_args":false,"name":"from_string of Equality","ret_type":{".class":"TypeAliasType","args":["pint.delegates.txt_defparser.plain.Equality"],"type_ref":"flexparser.flexparser.NullableParsedResult"},"type_guard":null,"type_is":null,"unpack_kwargs":false,"variables":[]}}}},"is_position_set":{".class":"SymbolTableNode","kind":"Mdef","node":{".class":"Var","flags":["is_property","is_ready"],"fullname":"pint.delegates.txt_defparser.plain.Equality.is_position_set","name":"is_position_set","type":"builtins.bool"}},"lhs":{".class":"SymbolTableNode","kind":"Mdef","node":{".class":"Var","flags":["is_property","is_ready"],"fullname":"pint.delegates.txt_defparser.plain.Equality.lhs","name":"lhs","type":"builtins.str"}},"raw":{".class":"SymbolTableNode","kind":"Mdef","node":{".class":"Var","flags":["is_property","is_ready"],"fullname":"pint.delegates.txt_defparser.plain.Equality.raw","name":"raw","type":{".class":"UnionType","items":["builtins.str",{".class":"NoneType"}],"uses_pep604_syntax":false}}},"rhs":{".class":"SymbolTableNode","kind":"Mdef","node":{".class":"Var","flags":["is_property","is_ready"],"fullname":"pint.delegates.txt_defparser.plain.Equality.rhs","name":"rhs","type":"builtins.str"}},"start_col":{".class":"SymbolTableNode","kind":"Mdef","node":{".class":"Var","flags":["is_property","is_ready"],"fullname":"pint.delegates.txt_defparser.plain.Equality.start_col","name":"start_col","type":"builtins.int"}},"start_line":{".class":"SymbolTableNode","kind":"Mdef","node":{".class":"Var","flags":["is_property","is_ready"],"fullname":"pint.delegates.txt_defparser.plain.Equality.start_line","name":"start_line","type":"builtins.int"}}},"self_type":{".class":"TypeVarType","default":{".class":"AnyType","missing_import_name":null,"source_any":null,"type_of_any":4},"fullname":"pint.delegates.txt_defparser.plain.Equality.Self","id":0,"name":"Self","namespace":"","upper_bound":"pint.delegates.txt_defparser.plain.Equality","values":[],"variance":0},"slots":null,"tuple_type":null,"type_vars":[],"typeddict_type":null}},"ParserConfig":{".class":"SymbolTableNode","cross_ref":"pint.delegates.base_defparser.ParserConfig","kind":"Gdef"},"PintParsedStatement":{".class":"SymbolTableNode","cross_ref":"pint.delegates.base_defparser.PintParsedStatement","kind":"Gdef"},"PrefixDefinition":{".class":"SymbolTableNode","kind":"Gdef","node":{".class":"TypeInfo","_promote":[],"abstract_attributes":[],"alt_promote":null,"bases":["pint.delegates.base_defparser.PintParsedStatement","pint.facets.plain.definitions.PrefixDefinition"],"dataclass_transform_spec":null,"declared_metaclass":null,"defn":{".class":"ClassDef","fullname":"pint.delegates.txt_defparser.plain.PrefixDefinition","name":"PrefixDefinition","type_vars":[]},"deletable_attributes":[],"deprecated":null,"flags":[],"fullname":"pint.delegates.txt_defparser.plain.PrefixDefinition","has_param_spec_type":false,"metaclass_type":null,"metadata":{"dataclass":{"attributes":[{"alias":null,"column":4,"has_default":false,"is_in_init":true,"is_init_var":false,"is_neither_frozen_nor_nonfrozen":false,"kw_only":false,"line":74,"name":"name","type":"builtins.str"},{"alias":null,"column":4,"has_default":false,"is_in_init":true,"is_init_var":false,"is_neither_frozen_nor_nonfrozen":false,"kw_only":false,"line":82,"name":"value","type":"numbers.Number"},{"alias":null,"column":4,"has_default":true,"is_in_init":true,"is_init_var":false,"is_neither_frozen_nor_nonfrozen":false,"kw_only":false,"line":84,"name":"defined_symbol","type":{".class":"UnionType","items":["builtins.str",{".class":"NoneType"}],"uses_pep604_syntax":true}},{"alias":null,"column":4,"has_default":true,"is_in_init":true,"is_init_var":false,"is_neither_frozen_nor_nonfrozen":false,"kw_only":false,"line":86,"name":"aliases","type":{".class":"Instance","args":["builtins.str"],"extra_attrs":null,"type_ref":"builtins.tuple"}},{"alias":null,"column":4,"has_default":true,"is_in_init":false,"is_init_var":false,"is_neither_frozen_nor_nonfrozen":false,"kw_only":false,"line":162,"name":"is_position_set","type":"builtins.bool"},{"alias":null,"column":4,"has_default":true,"is_in_init":false,"is_init_var":false,"is_neither_frozen_nor_nonfrozen":false,"kw_only":false,"line":164,"name":"start_line","type":"builtins.int"},{"alias":null,"column":4,"has_default":true,"is_in_init":false,"is_init_var":false,"is_neither_frozen_nor_nonfrozen":false,"kw_only":false,"line":165,"name":"start_col","type":"builtins.int"},{"alias":null,"column":4,"has_default":true,"is_in_init":false,"is_init_var":false,"is_neither_frozen_nor_nonfrozen":false,"kw_only":false,"line":167,"name":"end_line","type":"builtins.int"},{"alias":null,"column":4,"has_default":true,"is_in_init":false,"is_init_var":false,"is_neither_frozen_nor_nonfrozen":false,"kw_only":false,"line":168,"name":"end_col","type":"builtins.int"},{"alias":null,"column":4,"has_default":true,"is_in_init":false,"is_init_var":false,"is_neither_frozen_nor_nonfrozen":false,"kw_only":false,"line":170,"name":"raw","type":{".class":"UnionType","items":["builtins.str",{".class":"NoneType"}],"uses_pep604_syntax":false}}],"frozen":true},"dataclass_tag":{}},"module_name":"pint.delegates.txt_defparser.plain","mro":["pint.delegates.txt_defparser.plain.PrefixDefinition","pint.delegates.base_defparser.PintParsedStatement","flexparser.flexparser.ParsedStatement","flexparser.flexparser.Statement","pint.facets.plain.definitions.PrefixDefinition","pint.facets.plain.definitions.NamedDefinition","pint.errors.WithDefErr","builtins.object"],"names":{".class":"SymbolTable","__dataclass_fields__":{".class":"SymbolTableNode","kind":"Mdef","node":{".class":"Var","flags":["is_classvar","is_ready"],"fullname":"pint.delegates.txt_defparser.plain.PrefixDefinition.__dataclass_fields__","name":"__dataclass_fields__","type":{".class":"Instance","args":["builtins.str",{".class":"Instance","args":[{".class":"AnyType","missing_import_name":null,"source_any":null,"type_of_any":2}],"extra_attrs":null,"type_ref":"dataclasses.Field"}],"extra_attrs":null,"type_ref":"builtins.dict"}},"plugin_generated":true},"__init__":{".class":"SymbolTableNode","kind":"Mdef","node":{".class":"FuncDef","abstract_status":0,"arg_kinds":[0,0,0,1,1],"arg_names":["self","name","value","defined_symbol","aliases"],"dataclass_transform_spec":null,"deprecated":null,"flags":[],"fullname":"pint.delegates.txt_defparser.plain.PrefixDefinition.__init__","name":"__init__","type":{".class":"CallableType","arg_kinds":[0,0,0,1,1],"arg_names":["self","name","value","defined_symbol","aliases"],"arg_types":["pint.delegates.txt_defparser.plain.PrefixDefinition","builtins.str","numbers.Number",{".class":"UnionType","items":["builtins.str",{".class":"NoneType"}],"uses_pep604_syntax":false},{".class":"Instance","args":["builtins.str"],"extra_attrs":null,"type_ref":"builtins.tuple"}],"bound_args":[],"def_extras":{},"fallback":"builtins.function","from_concatenate":false,"implicit":false,"imprecise_arg_kinds":false,"is_ellipsis_args":false,"name":"__init__ of PrefixDefinition","ret_type":{".class":"NoneType"},"type_guard":null,"type_is":null,"unpack_kwargs":false,"variables":[]}},"plugin_generated":true},"__match_args__":{".class":"SymbolTableNode","kind":"Mdef","node":{".class":"Var","flags":["is_ready","allow_incompatible_override"],"fullname":"pint.delegates.txt_defparser.plain.PrefixDefinition.__match_args__","name":"__match_args__","type":{".class":"TupleType","implicit":false,"items":[{".class":"LiteralType","fallback":"builtins.str","value":"name"},{".class":"LiteralType","fallback":"builtins.str","value":"value"},{".class":"LiteralType","fallback":"builtins.str","value":"defined_symbol"},{".class":"LiteralType","fallback":"builtins.str","value":"aliases"}],"partial_fallback":{".class":"Instance","args":[{".class":"AnyType","missing_import_name":null,"source_any":null,"type_of_any":6}],"extra_attrs":null,"type_ref":"builtins.tuple"}}},"plugin_generated":true},"__mypy-replace":{".class":"SymbolTableNode","kind":"Mdef","node":{".class":"Decorator","func":{".class":"FuncDef","abstract_status":0,"arg_kinds":[5,5,5,5,5,5,5,5,5,5],"arg_names":["name","value","defined_symbol","aliases","is_position_set","start_line","start_col","end_line","end_col","raw"],"dataclass_transform_spec":null,"deprecated":null,"flags":["is_static","is_decorated"],"fullname":"pint.delegates.txt_defparser.plain.PrefixDefinition.__mypy-replace","name":"__mypy-replace","type":{".class":"CallableType","arg_kinds":[5,5,5,5,5,5,5,5,5,5],"arg_names":["name","value","defined_symbol","aliases","is_position_set","start_line","start_col","end_line","end_col","raw"],"arg_types":["builtins.str","numbers.Number",{".class":"UnionType","items":["builtins.str",{".class":"NoneType"}],"uses_pep604_syntax":false},{".class":"Instance","args":["builtins.str"],"extra_attrs":null,"type_ref":"builtins.tuple"},"builtins.bool","builtins.int","builtins.int","builtins.int","builtins.int",{".class":"UnionType","items":["builtins.str",{".class":"NoneType"}],"uses_pep604_syntax":false}],"bound_args":[],"def_extras":{},"fallback":"builtins.function","from_concatenate":false,"implicit":false,"imprecise_arg_kinds":false,"is_ellipsis_args":false,"name":"__mypy-replace of PrefixDefinition","ret_type":{".class":"NoneType"},"type_guard":null,"type_is":null,"unpack_kwargs":false,"variables":[]}},"is_overload":false,"var":{".class":"Var","flags":["is_staticmethod","is_ready"],"fullname":"pint.delegates.txt_defparser.plain.PrefixDefinition.__mypy-replace","name":"__mypy-replace","type":{".class":"CallableType","arg_kinds":[5,5,5,5,5,5,5,5,5,5],"arg_names":["name","value","defined_symbol","aliases","is_position_set","start_line","start_col","end_line","end_col","raw"],"arg_types":["builtins.str","numbers.Number",{".class":"UnionType","items":["builtins.str",{".class":"NoneType"}],"uses_pep604_syntax":false},{".class":"Instance","args":["builtins.str"],"extra_attrs":null,"type_ref":"builtins.tuple"},"builtins.bool","builtins.int","builtins.int","builtins.int","builtins.int",{".class":"UnionType","items":["builtins.str",{".class":"NoneType"}],"uses_pep604_syntax":false}],"bound_args":[],"def_extras":{},"fallback":"builtins.function","from_concatenate":false,"implicit":false,"imprecise_arg_kinds":false,"is_ellipsis_args":false,"name":"__mypy-replace of PrefixDefinition","ret_type":{".class":"NoneType"},"type_guard":null,"type_is":null,"unpack_kwargs":false,"variables":[]}}},"plugin_generated":true},"__replace__":{".class":"SymbolTableNode","kind":"Mdef","node":{".class":"FuncDef","abstract_status":0,"arg_kinds":[0,5,5,5,5],"arg_names":["self","name","value","defined_symbol","aliases"],"dataclass_transform_spec":null,"deprecated":null,"flags":[],"fullname":"pint.delegates.txt_defparser.plain.PrefixDefinition.__replace__","name":"__replace__","type":{".class":"CallableType","arg_kinds":[0,5,5,5,5],"arg_names":["self","name","value","defined_symbol","aliases"],"arg_types":["pint.delegates.txt_defparser.plain.PrefixDefinition","builtins.str","numbers.Number",{".class":"UnionType","items":["builtins.str",{".class":"NoneType"}],"uses_pep604_syntax":false},{".class":"Instance","args":["builtins.str"],"extra_attrs":null,"type_ref":"builtins.tuple"}],"bound_args":[],"def_extras":{},"fallback":"builtins.function","from_concatenate":false,"implicit":false,"imprecise_arg_kinds":false,"is_ellipsis_args":false,"name":"__replace__ of PrefixDefinition","ret_type":"pint.delegates.txt_defparser.plain.PrefixDefinition","type_guard":null,"type_is":null,"unpack_kwargs":false,"variables":[]}},"plugin_generated":true},"aliases":{".class":"SymbolTableNode","kind":"Mdef","node":{".class":"Var","flags":["is_property","is_ready"],"fullname":"pint.delegates.txt_defparser.plain.PrefixDefinition.aliases","name":"aliases","type":{".class":"Instance","args":["builtins.str"],"extra_attrs":null,"type_ref":"builtins.tuple"}}},"defined_symbol":{".class":"SymbolTableNode","kind":"Mdef","node":{".class":"Var","flags":["is_property","is_ready"],"fullname":"pint.delegates.txt_defparser.plain.PrefixDefinition.defined_symbol","name":"defined_symbol","type":{".class":"UnionType","items":["builtins.str",{".class":"NoneType"}],"uses_pep604_syntax":false}}},"end_col":{".class":"SymbolTableNode","kind":"Mdef","node":{".class":"Var","flags":["is_property","is_ready"],"fullname":"pint.delegates.txt_defparser.plain.PrefixDefinition.end_col","name":"end_col","type":"builtins.int"}},"end_line":{".class":"SymbolTableNode","kind":"Mdef","node":{".class":"Var","flags":["is_property","is_ready"],"fullname":"pint.delegates.txt_defparser.plain.PrefixDefinition.end_line","name":"end_line","type":"builtins.int"}},"from_string_and_config":{".class":"SymbolTableNode","kind":"Mdef","node":{".class":"Decorator","func":{".class":"FuncDef","abstract_status":0,"arg_kinds":[0,0,0],"arg_names":["cls","s","config"],"dataclass_transform_spec":null,"deprecated":null,"flags":["is_class","is_decorated"],"fullname":"pint.delegates.txt_defparser.plain.PrefixDefinition.from_string_and_config","name":"from_string_and_config","type":{".class":"CallableType","arg_kinds":[0,0,0],"arg_names":["cls","s","config"],"arg_types":[{".class":"TypeType","item":"pint.delegates.txt_defparser.plain.PrefixDefinition"},"builtins.str","pint.delegates.base_defparser.ParserConfig"],"bound_args":[],"def_extras":{"first_arg":"cls"},"fallback":"builtins.function","from_concatenate":false,"implicit":false,"imprecise_arg_kinds":false,"is_ellipsis_args":false,"name":"from_string_and_config of PrefixDefinition","ret_type":{".class":"TypeAliasType","args":["pint.delegates.txt_defparser.plain.PrefixDefinition"],"type_ref":"flexparser.flexparser.NullableParsedResult"},"type_guard":null,"type_is":null,"unpack_kwargs":false,"variables":[]}},"is_overload":false,"var":{".class":"Var","flags":["is_initialized_in_class","is_classmethod","is_ready","is_inferred"],"fullname":"pint.delegates.txt_defparser.plain.PrefixDefinition.from_string_and_config","name":"from_string_and_config","type":{".class":"CallableType","arg_kinds":[0,0,0],"arg_names":["cls","s","config"],"arg_types":[{".class":"TypeType","item":"pint.delegates.txt_defparser.plain.PrefixDefinition"},"builtins.str","pint.delegates.base_defparser.ParserConfig"],"bound_args":[],"def_extras":{"first_arg":"cls"},"fallback":"builtins.function","from_concatenate":false,"implicit":false,"imprecise_arg_kinds":false,"is_ellipsis_args":false,"name":"from_string_and_config of PrefixDefinition","ret_type":{".class":"TypeAliasType","args":["pint.delegates.txt_defparser.plain.PrefixDefinition"],"type_ref":"flexparser.flexparser.NullableParsedResult"},"type_guard":null,"type_is":null,"unpack_kwargs":false,"variables":[]}}}},"is_position_set":{".class":"SymbolTableNode","kind":"Mdef","node":{".class":"Var","flags":["is_property","is_ready"],"fullname":"pint.delegates.txt_defparser.plain.PrefixDefinition.is_position_set","name":"is_position_set","type":"builtins.bool"}},"name":{".class":"SymbolTableNode","kind":"Mdef","node":{".class":"Var","flags":["is_property","is_ready"],"fullname":"pint.delegates.txt_defparser.plain.PrefixDefinition.name","name":"name","type":"builtins.str"}},"raw":{".class":"SymbolTableNode","kind":"Mdef","node":{".class":"Var","flags":["is_property","is_ready"],"fullname":"pint.delegates.txt_defparser.plain.PrefixDefinition.raw","name":"raw","type":{".class":"UnionType","items":["builtins.str",{".class":"NoneType"}],"uses_pep604_syntax":false}}},"start_col":{".class":"SymbolTableNode","kind":"Mdef","node":{".class":"Var","flags":["is_property","is_ready"],"fullname":"pint.delegates.txt_defparser.plain.PrefixDefinition.start_col","name":"start_col","type":"builtins.int"}},"start_line":{".class":"SymbolTableNode","kind":"Mdef","node":{".class":"Var","flags":["is_property","is_ready"],"fullname":"pint.delegates.txt_defparser.plain.PrefixDefinition.start_line","name":"start_line","type":"builtins.int"}},"value":{".class":"SymbolTableNode","kind":"Mdef","node":{".class":"Var","flags":["is_property","is_ready"],"fullname":"pint.delegates.txt_defparser.plain.PrefixDefinition.value","name":"value","type":"numbers.Number"}}},"self_type":{".class":"TypeVarType","default":{".class":"AnyType","missing_import_name":null,"source_any":null,"type_of_any":4},"fullname":"pint.delegates.txt_defparser.plain.PrefixDefinition.Self","id":0,"name":"Self","namespace":"","upper_bound":"pint.delegates.txt_defparser.plain.PrefixDefinition","values":[],"variance":0},"slots":null,"tuple_type":null,"type_vars":[],"typeddict_type":null}},"UnitDefinition":{".class":"SymbolTableNode","kind":"Gdef","node":{".class":"TypeInfo","_promote":[],"abstract_attributes":[],"alt_promote":null,"bases":["pint.delegates.base_defparser.PintParsedStatement","pint.facets.plain.definitions.UnitDefinition"],"dataclass_transform_spec":null,"declared_metaclass":null,"defn":{".class":"ClassDef","fullname":"pint.delegates.txt_defparser.plain.UnitDefinition","name":"UnitDefinition","type_vars":[]},"deletable_attributes":[],"deprecated":null,"flags":[],"fullname":"pint.delegates.txt_defparser.plain.UnitDefinition","has_param_spec_type":false,"metaclass_type":null,"metadata":{"dataclass":{"attributes":[{"alias":null,"column":4,"has_default":false,"is_in_init":true,"is_init_var":false,"is_neither_frozen_nor_nonfrozen":false,"kw_only":false,"line":74,"name":"name","type":"builtins.str"},{"alias":null,"column":4,"has_default":false,"is_in_init":true,"is_init_var":false,"is_neither_frozen_nor_nonfrozen":false,"kw_only":false,"line":121,"name":"defined_symbol","type":{".class":"UnionType","items":["builtins.str",{".class":"NoneType"}],"uses_pep604_syntax":true}},{"alias":null,"column":4,"has_default":false,"is_in_init":true,"is_init_var":false,"is_neither_frozen_nor_nonfrozen":false,"kw_only":false,"line":123,"name":"aliases","type":{".class":"Instance","args":["builtins.str"],"extra_attrs":null,"type_ref":"builtins.tuple"}},{"alias":null,"column":4,"has_default":false,"is_in_init":true,"is_init_var":false,"is_neither_frozen_nor_nonfrozen":false,"kw_only":false,"line":129,"name":"converter","type":{".class":"UnionType","items":["pint.converters.Converter",{".class":"NoneType"}],"uses_pep604_syntax":true}},{"alias":null,"column":4,"has_default":false,"is_in_init":true,"is_init_var":false,"is_neither_frozen_nor_nonfrozen":false,"kw_only":false,"line":131,"name":"reference","type":{".class":"UnionType","items":["pint.util.UnitsContainer",{".class":"NoneType"}],"uses_pep604_syntax":true}},{"alias":null,"column":4,"has_default":true,"is_in_init":false,"is_init_var":false,"is_neither_frozen_nor_nonfrozen":false,"kw_only":false,"line":162,"name":"is_position_set","type":"builtins.bool"},{"alias":null,"column":4,"has_default":true,"is_in_init":false,"is_init_var":false,"is_neither_frozen_nor_nonfrozen":false,"kw_only":false,"line":164,"name":"start_line","type":"builtins.int"},{"alias":null,"column":4,"has_default":true,"is_in_init":false,"is_init_var":false,"is_neither_frozen_nor_nonfrozen":false,"kw_only":false,"line":165,"name":"start_col","type":"builtins.int"},{"alias":null,"column":4,"has_default":true,"is_in_init":false,"is_init_var":false,"is_neither_frozen_nor_nonfrozen":false,"kw_only":false,"line":167,"name":"end_line","type":"builtins.int"},{"alias":null,"column":4,"has_default":true,"is_in_init":false,"is_init_var":false,"is_neither_frozen_nor_nonfrozen":false,"kw_only":false,"line":168,"name":"end_col","type":"builtins.int"},{"alias":null,"column":4,"has_default":true,"is_in_init":false,"is_init_var":false,"is_neither_frozen_nor_nonfrozen":false,"kw_only":false,"line":170,"name":"raw","type":{".class":"UnionType","items":["builtins.str",{".class":"NoneType"}],"uses_pep604_syntax":false}}],"frozen":true},"dataclass_tag":{}},"module_name":"pint.delegates.txt_defparser.plain","mro":["pint.delegates.txt_defparser.plain.UnitDefinition","pint.delegates.base_defparser.PintParsedStatement","flexparser.flexparser.ParsedStatement","flexparser.flexparser.Statement","pint.facets.plain.definitions.UnitDefinition","pint.facets.plain.definitions.NamedDefinition","pint.errors.WithDefErr","builtins.object"],"names":{".class":"SymbolTable","__dataclass_fields__":{".class":"SymbolTableNode","kind":"Mdef","node":{".class":"Var","flags":["is_classvar","is_ready"],"fullname":"pint.delegates.txt_defparser.plain.UnitDefinition.__dataclass_fields__","name":"__dataclass_fields__","type":{".class":"Instance","args":["builtins.str",{".class":"Instance","args":[{".class":"AnyType","missing_import_name":null,"source_any":null,"type_of_any":2}],"extra_attrs":null,"type_ref":"dataclasses.Field"}],"extra_attrs":null,"type_ref":"builtins.dict"}},"plugin_generated":true},"__init__":{".class":"SymbolTableNode","kind":"Mdef","node":{".class":"FuncDef","abstract_status":0,"arg_kinds":[0,0,0,0,0,0],"arg_names":["self","name","defined_symbol","aliases","converter","reference"],"dataclass_transform_spec":null,"deprecated":null,"flags":[],"fullname":"pint.delegates.txt_defparser.plain.UnitDefinition.__init__","name":"__init__","type":{".class":"CallableType","arg_kinds":[0,0,0,0,0,0],"arg_names":["self","name","defined_symbol","aliases","converter","reference"],"arg_types":["pint.delegates.txt_defparser.plain.UnitDefinition","builtins.str",{".class":"UnionType","items":["builtins.str",{".class":"NoneType"}],"uses_pep604_syntax":false},{".class":"Instance","args":["builtins.str"],"extra_attrs":null,"type_ref":"builtins.tuple"},{".class":"UnionType","items":["pint.converters.Converter",{".class":"NoneType"}],"uses_pep604_syntax":false},{".class":"UnionType","items":["pint.util.UnitsContainer",{".class":"NoneType"}],"uses_pep604_syntax":false}],"bound_args":[],"def_extras":{},"fallback":"builtins.function","from_concatenate":false,"implicit":false,"imprecise_arg_kinds":false,"is_ellipsis_args":false,"name":"__init__ of UnitDefinition","ret_type":{".class":"NoneType"},"type_guard":null,"type_is":null,"unpack_kwargs":false,"variables":[]}},"plugin_generated":true},"__match_args__":{".class":"SymbolTableNode","kind":"Mdef","node":{".class":"Var","flags":["is_ready","allow_incompatible_override"],"fullname":"pint.delegates.txt_defparser.plain.UnitDefinition.__match_args__","name":"__match_args__","type":{".class":"TupleType","implicit":false,"items":[{".class":"LiteralType","fallback":"builtins.str","value":"name"},{".class":"LiteralType","fallback":"builtins.str","value":"defined_symbol"},{".class":"LiteralType","fallback":"builtins.str","value":"aliases"},{".class":"LiteralType","fallback":"builtins.str","value":"converter"},{".class":"LiteralType","fallback":"builtins.str","value":"reference"}],"partial_fallback":{".class":"Instance","args":[{".class":"AnyType","missing_import_name":null,"source_any":null,"type_of_any":6}],"extra_attrs":null,"type_ref":"builtins.tuple"}}},"plugin_generated":true},"__mypy-replace":{".class":"SymbolTableNode","kind":"Mdef","node":{".class":"Decorator","func":{".class":"FuncDef","abstract_status":0,"arg_kinds":[5,5,5,5,5,5,5,5,5,5,5],"arg_names":["name","defined_symbol","aliases","converter","reference","is_position_set","start_line","start_col","end_line","end_col","raw"],"dataclass_transform_spec":null,"deprecated":null,"flags":["is_static","is_decorated"],"fullname":"pint.delegates.txt_defparser.plain.UnitDefinition.__mypy-replace","name":"__mypy-replace","type":{".class":"CallableType","arg_kinds":[5,5,5,5,5,5,5,5,5,5,5],"arg_names":["name","defined_symbol","aliases","converter","reference","is_position_set","start_line","start_col","end_line","end_col","raw"],"arg_types":["builtins.str",{".class":"UnionType","items":["builtins.str",{".class":"NoneType"}],"uses_pep604_syntax":false},{".class":"Instance","args":["builtins.str"],"extra_attrs":null,"type_ref":"builtins.tuple"},{".class":"UnionType","items":["pint.converters.Converter",{".class":"NoneType"}],"uses_pep604_syntax":false},{".class":"UnionType","items":["pint.util.UnitsContainer",{".class":"NoneType"}],"uses_pep604_syntax":false},"builtins.bool","builtins.int","builtins.int","builtins.int","builtins.int",{".class":"UnionType","items":["builtins.str",{".class":"NoneType"}],"uses_pep604_syntax":false}],"bound_args":[],"def_extras":{},"fallback":"builtins.function","from_concatenate":false,"implicit":false,"imprecise_arg_kinds":false,"is_ellipsis_args":false,"name":"__mypy-replace of UnitDefinition","ret_type":{".class":"NoneType"},"type_guard":null,"type_is":null,"unpack_kwargs":false,"variables":[]}},"is_overload":false,"var":{".class":"Var","flags":["is_staticmethod","is_ready"],"fullname":"pint.delegates.txt_defparser.plain.UnitDefinition.__mypy-replace","name":"__mypy-replace","type":{".class":"CallableType","arg_kinds":[5,5,5,5,5,5,5,5,5,5,5],"arg_names":["name","defined_symbol","aliases","converter","reference","is_position_set","start_line","start_col","end_line","end_col","raw"],"arg_types":["builtins.str",{".class":"UnionType","items":["builtins.str",{".class":"NoneType"}],"uses_pep604_syntax":false},{".class":"Instance","args":["builtins.str"],"extra_attrs":null,"type_ref":"builtins.tuple"},{".class":"UnionType","items":["pint.converters.Converter",{".class":"NoneType"}],"uses_pep604_syntax":false},{".class":"UnionType","items":["pint.util.UnitsContainer",{".class":"NoneType"}],"uses_pep604_syntax":false},"builtins.bool","builtins.int","builtins.int","builtins.int","builtins.int",{".class":"UnionType","items":["builtins.str",{".class":"NoneType"}],"uses_pep604_syntax":false}],"bound_args":[],"def_extras":{},"fallback":"builtins.function","from_concatenate":false,"implicit":false,"imprecise_arg_kinds":false,"is_ellipsis_args":false,"name":"__mypy-replace of UnitDefinition","ret_type":{".class":"NoneType"},"type_guard":null,"type_is":null,"unpack_kwargs":false,"variables":[]}}},"plugin_generated":true},"__replace__":{".class":"SymbolTableNode","kind":"Mdef","node":{".class":"FuncDef","abstract_status":0,"arg_kinds":[0,5,5,5,5,5],"arg_names":["self","name","defined_symbol","aliases","converter","reference"],"dataclass_transform_spec":null,"deprecated":null,"flags":[],"fullname":"pint.delegates.txt_defparser.plain.UnitDefinition.__replace__","name":"__replace__","type":{".class":"CallableType","arg_kinds":[0,5,5,5,5,5],"arg_names":["self","name","defined_symbol","aliases","converter","reference"],"arg_types":["pint.delegates.txt_defparser.plain.UnitDefinition","builtins.str",{".class":"UnionType","items":["builtins.str",{".class":"NoneType"}],"uses_pep604_syntax":false},{".class":"Instance","args":["builtins.str"],"extra_attrs":null,"type_ref":"builtins.tuple"},{".class":"UnionType","items":["pint.converters.Converter",{".class":"NoneType"}],"uses_pep604_syntax":false},{".class":"UnionType","items":["pint.util.UnitsContainer",{".class":"NoneType"}],"uses_pep604_syntax":false}],"bound_args":[],"def_extras":{},"fallback":"builtins.function","from_concatenate":false,"implicit":false,"imprecise_arg_kinds":false,"is_ellipsis_args":false,"name":"__replace__ of UnitDefinition","ret_type":"pint.delegates.txt_defparser.plain.UnitDefinition","type_guard":null,"type_is":null,"unpack_kwargs":false,"variables":[]}},"plugin_generated":true},"aliases":{".class":"SymbolTableNode","kind":"Mdef","node":{".class":"Var","flags":["is_property","is_ready"],"fullname":"pint.delegates.txt_defparser.plain.UnitDefinition.aliases","name":"aliases","type":{".class":"Instance","args":["builtins.str"],"extra_attrs":null,"type_ref":"builtins.tuple"}}},"converter":{".class":"SymbolTableNode","kind":"Mdef","node":{".class":"Var","flags":["is_property","is_ready"],"fullname":"pint.delegates.txt_defparser.plain.UnitDefinition.converter","name":"converter","type":{".class":"UnionType","items":["pint.converters.Converter",{".class":"NoneType"}],"uses_pep604_syntax":false}}},"defined_symbol":{".class":"SymbolTableNode","kind":"Mdef","node":{".class":"Var","flags":["is_property","is_ready"],"fullname":"pint.delegates.txt_defparser.plain.UnitDefinition.defined_symbol","name":"defined_symbol","type":{".class":"UnionType","items":["builtins.str",{".class":"NoneType"}],"uses_pep604_syntax":false}}},"end_col":{".class":"SymbolTableNode","kind":"Mdef","node":{".class":"Var","flags":["is_property","is_ready"],"fullname":"pint.delegates.txt_defparser.plain.UnitDefinition.end_col","name":"end_col","type":"builtins.int"}},"end_line":{".class":"SymbolTableNode","kind":"Mdef","node":{".class":"Var","flags":["is_property","is_ready"],"fullname":"pint.delegates.txt_defparser.plain.UnitDefinition.end_line","name":"end_line","type":"builtins.int"}},"from_string_and_config":{".class":"SymbolTableNode","kind":"Mdef","node":{".class":"Decorator","func":{".class":"FuncDef","abstract_status":0,"arg_kinds":[0,0,0],"arg_names":["cls","s","config"],"dataclass_transform_spec":null,"deprecated":null,"flags":["is_class","is_decorated"],"fullname":"pint.delegates.txt_defparser.plain.UnitDefinition.from_string_and_config","name":"from_string_and_config","type":{".class":"CallableType","arg_kinds":[0,0,0],"arg_names":["cls","s","config"],"arg_types":[{".class":"TypeType","item":"pint.delegates.txt_defparser.plain.UnitDefinition"},"builtins.str","pint.delegates.base_defparser.ParserConfig"],"bound_args":[],"def_extras":{"first_arg":"cls"},"fallback":"builtins.function","from_concatenate":false,"implicit":false,"imprecise_arg_kinds":false,"is_ellipsis_args":false,"name":"from_string_and_config of UnitDefinition","ret_type":{".class":"TypeAliasType","args":["pint.delegates.txt_defparser.plain.UnitDefinition"],"type_ref":"flexparser.flexparser.NullableParsedResult"},"type_guard":null,"type_is":null,"unpack_kwargs":false,"variables":[]}},"is_overload":false,"var":{".class":"Var","flags":["is_initialized_in_class","is_classmethod","is_ready","is_inferred"],"fullname":"pint.delegates.txt_defparser.plain.UnitDefinition.from_string_and_config","name":"from_string_and_config","type":{".class":"CallableType","arg_kinds":[0,0,0],"arg_names":["cls","s","config"],"arg_types":[{".class":"TypeType","item":"pint.delegates.txt_defparser.plain.UnitDefinition"},"builtins.str","pint.delegates.base_defparser.ParserConfig"],"bound_args":[],"def_extras":{"first_arg":"cls"},"fallback":"builtins.function","from_concatenate":false,"implicit":false,"imprecise_arg_kinds":false,"is_ellipsis_args":false,"name":"from_string_and_config of UnitDefinition","ret_type":{".class":"TypeAliasType","args":["pint.delegates.txt_defparser.plain.UnitDefinition"],"type_ref":"flexparser.flexparser.NullableParsedResult"},"type_guard":null,"type_is":null,"unpack_kwargs":false,"variables":[]}}}},"is_position_set":{".class":"SymbolTableNode","kind":"Mdef","node":{".class":"Var","flags":["is_property","is_ready"],"fullname":"pint.delegates.txt_defparser.plain.UnitDefinition.is_position_set","name":"is_position_set","type":"builtins.bool"}},"name":{".class":"SymbolTableNode","kind":"Mdef","node":{".class":"Var","flags":["is_property","is_ready"],"fullname":"pint.delegates.txt_defparser.plain.UnitDefinition.name","name":"name","type":"builtins.str"}},"raw":{".class":"SymbolTableNode","kind":"Mdef","node":{".class":"Var","flags":["is_property","is_ready"],"fullname":"pint.delegates.txt_defparser.plain.UnitDefinition.raw","name":"raw","type":{".class":"UnionType","items":["builtins.str",{".class":"NoneType"}],"uses_pep604_syntax":false}}},"reference":{".class":"SymbolTableNode","kind":"Mdef","node":{".class":"Var","flags":["is_property","is_ready"],"fullname":"pint.delegates.txt_defparser.plain.UnitDefinition.reference","name":"reference","type":{".class":"UnionType","items":["pint.util.UnitsContainer",{".class":"NoneType"}],"uses_pep604_syntax":false}}},"start_col":{".class":"SymbolTableNode","kind":"Mdef","node":{".class":"Var","flags":["is_property","is_ready"],"fullname":"pint.delegates.txt_defparser.plain.UnitDefinition.start_col","name":"start_col","type":"builtins.int"}},"start_line":{".class":"SymbolTableNode","kind":"Mdef","node":{".class":"Var","flags":["is_property","is_ready"],"fullname":"pint.delegates.txt_defparser.plain.UnitDefinition.start_line","name":"start_line","type":"builtins.int"}}},"self_type":{".class":"TypeVarType","default":{".class":"AnyType","missing_import_name":null,"source_any":null,"type_of_any":4},"fullname":"pint.delegates.txt_defparser.plain.UnitDefinition.Self","id":0,"name":"Self","namespace":"","upper_bound":"pint.delegates.txt_defparser.plain.UnitDefinition","values":[],"variance":0},"slots":null,"tuple_type":null,"type_vars":[],"typeddict_type":null}},"UnitsContainer":{".class":"SymbolTableNode","cross_ref":"pint.util.UnitsContainer","kind":"Gdef"},"__annotations__":{".class":"SymbolTableNode","kind":"Gdef","node":{".class":"Var","flags":["is_ready"],"fullname":"pint.delegates.txt_defparser.plain.__annotations__","name":"__annotations__","type":{".class":"Instance","args":["builtins.str",{".class":"AnyType","missing_import_name":null,"source_any":null,"type_of_any":6}],"extra_attrs":null,"type_ref":"builtins.dict"}}},"__doc__":{".class":"SymbolTableNode","kind":"Gdef","node":{".class":"Var","flags":["is_ready"],"fullname":"pint.delegates.txt_defparser.plain.__doc__","name":"__doc__","type":"builtins.str"}},"__file__":{".class":"SymbolTableNode","kind":"Gdef","node":{".class":"Var","flags":["is_ready"],"fullname":"pint.delegates.txt_defparser.plain.__file__","name":"__file__","type":"builtins.str"}},"__name__":{".class":"SymbolTableNode","kind":"Gdef","node":{".class":"Var","flags":["is_ready"],"fullname":"pint.delegates.txt_defparser.plain.__name__","name":"__name__","type":"builtins.str"}},"__package__":{".class":"SymbolTableNode","kind":"Gdef","node":{".class":"Var","flags":["is_ready"],"fullname":"pint.delegates.txt_defparser.plain.__package__","name":"__package__","type":"builtins.str"}},"__spec__":{".class":"SymbolTableNode","kind":"Gdef","node":{".class":"Var","flags":["is_ready"],"fullname":"pint.delegates.txt_defparser.plain.__spec__","name":"__spec__","type":"_frozen_importlib.ModuleSpec"}},"annotations":{".class":"SymbolTableNode","cross_ref":"__future__.annotations","kind":"Gdef"},"common":{".class":"SymbolTableNode","cross_ref":"pint.delegates.txt_defparser.common","kind":"Gdef"},"dataclass":{".class":"SymbolTableNode","cross_ref":"dataclasses.dataclass","kind":"Gdef"},"definitions":{".class":"SymbolTableNode","cross_ref":"pint.facets.plain.definitions","kind":"Gdef"},"fp":{".class":"SymbolTableNode","cross_ref":"flexparser","kind":"Gdef"}},"path":"/home/gray/git/distopf_2/.venv/lib/python3.13/site-packages/pint/delegates/txt_defparser/plain.py"}