{".class":"MypyFile","_fullname":"pint.util","future_import_flags":["annotations"],"is_partial_stub_package":false,"is_stub":false,"names":{".class":"SymbolTable","Any":{".class":"SymbolTableNode","cross_ref":"typing.Any","kind":"Gdef"},"Callable":{".class":"SymbolTableNode","cross_ref":"typing.Callable","kind":"Gdef"},"ClassVar":{".class":"SymbolTableNode","cross_ref":"typing.ClassVar","kind":"Gdef"},"DefinitionSyntaxError":{".class":"SymbolTableNode","cross_ref":"pint.errors.DefinitionSyntaxError","kind":"Gdef"},"Fraction":{".class":"SymbolTableNode","cross_ref":"fractions.Fraction","kind":"Gdef"},"Generator":{".class":"SymbolTableNode","cross_ref":"typing.Generator","kind":"Gdef"},"Hashable":{".class":"SymbolTableNode","cross_ref":"typing.Hashable","kind":"Gdef"},"ItMatrix":{".class":"SymbolTableNode","kind":"Gdef","node":{".class":"TypeAlias","alias_tvars":[],"column":0,"fullname":"pint.util.ItMatrix","line":53,"no_args":false,"normalized":false,"python_3_12_type_alias":false,"target":{".class":"Instance","args":[{".class":"Instance","args":[{".class":"TypeAliasType","args":[],"type_ref":"pint._typing.Scalar"}],"extra_attrs":null,"type_ref":"typing.Iterable"}],"extra_attrs":null,"type_ref":"typing.Iterable"}}},"Iterable":{".class":"SymbolTableNode","cross_ref":"typing.Iterable","kind":"Gdef"},"Iterator":{".class":"SymbolTableNode","cross_ref":"typing.Iterator","kind":"Gdef"},"Mapping":{".class":"SymbolTableNode","cross_ref":"typing.Mapping","kind":"Gdef"},"Matrix":{".class":"SymbolTableNode","kind":"Gdef","node":{".class":"TypeAlias","alias_tvars":[],"column":0,"fullname":"pint.util.Matrix","line":54,"no_args":false,"normalized":false,"python_3_12_type_alias":false,"target":{".class":"Instance","args":[{".class":"Instance","args":[{".class":"TypeAliasType","args":[],"type_ref":"pint._typing.Scalar"}],"extra_attrs":null,"type_ref":"builtins.list"}],"extra_attrs":null,"type_ref":"builtins.list"}}},"NAME":{".class":"SymbolTableNode","cross_ref":"token.NAME","kind":"Gdef"},"NUMBER":{".class":"SymbolTableNode","cross_ref":"token.NUMBER","kind":"Gdef"},"NUMERIC_TYPES":{".class":"SymbolTableNode","cross_ref":"pint.compat.NUMERIC_TYPES","kind":"Gdef"},"NullHandler":{".class":"SymbolTableNode","cross_ref":"logging.NullHandler","kind":"Gdef"},"Number":{".class":"SymbolTableNode","cross_ref":"numbers.Number","kind":"Gdef"},"ParserHelper":{".class":"SymbolTableNode","kind":"Gdef","node":{".class":"TypeInfo","_promote":[],"abstract_attributes":[],"alt_promote":null,"bases":["pint.util.UnitsContainer"],"dataclass_transform_spec":null,"declared_metaclass":null,"defn":{".class":"ClassDef","fullname":"pint.util.ParserHelper","name":"ParserHelper","type_vars":[]},"deletable_attributes":[],"deprecated":null,"flags":[],"fullname":"pint.util.ParserHelper","has_param_spec_type":false,"metaclass_type":"abc.ABCMeta","metadata":{},"module_name":"pint.util","mro":["pint.util.ParserHelper","pint.util.UnitsContainer","typing.Mapping","typing.Collection","typing.Iterable","typing.Container","builtins.object"],"names":{".class":"SymbolTable","__copy__":{".class":"SymbolTableNode","kind":"Mdef","node":{".class":"FuncDef","abstract_status":0,"arg_kinds":[0],"arg_names":["self"],"dataclass_transform_spec":null,"deprecated":null,"flags":[],"fullname":"pint.util.ParserHelper.__copy__","name":"__copy__","type":null}},"__eq__":{".class":"SymbolTableNode","kind":"Mdef","node":{".class":"FuncDef","abstract_status":0,"arg_kinds":[0,0],"arg_names":[null,null],"dataclass_transform_spec":null,"deprecated":null,"flags":[],"fullname":"pint.util.ParserHelper.__eq__","name":"__eq__","type":{".class":"CallableType","arg_kinds":[0,0],"arg_names":[null,null],"arg_types":["pint.util.ParserHelper",{".class":"AnyType","missing_import_name":null,"source_any":null,"type_of_any":2}],"bound_args":[],"def_extras":{"first_arg":"self"},"fallback":"builtins.function","from_concatenate":false,"implicit":false,"imprecise_arg_kinds":false,"is_ellipsis_args":false,"name":"__eq__ of ParserHelper","ret_type":"builtins.bool","type_guard":null,"type_is":null,"unpack_kwargs":false,"variables":[]}}},"__floordiv__":{".class":"SymbolTableNode","kind":"Mdef","node":{".class":"Var","flags":["is_initialized_in_class","is_inferred","has_explicit_value"],"fullname":"pint.util.ParserHelper.__floordiv__","name":"__floordiv__","type":{".class":"CallableType","arg_kinds":[0,0],"arg_names":[null,null],"arg_types":["pint.util.ParserHelper",{".class":"AnyType","missing_import_name":null,"source_any":null,"type_of_any":1}],"bound_args":[],"def_extras":{"first_arg":"self"},"fallback":"builtins.function","from_concatenate":false,"implicit":true,"imprecise_arg_kinds":false,"is_ellipsis_args":false,"name":null,"ret_type":{".class":"AnyType","missing_import_name":null,"source_any":null,"type_of_any":1},"type_guard":null,"type_is":null,"unpack_kwargs":false,"variables":[]}}},"__getstate__":{".class":"SymbolTableNode","kind":"Mdef","node":{".class":"FuncDef","abstract_status":0,"arg_kinds":[0],"arg_names":["self"],"dataclass_transform_spec":null,"deprecated":null,"flags":[],"fullname":"pint.util.ParserHelper.__getstate__","name":"__getstate__","type":null}},"__hash__":{".class":"SymbolTableNode","kind":"Mdef","node":{".class":"FuncDef","abstract_status":0,"arg_kinds":[0],"arg_names":["self"],"dataclass_transform_spec":null,"deprecated":null,"flags":[],"fullname":"pint.util.ParserHelper.__hash__","name":"__hash__","type":null}},"__init__":{".class":"SymbolTableNode","kind":"Mdef","node":{".class":"FuncDef","abstract_status":0,"arg_kinds":[0,1,2,4],"arg_names":["self","scale","args","kwargs"],"dataclass_transform_spec":null,"deprecated":null,"flags":[],"fullname":"pint.util.ParserHelper.__init__","name":"__init__","type":{".class":"CallableType","arg_kinds":[0,1,2,4],"arg_names":["self","scale","args","kwargs"],"arg_types":["pint.util.ParserHelper",{".class":"TypeAliasType","args":[],"type_ref":"pint._typing.Scalar"},{".class":"AnyType","missing_import_name":null,"source_any":null,"type_of_any":1},{".class":"AnyType","missing_import_name":null,"source_any":null,"type_of_any":1}],"bound_args":[],"def_extras":{"first_arg":"self"},"fallback":"builtins.function","from_concatenate":false,"implicit":false,"imprecise_arg_kinds":false,"is_ellipsis_args":false,"name":"__init__ of ParserHelper","ret_type":{".class":"NoneType"},"type_guard":null,"type_is":null,"unpack_kwargs":false,"variables":[]}}},"__mul__":{".class":"SymbolTableNode","kind":"Mdef","node":{".class":"FuncDef","abstract_status":0,"arg_kinds":[0,0],"arg_names":[null,null],"dataclass_transform_spec":null,"deprecated":null,"flags":[],"fullname":"pint.util.ParserHelper.__mul__","name":"__mul__","type":null}},"__pow__":{".class":"SymbolTableNode","kind":"Mdef","node":{".class":"FuncDef","abstract_status":0,"arg_kinds":[0,0],"arg_names":[null,null],"dataclass_transform_spec":null,"deprecated":null,"flags":[],"fullname":"pint.util.ParserHelper.__pow__","name":"__pow__","type":null}},"__repr__":{".class":"SymbolTableNode","kind":"Mdef","node":{".class":"FuncDef","abstract_status":0,"arg_kinds":[0],"arg_names":[null],"dataclass_transform_spec":null,"deprecated":null,"flags":[],"fullname":"pint.util.ParserHelper.__repr__","name":"__repr__","type":null}},"__rmul__":{".class":"SymbolTableNode","kind":"Mdef","node":{".class":"Var","flags":["is_initialized_in_class","is_inferred","has_explicit_value"],"fullname":"pint.util.ParserHelper.__rmul__","name":"__rmul__","type":{".class":"CallableType","arg_kinds":[0,0],"arg_names":[null,null],"arg_types":["pint.util.ParserHelper",{".class":"AnyType","missing_import_name":null,"source_any":null,"type_of_any":1}],"bound_args":[],"def_extras":{"first_arg":"self"},"fallback":"builtins.function","from_concatenate":false,"implicit":true,"imprecise_arg_kinds":false,"is_ellipsis_args":false,"name":null,"ret_type":{".class":"AnyType","missing_import_name":null,"source_any":null,"type_of_any":1},"type_guard":null,"type_is":null,"unpack_kwargs":false,"variables":[]}}},"__rtruediv__":{".class":"SymbolTableNode","kind":"Mdef","node":{".class":"FuncDef","abstract_status":0,"arg_kinds":[0,0],"arg_names":[null,null],"dataclass_transform_spec":null,"deprecated":null,"flags":[],"fullname":"pint.util.ParserHelper.__rtruediv__","name":"__rtruediv__","type":null}},"__setstate__":{".class":"SymbolTableNode","kind":"Mdef","node":{".class":"FuncDef","abstract_status":0,"arg_kinds":[0,0],"arg_names":["self","state"],"dataclass_transform_spec":null,"deprecated":null,"flags":[],"fullname":"pint.util.ParserHelper.__setstate__","name":"__setstate__","type":null}},"__slots__":{".class":"SymbolTableNode","kind":"Mdef","node":{".class":"Var","flags":["is_initialized_in_class","is_inferred","has_explicit_value","allow_incompatible_override"],"fullname":"pint.util.ParserHelper.__slots__","name":"__slots__","type":{".class":"TupleType","implicit":false,"items":["builtins.str"],"partial_fallback":{".class":"Instance","args":[{".class":"AnyType","missing_import_name":null,"source_any":null,"type_of_any":6}],"extra_attrs":null,"type_ref":"builtins.tuple"}}}},"__str__":{".class":"SymbolTableNode","kind":"Mdef","node":{".class":"FuncDef","abstract_status":0,"arg_kinds":[0],"arg_names":[null],"dataclass_transform_spec":null,"deprecated":null,"flags":[],"fullname":"pint.util.ParserHelper.__str__","name":"__str__","type":null}},"__truediv__":{".class":"SymbolTableNode","kind":"Mdef","node":{".class":"FuncDef","abstract_status":0,"arg_kinds":[0,0],"arg_names":[null,null],"dataclass_transform_spec":null,"deprecated":null,"flags":[],"fullname":"pint.util.ParserHelper.__truediv__","name":"__truediv__","type":null}},"copy":{".class":"SymbolTableNode","kind":"Mdef","node":{".class":"FuncDef","abstract_status":0,"arg_kinds":[0],"arg_names":["self"],"dataclass_transform_spec":null,"deprecated":null,"flags":[],"fullname":"pint.util.ParserHelper.copy","name":"copy","type":null}},"eval_token":{".class":"SymbolTableNode","kind":"Mdef","node":{".class":"Decorator","func":{".class":"FuncDef","abstract_status":0,"arg_kinds":[0,0,1],"arg_names":["cls","token","non_int_type"],"dataclass_transform_spec":null,"deprecated":null,"flags":["is_class","is_decorated"],"fullname":"pint.util.ParserHelper.eval_token","name":"eval_token","type":{".class":"CallableType","arg_kinds":[0,0,1],"arg_names":["cls","token","non_int_type"],"arg_types":[{".class":"TypeType","item":"pint.util.ParserHelper"},{".class":"TypeAliasType","args":[],"type_ref":"tokenize.TokenInfo"},"builtins.type"],"bound_args":[],"def_extras":{"first_arg":"cls"},"fallback":"builtins.function","from_concatenate":false,"implicit":false,"imprecise_arg_kinds":false,"is_ellipsis_args":false,"name":"eval_token of ParserHelper","ret_type":{".class":"AnyType","missing_import_name":null,"source_any":null,"type_of_any":1},"type_guard":null,"type_is":null,"unpack_kwargs":false,"variables":[]}},"is_overload":false,"var":{".class":"Var","flags":["is_initialized_in_class","is_classmethod","is_ready","is_inferred"],"fullname":"pint.util.ParserHelper.eval_token","name":"eval_token","type":{".class":"CallableType","arg_kinds":[0,0,1],"arg_names":["cls","token","non_int_type"],"arg_types":[{".class":"TypeType","item":"pint.util.ParserHelper"},{".class":"TypeAliasType","args":[],"type_ref":"tokenize.TokenInfo"},"builtins.type"],"bound_args":[],"def_extras":{"first_arg":"cls"},"fallback":"builtins.function","from_concatenate":false,"implicit":false,"imprecise_arg_kinds":false,"is_ellipsis_args":false,"name":"eval_token of ParserHelper","ret_type":{".class":"AnyType","missing_import_name":null,"source_any":null,"type_of_any":1},"type_guard":null,"type_is":null,"unpack_kwargs":false,"variables":[]}}}},"from_string":{".class":"SymbolTableNode","kind":"Mdef","node":{".class":"Decorator","func":{".class":"FuncDef","abstract_status":0,"arg_kinds":[0,0,1],"arg_names":["cls","input_string","non_int_type"],"dataclass_transform_spec":null,"deprecated":null,"flags":["is_class","is_decorated"],"fullname":"pint.util.ParserHelper.from_string","name":"from_string","type":{".class":"CallableType","arg_kinds":[0,0,1],"arg_names":["cls","input_string","non_int_type"],"arg_types":[{".class":"TypeType","item":"pint.util.ParserHelper"},"builtins.str","builtins.type"],"bound_args":[],"def_extras":{"first_arg":"cls"},"fallback":"builtins.function","from_concatenate":false,"implicit":false,"imprecise_arg_kinds":false,"is_ellipsis_args":false,"name":"from_string of ParserHelper","ret_type":"pint.util.ParserHelper","type_guard":null,"type_is":null,"unpack_kwargs":false,"variables":[]}},"is_overload":false,"var":{".class":"Var","flags":["is_initialized_in_class","is_classmethod","is_ready","is_inferred"],"fullname":"pint.util.ParserHelper.from_string","name":"from_string","type":{".class":"Instance","args":["pint.util.ParserHelper"],"extra_attrs":null,"type_ref":"functools._lru_cache_wrapper"}}}},"from_word":{".class":"SymbolTableNode","kind":"Mdef","node":{".class":"Decorator","func":{".class":"FuncDef","abstract_status":0,"arg_kinds":[0,0,1],"arg_names":["cls","input_word","non_int_type"],"dataclass_transform_spec":null,"deprecated":null,"flags":["is_class","is_decorated"],"fullname":"pint.util.ParserHelper.from_word","name":"from_word","type":{".class":"CallableType","arg_kinds":[0,0,1],"arg_names":["cls","input_word","non_int_type"],"arg_types":[{".class":"TypeType","item":"pint.util.ParserHelper"},"builtins.str","builtins.type"],"bound_args":[],"def_extras":{"first_arg":"cls"},"fallback":"builtins.function","from_concatenate":false,"implicit":false,"imprecise_arg_kinds":false,"is_ellipsis_args":false,"name":"from_word of ParserHelper","ret_type":"pint.util.ParserHelper","type_guard":null,"type_is":null,"unpack_kwargs":false,"variables":[]}},"is_overload":false,"var":{".class":"Var","flags":["is_initialized_in_class","is_classmethod","is_ready","is_inferred"],"fullname":"pint.util.ParserHelper.from_word","name":"from_word","type":{".class":"CallableType","arg_kinds":[0,0,1],"arg_names":["cls","input_word","non_int_type"],"arg_types":[{".class":"TypeType","item":"pint.util.ParserHelper"},"builtins.str","builtins.type"],"bound_args":[],"def_extras":{"first_arg":"cls"},"fallback":"builtins.function","from_concatenate":false,"implicit":false,"imprecise_arg_kinds":false,"is_ellipsis_args":false,"name":"from_word of ParserHelper","ret_type":"pint.util.ParserHelper","type_guard":null,"type_is":null,"unpack_kwargs":false,"variables":[]}}}},"operate":{".class":"SymbolTableNode","kind":"Mdef","node":{".class":"FuncDef","abstract_status":0,"arg_kinds":[0,0,1,1],"arg_names":["self","items","op","cleanup"],"dataclass_transform_spec":null,"deprecated":null,"flags":[],"fullname":"pint.util.ParserHelper.operate","name":"operate","type":{".class":"CallableType","arg_kinds":[0,0,1,1],"arg_names":["self","items","op","cleanup"],"arg_types":["pint.util.ParserHelper",{".class":"AnyType","missing_import_name":null,"source_any":null,"type_of_any":1},{".class":"AnyType","missing_import_name":null,"source_any":null,"type_of_any":1},"builtins.bool"],"bound_args":[],"def_extras":{"first_arg":"self"},"fallback":"builtins.function","from_concatenate":false,"implicit":false,"imprecise_arg_kinds":false,"is_ellipsis_args":false,"name":"operate of ParserHelper","ret_type":{".class":"AnyType","missing_import_name":null,"source_any":null,"type_of_any":1},"type_guard":null,"type_is":null,"unpack_kwargs":false,"variables":[]}}},"scale":{".class":"SymbolTableNode","kind":"Mdef","node":{".class":"Var","flags":["is_initialized_in_class","is_ready"],"fullname":"pint.util.ParserHelper.scale","name":"scale","type":{".class":"TypeAliasType","args":[],"type_ref":"pint._typing.Scalar"}}}},"self_type":{".class":"TypeVarType","default":{".class":"AnyType","missing_import_name":null,"source_any":null,"type_of_any":4},"fullname":"pint.util.ParserHelper.Self","id":0,"name":"Self","namespace":"","upper_bound":"pint.util.ParserHelper","values":[],"variance":0},"slots":null,"tuple_type":null,"type_vars":[],"typeddict_type":null}},"PrettyIPython":{".class":"SymbolTableNode","kind":"Gdef","node":{".class":"TypeInfo","_promote":[],"abstract_attributes":[],"alt_promote":null,"bases":["builtins.object"],"dataclass_transform_spec":null,"declared_metaclass":null,"defn":{".class":"ClassDef","fullname":"pint.util.PrettyIPython","name":"PrettyIPython","type_vars":[]},"deletable_attributes":[],"deprecated":null,"flags":[],"fullname":"pint.util.PrettyIPython","has_param_spec_type":false,"metaclass_type":null,"metadata":{},"module_name":"pint.util","mro":["pint.util.PrettyIPython","builtins.object"],"names":{".class":"SymbolTable","_repr_html_":{".class":"SymbolTableNode","kind":"Mdef","node":{".class":"FuncDef","abstract_status":0,"arg_kinds":[0],"arg_names":["self"],"dataclass_transform_spec":null,"deprecated":null,"flags":[],"fullname":"pint.util.PrettyIPython._repr_html_","name":"_repr_html_","type":{".class":"CallableType","arg_kinds":[0],"arg_names":["self"],"arg_types":["pint.util.PrettyIPython"],"bound_args":[],"def_extras":{"first_arg":"self"},"fallback":"builtins.function","from_concatenate":false,"implicit":false,"imprecise_arg_kinds":false,"is_ellipsis_args":false,"name":"_repr_html_ of PrettyIPython","ret_type":"builtins.str","type_guard":null,"type_is":null,"unpack_kwargs":false,"variables":[]}}},"_repr_latex_":{".class":"SymbolTableNode","kind":"Mdef","node":{".class":"FuncDef","abstract_status":0,"arg_kinds":[0],"arg_names":["self"],"dataclass_transform_spec":null,"deprecated":null,"flags":[],"fullname":"pint.util.PrettyIPython._repr_latex_","name":"_repr_latex_","type":{".class":"CallableType","arg_kinds":[0],"arg_names":["self"],"arg_types":["pint.util.PrettyIPython"],"bound_args":[],"def_extras":{"first_arg":"self"},"fallback":"builtins.function","from_concatenate":false,"implicit":false,"imprecise_arg_kinds":false,"is_ellipsis_args":false,"name":"_repr_latex_ of PrettyIPython","ret_type":"builtins.str","type_guard":null,"type_is":null,"unpack_kwargs":false,"variables":[]}}},"_repr_pretty_":{".class":"SymbolTableNode","kind":"Mdef","node":{".class":"FuncDef","abstract_status":0,"arg_kinds":[0,0,0],"arg_names":["self","p","cycle"],"dataclass_transform_spec":null,"deprecated":null,"flags":[],"fullname":"pint.util.PrettyIPython._repr_pretty_","name":"_repr_pretty_","type":{".class":"CallableType","arg_kinds":[0,0,0],"arg_names":["self","p","cycle"],"arg_types":["pint.util.PrettyIPython",{".class":"AnyType","missing_import_name":null,"source_any":null,"type_of_any":1},"builtins.bool"],"bound_args":[],"def_extras":{"first_arg":"self"},"fallback":"builtins.function","from_concatenate":false,"implicit":false,"imprecise_arg_kinds":false,"is_ellipsis_args":false,"name":"_repr_pretty_ of PrettyIPython","ret_type":{".class":"AnyType","missing_import_name":null,"source_any":null,"type_of_any":1},"type_guard":null,"type_is":null,"unpack_kwargs":false,"variables":[]}}},"default_format":{".class":"SymbolTableNode","kind":"Mdef","node":{".class":"Var","flags":["is_initialized_in_class","is_ready"],"fullname":"pint.util.PrettyIPython.default_format","name":"default_format","type":"builtins.str"}}},"self_type":{".class":"TypeVarType","default":{".class":"AnyType","missing_import_name":null,"source_any":null,"type_of_any":4},"fullname":"pint.util.PrettyIPython.Self","id":0,"name":"Self","namespace":"","upper_bound":"pint.util.PrettyIPython","values":[],"variance":0},"slots":null,"tuple_type":null,"type_vars":[],"typeddict_type":null}},"QuantityOrUnitLike":{".class":"SymbolTableNode","cross_ref":"pint._typing.QuantityOrUnitLike","kind":"Gdef"},"Scalar":{".class":"SymbolTableNode","cross_ref":"pint._typing.Scalar","kind":"Gdef"},"Self":{".class":"SymbolTableNode","cross_ref":"typing.Self","kind":"Gdef"},"SharedRegistryObject":{".class":"SymbolTableNode","kind":"Gdef","node":{".class":"TypeInfo","_promote":[],"abstract_attributes":[],"alt_promote":null,"bases":["builtins.object"],"dataclass_transform_spec":null,"declared_metaclass":null,"defn":{".class":"ClassDef","fullname":"pint.util.SharedRegistryObject","name":"SharedRegistryObject","type_vars":[]},"deletable_attributes":[],"deprecated":null,"flags":[],"fullname":"pint.util.SharedRegistryObject","has_param_spec_type":false,"metaclass_type":null,"metadata":{},"module_name":"pint.util","mro":["pint.util.SharedRegistryObject","builtins.object"],"names":{".class":"SymbolTable","_REGISTRY":{".class":"SymbolTableNode","kind":"Mdef","node":{".class":"Var","flags":["is_initialized_in_class","is_classvar","is_ready"],"fullname":"pint.util.SharedRegistryObject._REGISTRY","name":"_REGISTRY","type":"pint.registry.UnitRegistry"}},"__new__":{".class":"SymbolTableNode","kind":"Mdef","node":{".class":"FuncDef","abstract_status":0,"arg_kinds":[0,2,4],"arg_names":["cls","args","kwargs"],"dataclass_transform_spec":null,"deprecated":null,"flags":["is_static"],"fullname":"pint.util.SharedRegistryObject.__new__","name":"__new__","type":null}},"_check":{".class":"SymbolTableNode","kind":"Mdef","node":{".class":"FuncDef","abstract_status":0,"arg_kinds":[0,0],"arg_names":["self","other"],"dataclass_transform_spec":null,"deprecated":null,"flags":[],"fullname":"pint.util.SharedRegistryObject._check","name":"_check","type":{".class":"CallableType","arg_kinds":[0,0],"arg_names":["self","other"],"arg_types":["pint.util.SharedRegistryObject",{".class":"AnyType","missing_import_name":null,"source_any":null,"type_of_any":2}],"bound_args":[],"def_extras":{"first_arg":"self"},"fallback":"builtins.function","from_concatenate":false,"implicit":false,"imprecise_arg_kinds":false,"is_ellipsis_args":false,"name":"_check of SharedRegistryObject","ret_type":"builtins.bool","type_guard":null,"type_is":null,"unpack_kwargs":false,"variables":[]}}},"_units":{".class":"SymbolTableNode","kind":"Mdef","node":{".class":"Var","flags":["is_initialized_in_class","is_ready"],"fullname":"pint.util.SharedRegistryObject._units","name":"_units","type":"pint.util.UnitsContainer"}}},"self_type":{".class":"TypeVarType","default":{".class":"AnyType","missing_import_name":null,"source_any":null,"type_of_any":4},"fullname":"pint.util.SharedRegistryObject.Self","id":0,"name":"Self","namespace":"","upper_bound":"pint.util.SharedRegistryObject","values":[],"variance":0},"slots":null,"tuple_type":null,"type_vars":[],"typeddict_type":null}},"T":{".class":"SymbolTableNode","kind":"Gdef","node":{".class":"TypeVarExpr","default":{".class":"AnyType","missing_import_name":null,"source_any":null,"type_of_any":4},"fullname":"pint.util.T","name":"T","upper_bound":"builtins.object","values":[],"variance":0}},"TH":{".class":"SymbolTableNode","kind":"Gdef","node":{".class":"TypeVarExpr","default":{".class":"AnyType","missing_import_name":null,"source_any":null,"type_of_any":4},"fullname":"pint.util.TH","name":"TH","upper_bound":"typing.Hashable","values":[],"variance":0}},"TT":{".class":"SymbolTableNode","kind":"Gdef","node":{".class":"TypeVarExpr","default":{".class":"AnyType","missing_import_name":null,"source_any":null,"type_of_any":4},"fullname":"pint.util.TT","name":"TT","upper_bound":"builtins.type","values":[],"variance":0}},"TYPE_CHECKING":{".class":"SymbolTableNode","cross_ref":"typing.TYPE_CHECKING","kind":"Gdef"},"TypeVar":{".class":"SymbolTableNode","cross_ref":"typing.TypeVar","kind":"Gdef"},"UnitRegistry":{".class":"SymbolTableNode","cross_ref":"pint.registry.UnitRegistry","kind":"Gdef"},"UnitsContainer":{".class":"SymbolTableNode","kind":"Gdef","node":{".class":"TypeInfo","_promote":[],"abstract_attributes":[],"alt_promote":null,"bases":[{".class":"Instance","args":["builtins.str",{".class":"TypeAliasType","args":[],"type_ref":"pint._typing.Scalar"}],"extra_attrs":null,"type_ref":"typing.Mapping"}],"dataclass_transform_spec":null,"declared_metaclass":null,"defn":{".class":"ClassDef","fullname":"pint.util.UnitsContainer","name":"UnitsContainer","type_vars":[]},"deletable_attributes":[],"deprecated":null,"flags":[],"fullname":"pint.util.UnitsContainer","has_param_spec_type":false,"metaclass_type":"abc.ABCMeta","metadata":{},"module_name":"pint.util","mro":["pint.util.UnitsContainer","typing.Mapping","typing.Collection","typing.Iterable","typing.Container","builtins.object"],"names":{".class":"SymbolTable","__contains__":{".class":"SymbolTableNode","kind":"Mdef","node":{".class":"FuncDef","abstract_status":0,"arg_kinds":[0,0],"arg_names":[null,null],"dataclass_transform_spec":null,"deprecated":null,"flags":[],"fullname":"pint.util.UnitsContainer.__contains__","name":"__contains__","type":{".class":"CallableType","arg_kinds":[0,0],"arg_names":[null,null],"arg_types":["pint.util.UnitsContainer","builtins.str"],"bound_args":[],"def_extras":{"first_arg":"self"},"fallback":"builtins.function","from_concatenate":false,"implicit":false,"imprecise_arg_kinds":false,"is_ellipsis_args":false,"name":"__contains__ of UnitsContainer","ret_type":"builtins.bool","type_guard":null,"type_is":null,"unpack_kwargs":false,"variables":[]}}},"__copy__":{".class":"SymbolTableNode","kind":"Mdef","node":{".class":"FuncDef","abstract_status":0,"arg_kinds":[0],"arg_names":["self"],"dataclass_transform_spec":null,"deprecated":null,"flags":[],"fullname":"pint.util.UnitsContainer.__copy__","name":"__copy__","type":null}},"__eq__":{".class":"SymbolTableNode","kind":"Mdef","node":{".class":"FuncDef","abstract_status":0,"arg_kinds":[0,0],"arg_names":[null,null],"dataclass_transform_spec":null,"deprecated":null,"flags":[],"fullname":"pint.util.UnitsContainer.__eq__","name":"__eq__","type":{".class":"CallableType","arg_kinds":[0,0],"arg_names":[null,null],"arg_types":["pint.util.UnitsContainer",{".class":"AnyType","missing_import_name":null,"source_any":null,"type_of_any":2}],"bound_args":[],"def_extras":{"first_arg":"self"},"fallback":"builtins.function","from_concatenate":false,"implicit":false,"imprecise_arg_kinds":false,"is_ellipsis_args":false,"name":"__eq__ of UnitsContainer","ret_type":"builtins.bool","type_guard":null,"type_is":null,"unpack_kwargs":false,"variables":[]}}},"__format__":{".class":"SymbolTableNode","kind":"Mdef","node":{".class":"FuncDef","abstract_status":0,"arg_kinds":[0,0],"arg_names":["self","spec"],"dataclass_transform_spec":null,"deprecated":null,"flags":[],"fullname":"pint.util.UnitsContainer.__format__","name":"__format__","type":{".class":"CallableType","arg_kinds":[0,0],"arg_names":["self","spec"],"arg_types":["pint.util.UnitsContainer","builtins.str"],"bound_args":[],"def_extras":{"first_arg":"self"},"fallback":"builtins.function","from_concatenate":false,"implicit":false,"imprecise_arg_kinds":false,"is_ellipsis_args":false,"name":"__format__ of UnitsContainer","ret_type":"builtins.str","type_guard":null,"type_is":null,"unpack_kwargs":false,"variables":[]}}},"__getitem__":{".class":"SymbolTableNode","kind":"Mdef","node":{".class":"FuncDef","abstract_status":0,"arg_kinds":[0,0],"arg_names":[null,null],"dataclass_transform_spec":null,"deprecated":null,"flags":[],"fullname":"pint.util.UnitsContainer.__getitem__","name":"__getitem__","type":{".class":"CallableType","arg_kinds":[0,0],"arg_names":[null,null],"arg_types":["pint.util.UnitsContainer","builtins.str"],"bound_args":[],"def_extras":{"first_arg":"self"},"fallback":"builtins.function","from_concatenate":false,"implicit":false,"imprecise_arg_kinds":false,"is_ellipsis_args":false,"name":"__getitem__ of UnitsContainer","ret_type":{".class":"TypeAliasType","args":[],"type_ref":"pint._typing.Scalar"},"type_guard":null,"type_is":null,"unpack_kwargs":false,"variables":[]}}},"__getstate__":{".class":"SymbolTableNode","kind":"Mdef","node":{".class":"FuncDef","abstract_status":0,"arg_kinds":[0],"arg_names":["self"],"dataclass_transform_spec":null,"deprecated":null,"flags":[],"fullname":"pint.util.UnitsContainer.__getstate__","name":"__getstate__","type":{".class":"CallableType","arg_kinds":[0],"arg_names":["self"],"arg_types":["pint.util.UnitsContainer"],"bound_args":[],"def_extras":{"first_arg":"self"},"fallback":"builtins.function","from_concatenate":false,"implicit":false,"imprecise_arg_kinds":false,"is_ellipsis_args":false,"name":"__getstate__ of UnitsContainer","ret_type":{".class":"TupleType","implicit":false,"items":["pint.util.udict",{".class":"TypeAliasType","args":[],"type_ref":"pint._typing.Scalar"},"builtins.type"],"partial_fallback":{".class":"Instance","args":[{".class":"AnyType","missing_import_name":null,"source_any":null,"type_of_any":6}],"extra_attrs":null,"type_ref":"builtins.tuple"}},"type_guard":null,"type_is":null,"unpack_kwargs":false,"variables":[]}}},"__hash__":{".class":"SymbolTableNode","kind":"Mdef","node":{".class":"FuncDef","abstract_status":0,"arg_kinds":[0],"arg_names":["self"],"dataclass_transform_spec":null,"deprecated":null,"flags":[],"fullname":"pint.util.UnitsContainer.__hash__","name":"__hash__","type":{".class":"CallableType","arg_kinds":[0],"arg_names":["self"],"arg_types":["pint.util.UnitsContainer"],"bound_args":[],"def_extras":{"first_arg":"self"},"fallback":"builtins.function","from_concatenate":false,"implicit":false,"imprecise_arg_kinds":false,"is_ellipsis_args":false,"name":"__hash__ of UnitsContainer","ret_type":"builtins.int","type_guard":null,"type_is":null,"unpack_kwargs":false,"variables":[]}}},"__init__":{".class":"SymbolTableNode","kind":"Mdef","node":{".class":"FuncDef","abstract_status":0,"arg_kinds":[0,2,5,4],"arg_names":["self","args","non_int_type","kwargs"],"dataclass_transform_spec":null,"deprecated":null,"flags":[],"fullname":"pint.util.UnitsContainer.__init__","name":"__init__","type":{".class":"CallableType","arg_kinds":[0,2,5,4],"arg_names":["self","args","non_int_type","kwargs"],"arg_types":["pint.util.UnitsContainer",{".class":"AnyType","missing_import_name":null,"source_any":null,"type_of_any":2},{".class":"UnionType","items":["builtins.type",{".class":"NoneType"}],"uses_pep604_syntax":true},{".class":"AnyType","missing_import_name":null,"source_any":null,"type_of_any":2}],"bound_args":[],"def_extras":{"first_arg":"self"},"fallback":"builtins.function","from_concatenate":false,"implicit":false,"imprecise_arg_kinds":false,"is_ellipsis_args":false,"name":"__init__ of UnitsContainer","ret_type":{".class":"NoneType"},"type_guard":null,"type_is":null,"unpack_kwargs":false,"variables":[]}}},"__iter__":{".class":"SymbolTableNode","kind":"Mdef","node":{".class":"FuncDef","abstract_status":0,"arg_kinds":[0],"arg_names":[null],"dataclass_transform_spec":null,"deprecated":null,"flags":[],"fullname":"pint.util.UnitsContainer.__iter__","name":"__iter__","type":{".class":"CallableType","arg_kinds":[0],"arg_names":[null],"arg_types":["pint.util.UnitsContainer"],"bound_args":[],"def_extras":{"first_arg":"self"},"fallback":"builtins.function","from_concatenate":false,"implicit":false,"imprecise_arg_kinds":false,"is_ellipsis_args":false,"name":"__iter__ of UnitsContainer","ret_type":{".class":"Instance","args":["builtins.str"],"extra_attrs":null,"type_ref":"typing.Iterator"},"type_guard":null,"type_is":null,"unpack_kwargs":false,"variables":[]}}},"__len__":{".class":"SymbolTableNode","kind":"Mdef","node":{".class":"FuncDef","abstract_status":0,"arg_kinds":[0],"arg_names":[null],"dataclass_transform_spec":null,"deprecated":null,"flags":[],"fullname":"pint.util.UnitsContainer.__len__","name":"__len__","type":{".class":"CallableType","arg_kinds":[0],"arg_names":[null],"arg_types":["pint.util.UnitsContainer"],"bound_args":[],"def_extras":{"first_arg":"self"},"fallback":"builtins.function","from_concatenate":false,"implicit":false,"imprecise_arg_kinds":false,"is_ellipsis_args":false,"name":"__len__ of UnitsContainer","ret_type":"builtins.int","type_guard":null,"type_is":null,"unpack_kwargs":false,"variables":[]}}},"__mul__":{".class":"SymbolTableNode","kind":"Mdef","node":{".class":"FuncDef","abstract_status":0,"arg_kinds":[0,0],"arg_names":[null,null],"dataclass_transform_spec":null,"deprecated":null,"flags":[],"fullname":"pint.util.UnitsContainer.__mul__","name":"__mul__","type":{".class":"CallableType","arg_kinds":[0,0],"arg_names":[null,null],"arg_types":["pint.util.UnitsContainer",{".class":"AnyType","missing_import_name":null,"source_any":null,"type_of_any":2}],"bound_args":[],"def_extras":{"first_arg":"self"},"fallback":"builtins.function","from_concatenate":false,"implicit":false,"imprecise_arg_kinds":false,"is_ellipsis_args":false,"name":"__mul__ of UnitsContainer","ret_type":{".class":"AnyType","missing_import_name":null,"source_any":null,"type_of_any":1},"type_guard":null,"type_is":null,"unpack_kwargs":false,"variables":[]}}},"__pow__":{".class":"SymbolTableNode","kind":"Mdef","node":{".class":"FuncDef","abstract_status":0,"arg_kinds":[0,0],"arg_names":[null,null],"dataclass_transform_spec":null,"deprecated":null,"flags":[],"fullname":"pint.util.UnitsContainer.__pow__","name":"__pow__","type":{".class":"CallableType","arg_kinds":[0,0],"arg_names":[null,null],"arg_types":["pint.util.UnitsContainer",{".class":"AnyType","missing_import_name":null,"source_any":null,"type_of_any":2}],"bound_args":[],"def_extras":{"first_arg":"self"},"fallback":"builtins.function","from_concatenate":false,"implicit":false,"imprecise_arg_kinds":false,"is_ellipsis_args":false,"name":"__pow__ of UnitsContainer","ret_type":{".class":"AnyType","missing_import_name":null,"source_any":null,"type_of_any":1},"type_guard":null,"type_is":null,"unpack_kwargs":false,"variables":[]}}},"__repr__":{".class":"SymbolTableNode","kind":"Mdef","node":{".class":"FuncDef","abstract_status":0,"arg_kinds":[0],"arg_names":[null],"dataclass_transform_spec":null,"deprecated":null,"flags":[],"fullname":"pint.util.UnitsContainer.__repr__","name":"__repr__","type":{".class":"CallableType","arg_kinds":[0],"arg_names":[null],"arg_types":["pint.util.UnitsContainer"],"bound_args":[],"def_extras":{"first_arg":"self"},"fallback":"builtins.function","from_concatenate":false,"implicit":false,"imprecise_arg_kinds":false,"is_ellipsis_args":false,"name":"__repr__ of UnitsContainer","ret_type":"builtins.str","type_guard":null,"type_is":null,"unpack_kwargs":false,"variables":[]}}},"__rmul__":{".class":"SymbolTableNode","kind":"Mdef","node":{".class":"Var","flags":["is_initialized_in_class","is_inferred","has_explicit_value"],"fullname":"pint.util.UnitsContainer.__rmul__","name":"__rmul__","type":{".class":"CallableType","arg_kinds":[0,0],"arg_names":[null,null],"arg_types":["pint.util.UnitsContainer",{".class":"AnyType","missing_import_name":null,"source_any":null,"type_of_any":2}],"bound_args":[],"def_extras":{"first_arg":"self"},"fallback":"builtins.function","from_concatenate":false,"implicit":false,"imprecise_arg_kinds":false,"is_ellipsis_args":false,"name":null,"ret_type":{".class":"AnyType","missing_import_name":null,"source_any":null,"type_of_any":1},"type_guard":null,"type_is":null,"unpack_kwargs":false,"variables":[]}}},"__rtruediv__":{".class":"SymbolTableNode","kind":"Mdef","node":{".class":"FuncDef","abstract_status":0,"arg_kinds":[0,0],"arg_names":[null,null],"dataclass_transform_spec":null,"deprecated":null,"flags":[],"fullname":"pint.util.UnitsContainer.__rtruediv__","name":"__rtruediv__","type":{".class":"CallableType","arg_kinds":[0,0],"arg_names":[null,null],"arg_types":["pint.util.UnitsContainer",{".class":"AnyType","missing_import_name":null,"source_any":null,"type_of_any":2}],"bound_args":[],"def_extras":{"first_arg":"self"},"fallback":"builtins.function","from_concatenate":false,"implicit":false,"imprecise_arg_kinds":false,"is_ellipsis_args":false,"name":"__rtruediv__ of UnitsContainer","ret_type":{".class":"AnyType","missing_import_name":null,"source_any":null,"type_of_any":1},"type_guard":null,"type_is":null,"unpack_kwargs":false,"variables":[]}}},"__setstate__":{".class":"SymbolTableNode","kind":"Mdef","node":{".class":"FuncDef","abstract_status":0,"arg_kinds":[0,0],"arg_names":["self","state"],"dataclass_transform_spec":null,"deprecated":null,"flags":[],"fullname":"pint.util.UnitsContainer.__setstate__","name":"__setstate__","type":{".class":"CallableType","arg_kinds":[0,0],"arg_names":["self","state"],"arg_types":["pint.util.UnitsContainer",{".class":"TupleType","implicit":false,"items":["pint.util.udict",{".class":"TypeAliasType","args":[],"type_ref":"pint._typing.Scalar"},"builtins.type"],"partial_fallback":{".class":"Instance","args":[{".class":"AnyType","missing_import_name":null,"source_any":null,"type_of_any":6}],"extra_attrs":null,"type_ref":"builtins.tuple"}}],"bound_args":[],"def_extras":{"first_arg":"self"},"fallback":"builtins.function","from_concatenate":false,"implicit":false,"imprecise_arg_kinds":false,"is_ellipsis_args":false,"name":"__setstate__ of UnitsContainer","ret_type":{".class":"AnyType","missing_import_name":null,"source_any":null,"type_of_any":1},"type_guard":null,"type_is":null,"unpack_kwargs":false,"variables":[]}}},"__slots__":{".class":"SymbolTableNode","kind":"Mdef","node":{".class":"Var","flags":["is_initialized_in_class","is_inferred","has_explicit_value","allow_incompatible_override"],"fullname":"pint.util.UnitsContainer.__slots__","name":"__slots__","type":{".class":"TupleType","implicit":false,"items":["builtins.str","builtins.str","builtins.str","builtins.str"],"partial_fallback":{".class":"Instance","args":[{".class":"AnyType","missing_import_name":null,"source_any":null,"type_of_any":6}],"extra_attrs":null,"type_ref":"builtins.tuple"}}}},"__str__":{".class":"SymbolTableNode","kind":"Mdef","node":{".class":"FuncDef","abstract_status":0,"arg_kinds":[0],"arg_names":[null],"dataclass_transform_spec":null,"deprecated":null,"flags":[],"fullname":"pint.util.UnitsContainer.__str__","name":"__str__","type":{".class":"CallableType","arg_kinds":[0],"arg_names":[null],"arg_types":["pint.util.UnitsContainer"],"bound_args":[],"def_extras":{"first_arg":"self"},"fallback":"builtins.function","from_concatenate":false,"implicit":false,"imprecise_arg_kinds":false,"is_ellipsis_args":false,"name":"__str__ of UnitsContainer","ret_type":"builtins.str","type_guard":null,"type_is":null,"unpack_kwargs":false,"variables":[]}}},"__truediv__":{".class":"SymbolTableNode","kind":"Mdef","node":{".class":"FuncDef","abstract_status":0,"arg_kinds":[0,0],"arg_names":[null,null],"dataclass_transform_spec":null,"deprecated":null,"flags":[],"fullname":"pint.util.UnitsContainer.__truediv__","name":"__truediv__","type":{".class":"CallableType","arg_kinds":[0,0],"arg_names":[null,null],"arg_types":["pint.util.UnitsContainer",{".class":"AnyType","missing_import_name":null,"source_any":null,"type_of_any":2}],"bound_args":[],"def_extras":{"first_arg":"self"},"fallback":"builtins.function","from_concatenate":false,"implicit":false,"imprecise_arg_kinds":false,"is_ellipsis_args":false,"name":"__truediv__ of UnitsContainer","ret_type":{".class":"AnyType","missing_import_name":null,"source_any":null,"type_of_any":1},"type_guard":null,"type_is":null,"unpack_kwargs":false,"variables":[]}}},"_d":{".class":"SymbolTableNode","kind":"Mdef","node":{".class":"Var","flags":["is_initialized_in_class","is_ready"],"fullname":"pint.util.UnitsContainer._d","name":"_d","type":"pint.util.udict"}},"_hash":{".class":"SymbolTableNode","kind":"Mdef","node":{".class":"Var","flags":["is_initialized_in_class","is_ready"],"fullname":"pint.util.UnitsContainer._hash","name":"_hash","type":{".class":"UnionType","items":["builtins.int",{".class":"NoneType"}],"uses_pep604_syntax":true}}},"_non_int_type":{".class":"SymbolTableNode","kind":"Mdef","node":{".class":"Var","flags":["is_initialized_in_class","is_ready"],"fullname":"pint.util.UnitsContainer._non_int_type","name":"_non_int_type","type":"builtins.type"}},"_normalize_nonfloat_value":{".class":"SymbolTableNode","kind":"Mdef","node":{".class":"FuncDef","abstract_status":0,"arg_kinds":[0,0],"arg_names":["self","value"],"dataclass_transform_spec":null,"deprecated":null,"flags":[],"fullname":"pint.util.UnitsContainer._normalize_nonfloat_value","name":"_normalize_nonfloat_value","type":{".class":"CallableType","arg_kinds":[0,0],"arg_names":["self","value"],"arg_types":["pint.util.UnitsContainer",{".class":"TypeAliasType","args":[],"type_ref":"pint._typing.Scalar"}],"bound_args":[],"def_extras":{"first_arg":"self"},"fallback":"builtins.function","from_concatenate":false,"implicit":false,"imprecise_arg_kinds":false,"is_ellipsis_args":false,"name":"_normalize_nonfloat_value of UnitsContainer","ret_type":{".class":"TypeAliasType","args":[],"type_ref":"pint._typing.Scalar"},"type_guard":null,"type_is":null,"unpack_kwargs":false,"variables":[]}}},"_one":{".class":"SymbolTableNode","kind":"Mdef","node":{".class":"Var","flags":["is_initialized_in_class","is_ready"],"fullname":"pint.util.UnitsContainer._one","name":"_one","type":{".class":"TypeAliasType","args":[],"type_ref":"pint._typing.Scalar"}}},"add":{".class":"SymbolTableNode","kind":"Mdef","node":{".class":"FuncDef","abstract_status":0,"arg_kinds":[0,0,0],"arg_names":["self","key","value"],"dataclass_transform_spec":null,"deprecated":null,"flags":[],"fullname":"pint.util.UnitsContainer.add","name":"add","type":{".class":"CallableType","arg_kinds":[0,0,0],"arg_names":["self","key","value"],"arg_types":[{".class":"TypeVarType","default":{".class":"AnyType","missing_import_name":null,"source_any":null,"type_of_any":4},"fullname":"pint.util.UnitsContainer.Self","id":0,"name":"Self","namespace":"","upper_bound":"pint.util.UnitsContainer","values":[],"variance":0},"builtins.str","numbers.Number"],"bound_args":[],"def_extras":{"first_arg":"self"},"fallback":"builtins.function","from_concatenate":false,"implicit":false,"imprecise_arg_kinds":false,"is_ellipsis_args":false,"name":"add of UnitsContainer","ret_type":{".class":"TypeVarType","default":{".class":"AnyType","missing_import_name":null,"source_any":null,"type_of_any":4},"fullname":"pint.util.UnitsContainer.Self","id":0,"name":"Self","namespace":"","upper_bound":"pint.util.UnitsContainer","values":[],"variance":0},"type_guard":null,"type_is":null,"unpack_kwargs":false,"variables":[{".class":"TypeVarType","default":{".class":"AnyType","missing_import_name":null,"source_any":null,"type_of_any":4},"fullname":"pint.util.UnitsContainer.Self","id":0,"name":"Self","namespace":"","upper_bound":"pint.util.UnitsContainer","values":[],"variance":0}]}}},"copy":{".class":"SymbolTableNode","kind":"Mdef","node":{".class":"FuncDef","abstract_status":0,"arg_kinds":[0],"arg_names":["self"],"dataclass_transform_spec":null,"deprecated":null,"flags":[],"fullname":"pint.util.UnitsContainer.copy","name":"copy","type":{".class":"CallableType","arg_kinds":[0],"arg_names":["self"],"arg_types":[{".class":"TypeVarType","default":{".class":"AnyType","missing_import_name":null,"source_any":null,"type_of_any":4},"fullname":"pint.util.UnitsContainer.Self","id":0,"name":"Self","namespace":"","upper_bound":"pint.util.UnitsContainer","values":[],"variance":0}],"bound_args":[],"def_extras":{"first_arg":"self"},"fallback":"builtins.function","from_concatenate":false,"implicit":false,"imprecise_arg_kinds":false,"is_ellipsis_args":false,"name":"copy of UnitsContainer","ret_type":{".class":"TypeVarType","default":{".class":"AnyType","missing_import_name":null,"source_any":null,"type_of_any":4},"fullname":"pint.util.UnitsContainer.Self","id":0,"name":"Self","namespace":"","upper_bound":"pint.util.UnitsContainer","values":[],"variance":0},"type_guard":null,"type_is":null,"unpack_kwargs":false,"variables":[{".class":"TypeVarType","default":{".class":"AnyType","missing_import_name":null,"source_any":null,"type_of_any":4},"fullname":"pint.util.UnitsContainer.Self","id":0,"name":"Self","namespace":"","upper_bound":"pint.util.UnitsContainer","values":[],"variance":0}]}}},"format_babel":{".class":"SymbolTableNode","kind":"Mdef","node":{".class":"FuncDef","abstract_status":0,"arg_kinds":[0,0,1,4],"arg_names":["self","spec","registry","kwspec"],"dataclass_transform_spec":null,"deprecated":null,"flags":[],"fullname":"pint.util.UnitsContainer.format_babel","name":"format_babel","type":{".class":"CallableType","arg_kinds":[0,0,1,4],"arg_names":["self","spec","registry","kwspec"],"arg_types":["pint.util.UnitsContainer","builtins.str",{".class":"AnyType","missing_import_name":null,"source_any":null,"type_of_any":1},{".class":"AnyType","missing_import_name":null,"source_any":null,"type_of_any":1}],"bound_args":[],"def_extras":{"first_arg":"self"},"fallback":"builtins.function","from_concatenate":false,"implicit":false,"imprecise_arg_kinds":false,"is_ellipsis_args":false,"name":"format_babel of UnitsContainer","ret_type":"builtins.str","type_guard":null,"type_is":null,"unpack_kwargs":false,"variables":[]}}},"remove":{".class":"SymbolTableNode","kind":"Mdef","node":{".class":"FuncDef","abstract_status":0,"arg_kinds":[0,0],"arg_names":["self","keys"],"dataclass_transform_spec":null,"deprecated":null,"flags":[],"fullname":"pint.util.UnitsContainer.remove","name":"remove","type":{".class":"CallableType","arg_kinds":[0,0],"arg_names":["self","keys"],"arg_types":[{".class":"TypeVarType","default":{".class":"AnyType","missing_import_name":null,"source_any":null,"type_of_any":4},"fullname":"pint.util.UnitsContainer.Self","id":0,"name":"Self","namespace":"","upper_bound":"pint.util.UnitsContainer","values":[],"variance":0},{".class":"Instance","args":["builtins.str"],"extra_attrs":null,"type_ref":"typing.Iterable"}],"bound_args":[],"def_extras":{"first_arg":"self"},"fallback":"builtins.function","from_concatenate":false,"implicit":false,"imprecise_arg_kinds":false,"is_ellipsis_args":false,"name":"remove of UnitsContainer","ret_type":{".class":"TypeVarType","default":{".class":"AnyType","missing_import_name":null,"source_any":null,"type_of_any":4},"fullname":"pint.util.UnitsContainer.Self","id":0,"name":"Self","namespace":"","upper_bound":"pint.util.UnitsContainer","values":[],"variance":0},"type_guard":null,"type_is":null,"unpack_kwargs":false,"variables":[{".class":"TypeVarType","default":{".class":"AnyType","missing_import_name":null,"source_any":null,"type_of_any":4},"fullname":"pint.util.UnitsContainer.Self","id":0,"name":"Self","namespace":"","upper_bound":"pint.util.UnitsContainer","values":[],"variance":0}]}}},"rename":{".class":"SymbolTableNode","kind":"Mdef","node":{".class":"FuncDef","abstract_status":0,"arg_kinds":[0,0,0],"arg_names":["self","oldkey","newkey"],"dataclass_transform_spec":null,"deprecated":null,"flags":[],"fullname":"pint.util.UnitsContainer.rename","name":"rename","type":{".class":"CallableType","arg_kinds":[0,0,0],"arg_names":["self","oldkey","newkey"],"arg_types":[{".class":"TypeVarType","default":{".class":"AnyType","missing_import_name":null,"source_any":null,"type_of_any":4},"fullname":"pint.util.UnitsContainer.Self","id":0,"name":"Self","namespace":"","upper_bound":"pint.util.UnitsContainer","values":[],"variance":0},"builtins.str","builtins.str"],"bound_args":[],"def_extras":{"first_arg":"self"},"fallback":"builtins.function","from_concatenate":false,"implicit":false,"imprecise_arg_kinds":false,"is_ellipsis_args":false,"name":"rename of UnitsContainer","ret_type":{".class":"TypeVarType","default":{".class":"AnyType","missing_import_name":null,"source_any":null,"type_of_any":4},"fullname":"pint.util.UnitsContainer.Self","id":0,"name":"Self","namespace":"","upper_bound":"pint.util.UnitsContainer","values":[],"variance":0},"type_guard":null,"type_is":null,"unpack_kwargs":false,"variables":[{".class":"TypeVarType","default":{".class":"AnyType","missing_import_name":null,"source_any":null,"type_of_any":4},"fullname":"pint.util.UnitsContainer.Self","id":0,"name":"Self","namespace":"","upper_bound":"pint.util.UnitsContainer","values":[],"variance":0}]}}},"unit_items":{".class":"SymbolTableNode","kind":"Mdef","node":{".class":"FuncDef","abstract_status":0,"arg_kinds":[0],"arg_names":["self"],"dataclass_transform_spec":null,"deprecated":null,"flags":[],"fullname":"pint.util.UnitsContainer.unit_items","name":"unit_items","type":{".class":"CallableType","arg_kinds":[0],"arg_names":["self"],"arg_types":["pint.util.UnitsContainer"],"bound_args":[],"def_extras":{"first_arg":"self"},"fallback":"builtins.function","from_concatenate":false,"implicit":false,"imprecise_arg_kinds":false,"is_ellipsis_args":false,"name":"unit_items of UnitsContainer","ret_type":{".class":"Instance","args":[{".class":"TupleType","implicit":false,"items":["builtins.str",{".class":"TypeAliasType","args":[],"type_ref":"pint._typing.Scalar"}],"partial_fallback":{".class":"Instance","args":[{".class":"AnyType","missing_import_name":null,"source_any":null,"type_of_any":6}],"extra_attrs":null,"type_ref":"builtins.tuple"}}],"extra_attrs":null,"type_ref":"typing.Iterable"},"type_guard":null,"type_is":null,"unpack_kwargs":false,"variables":[]}}}},"self_type":{".class":"TypeVarType","default":{".class":"AnyType","missing_import_name":null,"source_any":null,"type_of_any":4},"fullname":"pint.util.UnitsContainer.Self","id":0,"name":"Self","namespace":"","upper_bound":"pint.util.UnitsContainer","values":[],"variance":0},"slots":null,"tuple_type":null,"type_vars":[],"typeddict_type":null}},"__annotations__":{".class":"SymbolTableNode","kind":"Gdef","node":{".class":"Var","flags":["is_ready"],"fullname":"pint.util.__annotations__","name":"__annotations__","type":{".class":"Instance","args":["builtins.str",{".class":"AnyType","missing_import_name":null,"source_any":null,"type_of_any":6}],"extra_attrs":null,"type_ref":"builtins.dict"}}},"__doc__":{".class":"SymbolTableNode","kind":"Gdef","node":{".class":"Var","flags":["is_ready"],"fullname":"pint.util.__doc__","name":"__doc__","type":"builtins.str"}},"__file__":{".class":"SymbolTableNode","kind":"Gdef","node":{".class":"Var","flags":["is_ready"],"fullname":"pint.util.__file__","name":"__file__","type":"builtins.str"}},"__name__":{".class":"SymbolTableNode","kind":"Gdef","node":{".class":"Var","flags":["is_ready"],"fullname":"pint.util.__name__","name":"__name__","type":"builtins.str"}},"__package__":{".class":"SymbolTableNode","kind":"Gdef","node":{".class":"Var","flags":["is_ready"],"fullname":"pint.util.__package__","name":"__package__","type":"builtins.str"}},"__spec__":{".class":"SymbolTableNode","kind":"Gdef","node":{".class":"Var","flags":["is_ready"],"fullname":"pint.util.__spec__","name":"__spec__","type":"_frozen_importlib.ModuleSpec"}},"_is_dim":{".class":"SymbolTableNode","kind":"Gdef","node":{".class":"FuncDef","abstract_status":0,"arg_kinds":[0],"arg_names":["name"],"dataclass_transform_spec":null,"deprecated":null,"flags":[],"fullname":"pint.util._is_dim","name":"_is_dim","type":{".class":"CallableType","arg_kinds":[0],"arg_names":["name"],"arg_types":["builtins.str"],"bound_args":[],"def_extras":{"first_arg":null},"fallback":"builtins.function","from_concatenate":false,"implicit":false,"imprecise_arg_kinds":false,"is_ellipsis_args":false,"name":"_is_dim","ret_type":"builtins.bool","type_guard":null,"type_is":null,"unpack_kwargs":false,"variables":[]}}},"_noop":{".class":"SymbolTableNode","kind":"Gdef","node":{".class":"FuncDef","abstract_status":0,"arg_kinds":[0],"arg_names":["x"],"dataclass_transform_spec":null,"deprecated":null,"flags":[],"fullname":"pint.util._noop","name":"_noop","type":{".class":"CallableType","arg_kinds":[0],"arg_names":["x"],"arg_types":[{".class":"TypeVarType","default":{".class":"AnyType","missing_import_name":null,"source_any":null,"type_of_any":4},"fullname":"pint.util.T","id":-1,"name":"T","namespace":"pint.util._noop","upper_bound":"builtins.object","values":[],"variance":0}],"bound_args":[],"def_extras":{"first_arg":null},"fallback":"builtins.function","from_concatenate":false,"implicit":false,"imprecise_arg_kinds":false,"is_ellipsis_args":false,"name":"_noop","ret_type":{".class":"TypeVarType","default":{".class":"AnyType","missing_import_name":null,"source_any":null,"type_of_any":4},"fullname":"pint.util.T","id":-1,"name":"T","namespace":"pint.util._noop","upper_bound":"builtins.object","values":[],"variance":0},"type_guard":null,"type_is":null,"unpack_kwargs":false,"variables":[{".class":"TypeVarType","default":{".class":"AnyType","missing_import_name":null,"source_any":null,"type_of_any":4},"fullname":"pint.util.T","id":-1,"name":"T","namespace":"pint.util._noop","upper_bound":"builtins.object","values":[],"variance":0}]}}},"_pretty_exp_re":{".class":"SymbolTableNode","kind":"Gdef","node":{".class":"Var","flags":["is_inferred","has_explicit_value"],"fullname":"pint.util._pretty_exp_re","name":"_pretty_exp_re","type":{".class":"Instance","args":["builtins.str"],"extra_attrs":null,"type_ref":"re.Pattern"}}},"_pretty_table":{".class":"SymbolTableNode","kind":"Gdef","node":{".class":"Var","flags":["is_inferred","has_explicit_value"],"fullname":"pint.util._pretty_table","name":"_pretty_table","type":{".class":"Instance","args":["builtins.int","builtins.int"],"extra_attrs":null,"type_ref":"builtins.dict"}}},"_subs_re":{".class":"SymbolTableNode","kind":"Gdef","node":{".class":"Var","flags":["is_inferred","has_explicit_value"],"fullname":"pint.util._subs_re","name":"_subs_re","type":{".class":"Instance","args":[{".class":"TupleType","implicit":false,"items":[{".class":"Instance","args":["builtins.str"],"extra_attrs":null,"type_ref":"re.Pattern"},"builtins.str"],"partial_fallback":{".class":"Instance","args":[{".class":"AnyType","missing_import_name":null,"source_any":null,"type_of_any":6}],"extra_attrs":null,"type_ref":"builtins.tuple"}}],"extra_attrs":null,"type_ref":"builtins.list"}}},"_subs_re_list":{".class":"SymbolTableNode","kind":"Gdef","node":{".class":"Var","flags":["is_inferred","has_explicit_value"],"fullname":"pint.util._subs_re_list","name":"_subs_re_list","type":{".class":"Instance","args":[{".class":"TupleType","implicit":false,"items":["builtins.str","builtins.str"],"partial_fallback":{".class":"Instance","args":["builtins.str"],"extra_attrs":null,"type_ref":"builtins.tuple"}}],"extra_attrs":null,"type_ref":"builtins.list"}}},"annotations":{".class":"SymbolTableNode","cross_ref":"__future__.annotations","kind":"Gdef"},"build_eval_tree":{".class":"SymbolTableNode","cross_ref":"pint.pint_eval.build_eval_tree","kind":"Gdef"},"column_echelon_form":{".class":"SymbolTableNode","kind":"Gdef","node":{".class":"FuncDef","abstract_status":0,"arg_kinds":[0,1,1],"arg_names":["matrix","ntype","transpose_result"],"dataclass_transform_spec":null,"deprecated":null,"flags":[],"fullname":"pint.util.column_echelon_form","name":"column_echelon_form","type":{".class":"CallableType","arg_kinds":[0,1,1],"arg_names":["matrix","ntype","transpose_result"],"arg_types":[{".class":"TypeAliasType","args":[],"type_ref":"pint.util.ItMatrix"},"builtins.type","builtins.bool"],"bound_args":[],"def_extras":{"first_arg":null},"fallback":"builtins.function","from_concatenate":false,"implicit":false,"imprecise_arg_kinds":false,"is_ellipsis_args":false,"name":"column_echelon_form","ret_type":{".class":"TupleType","implicit":false,"items":[{".class":"TypeAliasType","args":[],"type_ref":"pint.util.Matrix"},{".class":"TypeAliasType","args":[],"type_ref":"pint.util.Matrix"},{".class":"Instance","args":["builtins.int"],"extra_attrs":null,"type_ref":"builtins.list"}],"partial_fallback":{".class":"Instance","args":[{".class":"AnyType","missing_import_name":null,"source_any":null,"type_of_any":6}],"extra_attrs":null,"type_ref":"builtins.tuple"}},"type_guard":null,"type_is":null,"unpack_kwargs":false,"variables":[]}}},"create_class_with_registry":{".class":"SymbolTableNode","kind":"Gdef","node":{".class":"FuncDef","abstract_status":0,"arg_kinds":[0,0],"arg_names":["registry","base_class"],"dataclass_transform_spec":null,"deprecated":null,"flags":[],"fullname":"pint.util.create_class_with_registry","name":"create_class_with_registry","type":{".class":"CallableType","arg_kinds":[0,0],"arg_names":["registry","base_class"],"arg_types":["pint.registry.UnitRegistry",{".class":"TypeType","item":{".class":"TypeVarType","default":{".class":"AnyType","missing_import_name":null,"source_any":null,"type_of_any":4},"fullname":"pint.util.TT","id":-1,"name":"TT","namespace":"pint.util.create_class_with_registry","upper_bound":"builtins.type","values":[],"variance":0}}],"bound_args":[],"def_extras":{"first_arg":null},"fallback":"builtins.function","from_concatenate":false,"implicit":false,"imprecise_arg_kinds":false,"is_ellipsis_args":false,"name":"create_class_with_registry","ret_type":{".class":"TypeType","item":{".class":"TypeVarType","default":{".class":"AnyType","missing_import_name":null,"source_any":null,"type_of_any":4},"fullname":"pint.util.TT","id":-1,"name":"TT","namespace":"pint.util.create_class_with_registry","upper_bound":"builtins.type","values":[],"variance":0}},"type_guard":null,"type_is":null,"unpack_kwargs":false,"variables":[{".class":"TypeVarType","default":{".class":"AnyType","missing_import_name":null,"source_any":null,"type_of_any":4},"fullname":"pint.util.TT","id":-1,"name":"TT","namespace":"pint.util.create_class_with_registry","upper_bound":"builtins.type","values":[],"variance":0}]}}},"find_connected_nodes":{".class":"SymbolTableNode","kind":"Gdef","node":{".class":"FuncDef","abstract_status":0,"arg_kinds":[0,0,1],"arg_names":["graph","start","visited"],"dataclass_transform_spec":null,"deprecated":null,"flags":[],"fullname":"pint.util.find_connected_nodes","name":"find_connected_nodes","type":{".class":"CallableType","arg_kinds":[0,0,1],"arg_names":["graph","start","visited"],"arg_types":[{".class":"Instance","args":[{".class":"TypeVarType","default":{".class":"AnyType","missing_import_name":null,"source_any":null,"type_of_any":4},"fullname":"pint.util.TH","id":-1,"name":"TH","namespace":"pint.util.find_connected_nodes","upper_bound":"typing.Hashable","values":[],"variance":0},{".class":"Instance","args":[{".class":"TypeVarType","default":{".class":"AnyType","missing_import_name":null,"source_any":null,"type_of_any":4},"fullname":"pint.util.TH","id":-1,"name":"TH","namespace":"pint.util.find_connected_nodes","upper_bound":"typing.Hashable","values":[],"variance":0}],"extra_attrs":null,"type_ref":"builtins.set"}],"extra_attrs":null,"type_ref":"builtins.dict"},{".class":"TypeVarType","default":{".class":"AnyType","missing_import_name":null,"source_any":null,"type_of_any":4},"fullname":"pint.util.TH","id":-1,"name":"TH","namespace":"pint.util.find_connected_nodes","upper_bound":"typing.Hashable","values":[],"variance":0},{".class":"UnionType","items":[{".class":"Instance","args":[{".class":"TypeVarType","default":{".class":"AnyType","missing_import_name":null,"source_any":null,"type_of_any":4},"fullname":"pint.util.TH","id":-1,"name":"TH","namespace":"pint.util.find_connected_nodes","upper_bound":"typing.Hashable","values":[],"variance":0}],"extra_attrs":null,"type_ref":"builtins.set"},{".class":"NoneType"}],"uses_pep604_syntax":true}],"bound_args":[],"def_extras":{"first_arg":null},"fallback":"builtins.function","from_concatenate":false,"implicit":false,"imprecise_arg_kinds":false,"is_ellipsis_args":false,"name":"find_connected_nodes","ret_type":{".class":"UnionType","items":[{".class":"Instance","args":[{".class":"TypeVarType","default":{".class":"AnyType","missing_import_name":null,"source_any":null,"type_of_any":4},"fullname":"pint.util.TH","id":-1,"name":"TH","namespace":"pint.util.find_connected_nodes","upper_bound":"typing.Hashable","values":[],"variance":0}],"extra_attrs":null,"type_ref":"builtins.set"},{".class":"NoneType"}],"uses_pep604_syntax":true},"type_guard":null,"type_is":null,"unpack_kwargs":false,"variables":[{".class":"TypeVarType","default":{".class":"AnyType","missing_import_name":null,"source_any":null,"type_of_any":4},"fullname":"pint.util.TH","id":-1,"name":"TH","namespace":"pint.util.find_connected_nodes","upper_bound":"typing.Hashable","values":[],"variance":0}]}}},"find_shortest_path":{".class":"SymbolTableNode","kind":"Gdef","node":{".class":"FuncDef","abstract_status":0,"arg_kinds":[0,0,0,1],"arg_names":["graph","start","end","path"],"dataclass_transform_spec":null,"deprecated":null,"flags":[],"fullname":"pint.util.find_shortest_path","name":"find_shortest_path","type":{".class":"CallableType","arg_kinds":[0,0,0,1],"arg_names":["graph","start","end","path"],"arg_types":[{".class":"Instance","args":[{".class":"TypeVarType","default":{".class":"AnyType","missing_import_name":null,"source_any":null,"type_of_any":4},"fullname":"pint.util.TH","id":-1,"name":"TH","namespace":"pint.util.find_shortest_path","upper_bound":"typing.Hashable","values":[],"variance":0},{".class":"Instance","args":[{".class":"TypeVarType","default":{".class":"AnyType","missing_import_name":null,"source_any":null,"type_of_any":4},"fullname":"pint.util.TH","id":-1,"name":"TH","namespace":"pint.util.find_shortest_path","upper_bound":"typing.Hashable","values":[],"variance":0}],"extra_attrs":null,"type_ref":"builtins.set"}],"extra_attrs":null,"type_ref":"builtins.dict"},{".class":"TypeVarType","default":{".class":"AnyType","missing_import_name":null,"source_any":null,"type_of_any":4},"fullname":"pint.util.TH","id":-1,"name":"TH","namespace":"pint.util.find_shortest_path","upper_bound":"typing.Hashable","values":[],"variance":0},{".class":"TypeVarType","default":{".class":"AnyType","missing_import_name":null,"source_any":null,"type_of_any":4},"fullname":"pint.util.TH","id":-1,"name":"TH","namespace":"pint.util.find_shortest_path","upper_bound":"typing.Hashable","values":[],"variance":0},{".class":"UnionType","items":[{".class":"Instance","args":[{".class":"TypeVarType","default":{".class":"AnyType","missing_import_name":null,"source_any":null,"type_of_any":4},"fullname":"pint.util.TH","id":-1,"name":"TH","namespace":"pint.util.find_shortest_path","upper_bound":"typing.Hashable","values":[],"variance":0}],"extra_attrs":null,"type_ref":"builtins.list"},{".class":"NoneType"}],"uses_pep604_syntax":true}],"bound_args":[],"def_extras":{"first_arg":null},"fallback":"builtins.function","from_concatenate":false,"implicit":false,"imprecise_arg_kinds":false,"is_ellipsis_args":false,"name":"find_shortest_path","ret_type":{".class":"AnyType","missing_import_name":null,"source_any":null,"type_of_any":1},"type_guard":null,"type_is":null,"unpack_kwargs":false,"variables":[{".class":"TypeVarType","default":{".class":"AnyType","missing_import_name":null,"source_any":null,"type_of_any":4},"fullname":"pint.util.TH","id":-1,"name":"TH","namespace":"pint.util.find_shortest_path","upper_bound":"typing.Hashable","values":[],"variance":0}]}}},"getattr_maybe_raise":{".class":"SymbolTableNode","kind":"Gdef","node":{".class":"FuncDef","abstract_status":0,"arg_kinds":[0,0],"arg_names":["obj","item"],"dataclass_transform_spec":null,"deprecated":null,"flags":[],"fullname":"pint.util.getattr_maybe_raise","name":"getattr_maybe_raise","type":{".class":"CallableType","arg_kinds":[0,0],"arg_names":["obj","item"],"arg_types":[{".class":"AnyType","missing_import_name":null,"source_any":null,"type_of_any":2},"builtins.str"],"bound_args":[],"def_extras":{"first_arg":null},"fallback":"builtins.function","from_concatenate":false,"implicit":false,"imprecise_arg_kinds":false,"is_ellipsis_args":false,"name":"getattr_maybe_raise","ret_type":{".class":"AnyType","missing_import_name":null,"source_any":null,"type_of_any":1},"type_guard":null,"type_is":null,"unpack_kwargs":false,"variables":[]}}},"infer_base_unit":{".class":"SymbolTableNode","kind":"Gdef","node":{".class":"FuncDef","abstract_status":0,"arg_kinds":[0,1],"arg_names":["unit_like","registry"],"dataclass_transform_spec":null,"deprecated":null,"flags":[],"fullname":"pint.util.infer_base_unit","name":"infer_base_unit","type":{".class":"CallableType","arg_kinds":[0,1],"arg_names":["unit_like","registry"],"arg_types":[{".class":"TypeAliasType","args":[],"type_ref":"pint._typing.QuantityOrUnitLike"},{".class":"UnionType","items":["pint.registry.UnitRegistry",{".class":"NoneType"}],"uses_pep604_syntax":true}],"bound_args":[],"def_extras":{"first_arg":null},"fallback":"builtins.function","from_concatenate":false,"implicit":false,"imprecise_arg_kinds":false,"is_ellipsis_args":false,"name":"infer_base_unit","ret_type":"pint.util.UnitsContainer","type_guard":null,"type_is":null,"unpack_kwargs":false,"variables":[]}}},"iterable":{".class":"SymbolTableNode","kind":"Gdef","node":{".class":"FuncDef","abstract_status":0,"arg_kinds":[0],"arg_names":["y"],"dataclass_transform_spec":null,"deprecated":null,"flags":[],"fullname":"pint.util.iterable","name":"iterable","type":{".class":"CallableType","arg_kinds":[0],"arg_names":["y"],"arg_types":[{".class":"AnyType","missing_import_name":null,"source_any":null,"type_of_any":2}],"bound_args":[],"def_extras":{"first_arg":null},"fallback":"builtins.function","from_concatenate":false,"implicit":false,"imprecise_arg_kinds":false,"is_ellipsis_args":false,"name":"iterable","ret_type":"builtins.bool","type_guard":null,"type_is":null,"unpack_kwargs":false,"variables":[]}}},"logger":{".class":"SymbolTableNode","kind":"Gdef","node":{".class":"Var","flags":["is_inferred","has_explicit_value"],"fullname":"pint.util.logger","name":"logger","type":"logging.Logger"}},"logging":{".class":"SymbolTableNode","cross_ref":"logging","kind":"Gdef"},"lru_cache":{".class":"SymbolTableNode","cross_ref":"functools.lru_cache","kind":"Gdef"},"math":{".class":"SymbolTableNode","cross_ref":"math","kind":"Gdef"},"matrix_apply":{".class":"SymbolTableNode","kind":"Gdef","node":{".class":"FuncDef","abstract_status":0,"arg_kinds":[0,0],"arg_names":["matrix","func"],"dataclass_transform_spec":null,"deprecated":null,"flags":[],"fullname":"pint.util.matrix_apply","name":"matrix_apply","type":{".class":"CallableType","arg_kinds":[0,0],"arg_names":["matrix","func"],"arg_types":[{".class":"TypeAliasType","args":[],"type_ref":"pint.util.ItMatrix"},{".class":"CallableType","arg_kinds":[0],"arg_names":[null],"arg_types":[{".class":"TypeAliasType","args":[],"type_ref":"pint._typing.Scalar"}],"bound_args":[],"def_extras":{},"fallback":"builtins.function","from_concatenate":false,"implicit":false,"imprecise_arg_kinds":false,"is_ellipsis_args":false,"name":null,"ret_type":{".class":"TypeAliasType","args":[],"type_ref":"pint._typing.Scalar"},"type_guard":null,"type_is":null,"unpack_kwargs":false,"variables":[]}],"bound_args":[],"def_extras":{"first_arg":null},"fallback":"builtins.function","from_concatenate":false,"implicit":false,"imprecise_arg_kinds":false,"is_ellipsis_args":false,"name":"matrix_apply","ret_type":{".class":"TypeAliasType","args":[],"type_ref":"pint.util.Matrix"},"type_guard":null,"type_is":null,"unpack_kwargs":false,"variables":[]}}},"matrix_to_string":{".class":"SymbolTableNode","kind":"Gdef","node":{".class":"FuncDef","abstract_status":0,"arg_kinds":[0,1,1,1],"arg_names":["matrix","row_headers","col_headers","fmtfun"],"dataclass_transform_spec":null,"deprecated":null,"flags":[],"fullname":"pint.util.matrix_to_string","name":"matrix_to_string","type":{".class":"CallableType","arg_kinds":[0,1,1,1],"arg_names":["matrix","row_headers","col_headers","fmtfun"],"arg_types":[{".class":"TypeAliasType","args":[],"type_ref":"pint.util.ItMatrix"},{".class":"UnionType","items":[{".class":"Instance","args":["builtins.str"],"extra_attrs":null,"type_ref":"typing.Iterable"},{".class":"NoneType"}],"uses_pep604_syntax":true},{".class":"UnionType","items":[{".class":"Instance","args":["builtins.str"],"extra_attrs":null,"type_ref":"typing.Iterable"},{".class":"NoneType"}],"uses_pep604_syntax":true},{".class":"CallableType","arg_kinds":[0],"arg_names":[null],"arg_types":[{".class":"TypeAliasType","args":[],"type_ref":"pint._typing.Scalar"}],"bound_args":[],"def_extras":{},"fallback":"builtins.function","from_concatenate":false,"implicit":false,"imprecise_arg_kinds":false,"is_ellipsis_args":false,"name":null,"ret_type":"builtins.str","type_guard":null,"type_is":null,"unpack_kwargs":false,"variables":[]}],"bound_args":[],"def_extras":{"first_arg":null},"fallback":"builtins.function","from_concatenate":false,"implicit":false,"imprecise_arg_kinds":false,"is_ellipsis_args":false,"name":"matrix_to_string","ret_type":"builtins.str","type_guard":null,"type_is":null,"unpack_kwargs":false,"variables":[]}}},"operator":{".class":"SymbolTableNode","cross_ref":"operator","kind":"Gdef"},"partial":{".class":"SymbolTableNode","cross_ref":"functools.partial","kind":"Gdef"},"pi_theorem":{".class":"SymbolTableNode","kind":"Gdef","node":{".class":"FuncDef","abstract_status":0,"arg_kinds":[0,1],"arg_names":["quantities","registry"],"dataclass_transform_spec":null,"deprecated":null,"flags":[],"fullname":"pint.util.pi_theorem","name":"pi_theorem","type":{".class":"CallableType","arg_kinds":[0,1],"arg_names":["quantities","registry"],"arg_types":[{".class":"Instance","args":["builtins.str",{".class":"AnyType","missing_import_name":null,"source_any":null,"type_of_any":2}],"extra_attrs":null,"type_ref":"builtins.dict"},{".class":"UnionType","items":["pint.registry.UnitRegistry",{".class":"NoneType"}],"uses_pep604_syntax":true}],"bound_args":[],"def_extras":{"first_arg":null},"fallback":"builtins.function","from_concatenate":false,"implicit":false,"imprecise_arg_kinds":false,"is_ellipsis_args":false,"name":"pi_theorem","ret_type":{".class":"AnyType","missing_import_name":null,"source_any":null,"type_of_any":1},"type_guard":null,"type_is":null,"unpack_kwargs":false,"variables":[]}}},"pint_eval":{".class":"SymbolTableNode","cross_ref":"pint.pint_eval","kind":"Gdef"},"re":{".class":"SymbolTableNode","cross_ref":"re","kind":"Gdef"},"sized":{".class":"SymbolTableNode","kind":"Gdef","node":{".class":"FuncDef","abstract_status":0,"arg_kinds":[0],"arg_names":["y"],"dataclass_transform_spec":null,"deprecated":null,"flags":[],"fullname":"pint.util.sized","name":"sized","type":{".class":"CallableType","arg_kinds":[0],"arg_names":["y"],"arg_types":[{".class":"AnyType","missing_import_name":null,"source_any":null,"type_of_any":2}],"bound_args":[],"def_extras":{"first_arg":null},"fallback":"builtins.function","from_concatenate":false,"implicit":false,"imprecise_arg_kinds":false,"is_ellipsis_args":false,"name":"sized","ret_type":"builtins.bool","type_guard":null,"type_is":null,"unpack_kwargs":false,"variables":[]}}},"solve_dependencies":{".class":"SymbolTableNode","kind":"Gdef","node":{".class":"FuncDef","abstract_status":0,"arg_kinds":[0],"arg_names":["dependencies"],"dataclass_transform_spec":null,"deprecated":null,"flags":[],"fullname":"pint.util.solve_dependencies","name":"solve_dependencies","type":{".class":"CallableType","arg_kinds":[0],"arg_names":["dependencies"],"arg_types":[{".class":"Instance","args":[{".class":"TypeVarType","default":{".class":"AnyType","missing_import_name":null,"source_any":null,"type_of_any":4},"fullname":"pint.util.TH","id":-1,"name":"TH","namespace":"pint.util.solve_dependencies","upper_bound":"typing.Hashable","values":[],"variance":0},{".class":"Instance","args":[{".class":"TypeVarType","default":{".class":"AnyType","missing_import_name":null,"source_any":null,"type_of_any":4},"fullname":"pint.util.TH","id":-1,"name":"TH","namespace":"pint.util.solve_dependencies","upper_bound":"typing.Hashable","values":[],"variance":0}],"extra_attrs":null,"type_ref":"builtins.set"}],"extra_attrs":null,"type_ref":"builtins.dict"}],"bound_args":[],"def_extras":{"first_arg":null},"fallback":"builtins.function","from_concatenate":false,"implicit":false,"imprecise_arg_kinds":false,"is_ellipsis_args":false,"name":"solve_dependencies","ret_type":{".class":"Instance","args":[{".class":"Instance","args":[{".class":"TypeVarType","default":{".class":"AnyType","missing_import_name":null,"source_any":null,"type_of_any":4},"fullname":"pint.util.TH","id":-1,"name":"TH","namespace":"pint.util.solve_dependencies","upper_bound":"typing.Hashable","values":[],"variance":0}],"extra_attrs":null,"type_ref":"builtins.set"},{".class":"NoneType"},{".class":"NoneType"}],"extra_attrs":null,"type_ref":"typing.Generator"},"type_guard":null,"type_is":null,"unpack_kwargs":false,"variables":[{".class":"TypeVarType","default":{".class":"AnyType","missing_import_name":null,"source_any":null,"type_of_any":4},"fullname":"pint.util.TH","id":-1,"name":"TH","namespace":"pint.util.solve_dependencies","upper_bound":"typing.Hashable","values":[],"variance":0}]}}},"string_preprocessor":{".class":"SymbolTableNode","kind":"Gdef","node":{".class":"FuncDef","abstract_status":0,"arg_kinds":[0],"arg_names":["input_string"],"dataclass_transform_spec":null,"deprecated":null,"flags":[],"fullname":"pint.util.string_preprocessor","name":"string_preprocessor","type":{".class":"CallableType","arg_kinds":[0],"arg_names":["input_string"],"arg_types":["builtins.str"],"bound_args":[],"def_extras":{"first_arg":null},"fallback":"builtins.function","from_concatenate":false,"implicit":false,"imprecise_arg_kinds":false,"is_ellipsis_args":false,"name":"string_preprocessor","ret_type":"builtins.str","type_guard":null,"type_is":null,"unpack_kwargs":false,"variables":[]}}},"to_units_container":{".class":"SymbolTableNode","kind":"Gdef","node":{".class":"FuncDef","abstract_status":0,"arg_kinds":[0,1],"arg_names":["unit_like","registry"],"dataclass_transform_spec":null,"deprecated":null,"flags":[],"fullname":"pint.util.to_units_container","name":"to_units_container","type":{".class":"CallableType","arg_kinds":[0,1],"arg_names":["unit_like","registry"],"arg_types":[{".class":"TypeAliasType","args":[],"type_ref":"pint._typing.QuantityOrUnitLike"},{".class":"UnionType","items":["pint.registry.UnitRegistry",{".class":"NoneType"}],"uses_pep604_syntax":true}],"bound_args":[],"def_extras":{"first_arg":null},"fallback":"builtins.function","from_concatenate":false,"implicit":false,"imprecise_arg_kinds":false,"is_ellipsis_args":false,"name":"to_units_container","ret_type":"pint.util.UnitsContainer","type_guard":null,"type_is":null,"unpack_kwargs":false,"variables":[]}}},"tokenize":{".class":"SymbolTableNode","cross_ref":"tokenize","kind":"Gdef"},"transpose":{".class":"SymbolTableNode","kind":"Gdef","node":{".class":"FuncDef","abstract_status":0,"arg_kinds":[0],"arg_names":["matrix"],"dataclass_transform_spec":null,"deprecated":null,"flags":[],"fullname":"pint.util.transpose","name":"transpose","type":{".class":"CallableType","arg_kinds":[0],"arg_names":["matrix"],"arg_types":[{".class":"TypeAliasType","args":[],"type_ref":"pint.util.ItMatrix"}],"bound_args":[],"def_extras":{"first_arg":null},"fallback":"builtins.function","from_concatenate":false,"implicit":false,"imprecise_arg_kinds":false,"is_ellipsis_args":false,"name":"transpose","ret_type":{".class":"TypeAliasType","args":[],"type_ref":"pint.util.Matrix"},"type_guard":null,"type_is":null,"unpack_kwargs":false,"variables":[]}}},"types":{".class":"SymbolTableNode","cross_ref":"types","kind":"Gdef"},"udict":{".class":"SymbolTableNode","kind":"Gdef","node":{".class":"TypeInfo","_promote":[],"abstract_attributes":[],"alt_promote":null,"bases":[{".class":"Instance","args":["builtins.str",{".class":"TypeAliasType","args":[],"type_ref":"pint._typing.Scalar"}],"extra_attrs":null,"type_ref":"builtins.dict"}],"dataclass_transform_spec":null,"declared_metaclass":null,"defn":{".class":"ClassDef","fullname":"pint.util.udict","name":"udict","type_vars":[]},"deletable_attributes":[],"deprecated":null,"flags":[],"fullname":"pint.util.udict","has_param_spec_type":false,"metaclass_type":"abc.ABCMeta","metadata":{},"module_name":"pint.util","mro":["pint.util.udict","builtins.dict","typing.MutableMapping","typing.Mapping","typing.Collection","typing.Iterable","typing.Container","builtins.object"],"names":{".class":"SymbolTable","__missing__":{".class":"SymbolTableNode","kind":"Mdef","node":{".class":"FuncDef","abstract_status":0,"arg_kinds":[0,0],"arg_names":["self","key"],"dataclass_transform_spec":null,"deprecated":null,"flags":[],"fullname":"pint.util.udict.__missing__","name":"__missing__","type":{".class":"CallableType","arg_kinds":[0,0],"arg_names":["self","key"],"arg_types":["pint.util.udict","builtins.str"],"bound_args":[],"def_extras":{"first_arg":"self"},"fallback":"builtins.function","from_concatenate":false,"implicit":false,"imprecise_arg_kinds":false,"is_ellipsis_args":false,"name":"__missing__ of udict","ret_type":{".class":"AnyType","missing_import_name":null,"source_any":null,"type_of_any":1},"type_guard":null,"type_is":null,"unpack_kwargs":false,"variables":[]}}},"copy":{".class":"SymbolTableNode","kind":"Mdef","node":{".class":"FuncDef","abstract_status":0,"arg_kinds":[0],"arg_names":["self"],"dataclass_transform_spec":null,"deprecated":null,"flags":[],"fullname":"pint.util.udict.copy","name":"copy","type":{".class":"CallableType","arg_kinds":[0],"arg_names":["self"],"arg_types":[{".class":"TypeVarType","default":{".class":"AnyType","missing_import_name":null,"source_any":null,"type_of_any":4},"fullname":"pint.util.udict.Self","id":0,"name":"Self","namespace":"","upper_bound":"pint.util.udict","values":[],"variance":0}],"bound_args":[],"def_extras":{"first_arg":"self"},"fallback":"builtins.function","from_concatenate":false,"implicit":false,"imprecise_arg_kinds":false,"is_ellipsis_args":false,"name":"copy of udict","ret_type":{".class":"TypeVarType","default":{".class":"AnyType","missing_import_name":null,"source_any":null,"type_of_any":4},"fullname":"pint.util.udict.Self","id":0,"name":"Self","namespace":"","upper_bound":"pint.util.udict","values":[],"variance":0},"type_guard":null,"type_is":null,"unpack_kwargs":false,"variables":[{".class":"TypeVarType","default":{".class":"AnyType","missing_import_name":null,"source_any":null,"type_of_any":4},"fullname":"pint.util.udict.Self","id":0,"name":"Self","namespace":"","upper_bound":"pint.util.udict","values":[],"variance":0}]}}}},"self_type":{".class":"TypeVarType","default":{".class":"AnyType","missing_import_name":null,"source_any":null,"type_of_any":4},"fullname":"pint.util.udict.Self","id":0,"name":"Self","namespace":"","upper_bound":"pint.util.udict","values":[],"variance":0},"slots":null,"tuple_type":null,"type_vars":[],"typeddict_type":null}}},"path":"/home/gray/git/distopf_2/.venv/lib/python3.13/site-packages/pint/util.py"}